Workbook
Name Depreciação: #REF!
Name Depreciação: #REF!
Name Depreciação: #REF!
Name Despesas_com_Marketing: #REF!
Name Despesas_com_Produtos: #REF!
Name Despesas_com_RH: #REF!
Name Despesas_com_Serviços: #REF!
Name Despesas_Não_Operacionais: #REF!
Name Despesas_Operacionais: #REF!
Name Impostos: #REF!
Name Investimentos: #REF!
Name Receitas_com_Produtos: #REF!
Name Receitas_Com_Serviços: #REF!
Name Receitas_Não_Operacionais: #REF!
Name Sal: [1]Cad3!$B$5:$B$14
Name Sal: [2]Cad3!$B$5:$B$14

Sheet MENU
E2: RESOLUÇÃO Nº 1/17 DE 5 DE JANEIRO Prestações de Contas dos Órgãos Autónomos, Sector Empresarial Público e demais Serviços e Entidades do sector Produtivo regidos pelo Plano Geral de Contabilidade.
C3: ENTIDADE:
C4: PERÍODO:
C6: 1.0 | D6: PLANO DE CONTAS E BALANCETE | E6: O Plano de Contas serve de guia para o preenchimento do Balancete, pois o mesmo está estruturado conforme a elaboração e apresentação do Balanço Patrimonial e da Demonstração de Resultados, de acordo com o estabelecido no Plano Geral de Contabilidade, aprovado pelo Decreto nº 82/2001, de 16 de Novembro, actualizado pelo Decreto Presidencial nº 180/19, de 24 de Maio, que regula a implementação do IVA.
C8: 2.0 | D8: BALANÇO PATRIMONIAL | E8: Registar os valores referentes ao Balanço Patrimonial, classificando-os em Activos (Não Corrente e Corrente), Passivo (Não Corrente e Corrente) e o Capital Próprio.
C10: 3.0 | D10: DEMONSTRAÇÃO DO RESULTADO DO EXERCÍCIO | E10: Registar os valores referentes ao resultado do exercício, classificando-os em Proveitos (Receitas) e Custos (Despesas).
C12: 4.0 | D12: GRÁFICOS DEMONSTRAÇÕES CONTÁBEIS | E12: Apresentação dos Gráficos do Balanço Patrimonial e Demonstração do Resultado do Exercício para melhor visualização
C14: 4.0 | D14: INDICADORES FINANCEIROS | E14: Análise dos principais indicadores financeiros com base nas demonstrações financeiras
C16: 5.0 | D16: AVALIAÇÃO DA CONTA | E16: Avaliação Final da Conta.
C18: 6.0 | D18: RELATÓRIO COMPLETO | E18: Relatório Completo das Demonstrações Financeiras e Indicadores Financeiros para impressão.

Sheet Plano Contas
A3: NOTA | B3: CÓDIGO | C3: CONTAS DO BALANÇO PATRIMONIAL | D3: CONTA DO PGC | E3: NATUREZA DA CONTA
B6: 1 | C6: ACTIVO
B7: 1.1 | C7: Activos não Correntes | D7: 1
B8: 1.1.1 | C8: Imobilizações corpóreas | D8: 11
B9: 1.1.1.1 | C9: Terrenos e recursos naturais | D9: 11.1 | E9: Devedora
B10: 1.1.1.2 | C10: Edifícios e outras construções | D10: 11.2 | E10: Devedora
B11: 1.1.1.3 | C11: Equipamento básico | D11: 11.3 | E11: Devedora
B12: 1.1.1.4 | C12: Equipamento de transporte | D12: 11.4 | E12: Devedora
B13: 1.1.1.5 | C13: Equipamento administrativo | D13: 11.5 | E13: Devedora
B14: 1.1.1.6 | C14: Taras e vasilhames | D14: 11.6 | E14: Devedora
B15: 1.1.1.7 | C15: Outras imobilizações corpóreas | D15: 11.9 | E15: Devedora
B16: 1.1.1.8 | C16: Imobilizado em curso | D16: 14.1 | E16: Devedora
B17: 1.1.1.9 | C17: Adiantamentos por conta de imobilizações corpóres | D17: 14.7 | E17: Devedora
B18: 1.1.1.10 | C18: Amortizações acumuladas - Imobilizações corpóreas | D18: 18.1 | E18: Credora
B19: 1.1.2 | C19: Imobilizações incorpóreas | D19: 12
B20: 1.1.2.1 | C20: Trespasses | D20: 12.1 | E20: Devedora
B21: 1.1.2.2 | C21: Despesas de desenvolvimento | D21: 12.2 | E21: Devedora
B22: 1.1.2.3 | C22: Propriedade industrial e outros direitos e contratos | D22: 12.3 | E22: Devedora
B23: 1.1.2.4 | C23: Despesas de constituição | D23: 12.4 | E23: Devedora
B24: 1.1.2.5 | C24: Outras imobilizações incorpóreas | D24: 12.9 | E24: Devedora
B25: 1.1.2.6 | C25: Adiantamentos por conta de imobilizado incorpóreo | D25: 14.8 | E25: Devedora
B26: 1.1.2.7 | C26: Amortizações acumuladas - Imobilizações incorpóreas | D26: 18.2 | E26: Credora
B27: 1.1.3 | C27: Investimentos em subsidiárias e associadas | D27: 13
B28: 1.1.3.1 | C28: Empresas subsidiárias | D28: 13.1 | E28: Devedora
B29: 1.1.3.1.1 | C29: Partes de capital | D29: 13.1.1 | E29: Devedora
B30: 1.1.3.1.2 | C30: Obrigações e outros títulos de participaçãpo | D30: 13.1.2 | E30: Devedora
B31: 1.1.3.1.3 | C31: Empréstimos | D31: 13.1.3 | E31: Devedora
B32: 1.1.3.1.4 | C32: Adiantamentos por conta | D32: 13.1.4 | E32: Devedora
B33: 1.1.3.2 | C33: Empresas associadas | D33: 13.2 | E33: Devedora
B34: 1.1.3.2.1 | C34: Partes de capital | D34: 13.2.1 | E34: Devedora
B35: 1.1.3.2.2 | C35: Obrigações e outros títulos de participaçãpo | D35: 13.2.2 | E35: Devedora
B36: 1.1.3.2.3 | C36: Empréstimos | D36: 13.2.3 | E36: Devedora
B37: 1.1.3.2.4 | C37: Adiantamentos por conta | D37: 13.2.4 | E37: Devedora
B38: 1.1.4 | C38: Outros activos financeiros
B39: 1.1.4.1 | C39: Investimentos em outras empresas | D39: 13.3 | E39: Devedora
B40: 1.1.4.2 | C40: Investimentos em imóveis | D40: 13.4 | E40: Devedora
B41: 1.1.4.3 | C41: Fundos | D41: 13.5 | E41: Devedora
B42: 1.1.4.4 | C42: Outros investimentos financeiros | D42: 13.9 | E42: Devedora
B43: 1.1.4.5 | C43: Adiantamento por conta de investimentos financeiros | D43: 14.9 | E43: Devedora
B44: 1.1.4.6 | C44: Amortizações acumuladas - Investimentos financeiros em imóveis | D44: 18.3 | E44: Credora
B45: 1.1.5 | C45: Provisões para investimentos financeiros | D45: 19
B46: 1.1.5.1 | C46: Empresas subsidiárias | D46: 19.1 | E46: Credora
B47: 1.1.5.2 | C47: Empresas associadas | D47: 19.2 | E47: Credora
B48: 1.1.5.3 | C48: Outras empresas | D48: 19.3 | E48: Credora
B49: 1.1.5.4 | C49: Fundos | D49: 19.4 | E49: Credora
B50: 1.1.5.5 | C50: Outros investimentos financeiros | D50: 19.9 | E50: Credora
B51: 1.1.6 | C51: Outros activos não correntes | E51: Devedora
B53: 1.2 | C53: Activos Correntes | D53: 2
B54: 1.2.1 | C54: Existências
B55: 1.2.1.1 | C55: Matérias-primas, subsidiárias e de consumo | D55: 22 | E55: Devedora
B56: 1.2.1.2 | C56: Produtos e trabalhos em curso | D56: 23 | E56: Devedora
B57: 1.2.1.3 | C57: Produtos acabados e intermédios | D57: 24 | E57: Devedora
B58: 1.2.1.4 | C58: Subprodutos, desperdícios, resíduos e refugos | D58: 25 | E58: Devedora
B59: 1.2.1.5 | C59: Mercadorias | D59: 26 | E59: Devedora
B60: 1.2.1.6 | C60: Matérias-primas, mercadorias e materiais em trânsito | D60: 27 | E60: Devedora
B61: 1.2.1.7 | C61: Adiantamentos por conta de compras | D61: 28 | E61: Devedora
B62: 1.2.1.8 | C62: Provisões para depreciação de existências | D62: 29 | E62: Credora
B63: 1.2.2 | C63: Contas a receber | E63: Devedora
B64: 1.2.2.1 | C64: Clientes-correntes | D64: 31.1 | E64: Devedora
B65: 1.2.2.2 | C65: Clientes - títulos a receber | D65: 31.2 | E65: Devedora
B66: 1.2.2.3 | C66: Clientes de cobrança duvidosa | D66: 31.8 | E66: Devedora
B67: 1.2.2.4 | C67: Fornecedores - saldos devedores | D67: 32.9 | E67: Devedora
B68: 1.2.2.5 | C68: Estado | D68: 34 | E68: Devedora
B69: 1.2.2.6 | C69: Participantes e participadas | D69: 35 | E69: Devedora
B70: 1.2.2.7 | C70: Pessoal | D70: 36 | E70: Devedora
B71: 1.2.2.8 | C71: Devedores - vendas de imobilizado | D71: 37.2 | E71: Devedora
B72: 1.2.2.9 | C72: Outros devedores
B73: 1.2.2.10 | C73: Provisões para cobrança duvidosa | D73: 38 | E73: Credora
C74: Provisões para clientes | D74: 38.1
C75: Provisões para saldos devedores de fornecedores | D75: 38.2 | E75: Credora
C76: Provisões para participantes e participadas | D76: 38.3 | E76: Credora
C77: Provisões para dívidas de pessoal | D77: 38.4 | E77: Credora
C78: Provisões para outros saldos a receber | D78: 38.5 | E78: Credora
B79: 1.2.3 | C79: Disponibilidades
B80: 1.2.3.1 | C80: Títulos negociáveis | D80: 41 | E80: Devedora
B81: 1.2.3.2 | C81: Saldos em bancos | E81: Devedora
B82: 1.2.3.2.1 | C82: Depósitos a prazo | D82: 42 | E82: Devedora
B83: 1.2.3.2.2 | C83: Depósitos a ordem | D83: 43 | E83: Devedora
B84: 1.2.3.2.3 | C84: Outros depósitos | D84: 44 | E84: Devedora
B85: 1.2.3.3 | C85: Caixa | D85: 45 | E85: Devedora
B86: 1.2.3.4 | C86: Conta transitória | D86: 48 | E86: Devedora
B87: 1.2.3.5 | C87: Provisões | D87: 49 | E87: Credora
B88: 1.2.4 | C88: Outros activos correntes
B89: 1.2.4.1 | C89: Proveitos a faturar - Contratos plurianuais em curso | D89: 37.3 | E89: Devedora
B90: 1.2.4.2 | C90: Proveitos a faturar - Encargos a repartir por exercícios futuros | D90: 37.4 | E90: Devedora
B91: 1.2.4.3 | C91: Outros valores a receber | D91: 37.9 | E91: Devedora
B93: 2 | C93: CAPITAL PRÓPRIO E PASSIVO
B94: 2.1 | C94: Capital Próprio | D94: 3
B95: 2.1.1 | C95: Capital
B96: 2.1.1.1 | C96: Capital | D96: 51 | E96: Credora
B97: 2.1.1.2 | C97: Acções/quotas próprias | D97: 52 | E97: Credora
B98: 2.1.1.3 | C98: Prémios de emissão | D98: 53 | E98: Credora
B99: 2.1.1.4 | C99: Prestações suplementares | D99: 54 | E99: Credora
B100: 2.1.2 | C100: Reservas
B101: 2.1.2.1 | C101: Reserva legal | D101: 55 | E101: Credora
B102: 2.1.2.2 | C102: Reservas de reavaliação | D102: 56 | E102: Credora
B103: 2.1.2.3 | C103: Reservas com fins especiais | D103: 57 | E103: Credora
B104: 2.1.2.4 | C104: Reservas livres | D104: 58 | E104: Credora
B105: 2.1.3 | C105: Resultados transitados
B106: 2.1.3.1 | C106: Transferência dos resultados do exercício anterior | D106: 81.1 | E106: Credora
...

Sheet Balancete
B3: BALANCETE INICIAL E FINAL - ANO DE 202---
B4: Valor em Kwanzas
B5: Conta | C5: Designação da Conta | D5: Movim. Débito | E5: Movim. Crédito | F5: Saldo do Ano Corrente | G5: Saldo do Ano Anterior | H5: Coluna1
B6: 1 | C6: Meios Fixos e Investimentos | D6: =D7+D35+D43+D60+D68+D86 -> 9.6280248e+09 | E6: =E7+E35+E43+E60+E68+E86 -> 6.1830743e+09 | F6: =IF(D6>0,D6-E6,D6-E6) -> 3.4449505e+09 | G6: =G7+G35+G43+G60+G68+G86 -> 0
B7: 11 | C7: Imobilizações Corpóreas | D7: =D8+D13+D17+D21+D24+D29+D32 -> 9.2928895e+09 | E7: =E8+E13+E17+E21+E24+E29+E32 -> 53258116 | F7: =IF(D7>=E7,D7-E7,D7-E7) -> 9.2396314e+09 | G7: =G8+G13+G17+G21+G24+G29+G32 -> 0
B8: 111 | C8: Terrenos e recursos naturais | D8: =SUM(D9:D12) -> 0 | E8: =SUM(E9:E12) -> 0 | F8: =IF(D8>=E8,D8-E8,D8-E8) -> 0 | G8: =SUM(G9:G12) -> 0
B9: 1111 | C9: Terrenos em bruto | F9: =IF(D9>=E9,D9-E9,D9-E9) -> 0
B10: 1112 | C10: Terrenos com arranjos | F10: =IF(D10>=E10,D10-E10,D10-E10) -> 0
B11: 1113 | C11: Subsolos | F11: =IF(D11>=E11,D11-E11,D11-E11) -> 0
B12: 1114 | C12: Terrenos com edíficios | F12: =IF(D12>=E12,D12-E12,D12-E12) -> 0
B13: 112 | C13: Edíficios e outras construções | D13: =SUM(D14:D16) -> 4.3974829e+09 | E13: =SUM(E14:E16) -> 0 | F13: =IF(D13>=E13,D13-E13,D13-E13) -> 4.3974829e+09 | G13: =SUM(G14:G16) -> 0
B14: 1121 | C14: Edíficos | D14: 4.3974829e+09 | E14: 0 | F14: =IF(D14>=E14,D14-E14,D14-E14) -> 4.3974829e+09
B15: 1122 | C15: Outras construções | F15: =IF(D15>=E15,D15-E15,D15-E15) -> 0
B16: 1123 | C16: Instalações | F16: =IF(D16>=E16,D16-E16,D16-E16) -> 0
B17: 113 | C17: Equipamento básico | D17: =SUM(D18:D20) -> 2.987458e+09 | E17: =SUM(E18:E20) -> 0 | F17: =IF(D17>=E17,D17-E17,D17-E17) -> 2.987458e+09 | G17: =SUM(G18:G20) -> 0
B18: 1131 | C18: Material industrial | D18: 2.987458e+09 | F18: =IF(D18>=E18,D18-E18,D18-E18) -> 2.987458e+09
B19: 1132 | C19: Ferramentas industriais | F19: =IF(D19>=E19,D19-E19,D19-E19) -> 0
B20: 1133 | C20: Melhoramentos em equipamentos básicos | F20: =IF(D20>=E20,D20-E20,D20-E20) -> 0
B21: 114 | C21: Equipamento de carga e transporte | D21: =SUM(D22:D23) -> 7.8204229e+08 | E21: =SUM(E22:E23) -> 0 | F21: =IF(D21>=E21,D21-E21,D21-E21) -> 7.8204229e+08 | G21: =SUM(G22:G23) -> 0
B22: 1141 | C22: Veículos pesados | D22: 7.8204229e+08 | F22: =IF(D22>=E22,D22-E22,D22-E22) -> 7.8204229e+08
B23: 1142 | C23: Veículos mistos e ligeiros | F23: =IF(D23>=E23,D23-E23,D23-E23) -> 0
B24: 115 | C24: Equipamento administrativo | D24: =SUM(D25:D28) -> 6.3292314e+08 | E24: =SUM(E25:E28) -> 0 | F24: =IF(D24>=E24,D24-E24,D24-E24) -> 6.3292314e+08 | G24: =SUM(G25:G28) -> 0
B25: 1151 | C25: Equipamento informático | D25: 6.3292314e+08 | F25: =IF(D25>=E25,D25-E25,D25-E25) -> 6.3292314e+08
B26: 1152 | C26: Equipamento Social | F26: =IF(D26>=E26,D26-E26,D26-E26) -> 0
B27: 1153 | C27: Mobiliario | F27: =IF(D27>=E27,D27-E27,D27-E27) -> 0
B28: 1154 | C28: Outros equipamentos administrativos | F28: =IF(D28>=E28,D28-E28,D28-E28) -> 0
B29: 116 | C29: Taras e vasilhame | D29: =D30+D31 -> 0 | E29: =E30+E31 -> 0 | F29: =IF(D29>=E29,D29-E29,D29-E29) -> 0 | G29: =G30+G31 -> 0
B30: 1161 | C30: Embalagens retornáveis | F30: =IF(D30>=E30,D30-E30,D30-E30) -> 0
B31: 1162 | C31: Outras taras e outras embalagens | F31: =IF(D31>=E31,D31-E31,D31-E31) -> 0
B32: 119 | C32: Outras imobilizações corpóreas | D32: =SUM(D33:D34) -> 4.9298322e+08 | E32: =SUM(E33:E34) -> 53258116 | F32: =IF(D32>=E32,D32-E32,D32-E32) -> 4.397251e+08 | G32: =SUM(G33:G34) -> 0
B33: 1191 | C33: Outras inst. e máquinas de uso especifico | D33: 4.9298322e+08 | E33: 53258116 | F33: =IF(D33>=E33,D33-E33,D33-E33) -> 4.397251e+08
B34: 1192 | C34: Outras imobilizações | F34: =IF(D34>=E34,D34-E34,D34-E34) -> 0
B35: 12 | C35: Imobilizações Incorpóreas | D35: =D36+D37+D38+D41+D42 -> 2.8187711e+08 | E35: =E36+E37+E38+E41+E42 -> 0 | F35: =IF(D35>=E35,D35-E35,D35-E35) -> 2.8187711e+08 | G35: =G36+G37+G38+G41+G42 -> 0
B36: 121 | C36: Trespasses | F36: =IF(D36>=E36,D36-E36,D36-E36) -> 0
B37: 122 | C37: Despesas de investigação e desenvolvimento | D37: 1.3370129e+08 | F37: =IF(D37>=E37,D37-E37,D37-E37) -> 1.3370129e+08
B38: 123 | C38: Propriedade industrial e outros direitos e contratos | D38: =SUM(D39:D40) -> 4887501 | E38: =SUM(E39:E40) -> 0 | F38: =IF(D38>=E38,D38-E38,D38-E38) -> 4887501 | G38: =SUM(G39:G40) -> 0
B39: 1231 | C39: Licenças informáticas diversas | F39: =IF(D39>=E39,D39-E39,D39-E39) -> 0
B40: 1232 | C40: Propriedade industrial e outros | D40: 4887501 | F40: =IF(D40>=E40,D40-E40,D40-E40) -> 4887501
B41: 124 | C41: Despesas de constituição | F41: =IF(D41>=E41,D41-E41,D41-E41) -> 0
B42: 129 | C42: Outras imobilizações incorpóreas | D42: 1.4328832e+08 | F42: =IF(D42>=E42,D42-E42,D42-E42) -> 1.4328832e+08
B43: 13 | C43: Investimentos Financeiros | D43: =D44+D49+D54 -> 0 | E43: =E44+E49+E54 -> 0 | F43: =IF(D43>=E43,D43-E43,D43-E43) -> 0 | G43: =SUM(G44:G54) -> 0
B44: 131 | C44: Empresas subsidiárias | D44: =SUM(D45:D48) -> 0 | E44: =SUM(E45:E48) -> 0 | F44: =IF(D44>=E44,D44-E44,D44-E44) -> 0 | G44: =SUM(G45:G48) -> 0
B45: 1311 | C45: Partes de capital | F45: =IF(D45>=E45,D45-E45,D45-E45) -> 0
B46: 1312 | C46: Obrigações e outros títulos de participação | F46: =IF(D46>=E46,D46-E46,D46-E46) -> 0
B47: 1313 | C47: Empréstimos | F47: =IF(D47>=E47,D47-E47,D47-E47) -> 0
B48: 1314 | C48: Adiantamentos por conta de empresas subsidiárias | F48: =IF(D48>=E48,D48-E48,D48-E48) -> 0
B49: 132 | C49: Empresas associadas | D49: =SUM(D50:D53) -> 0 | E49: =SUM(E50:E53) -> 0 | F49: =IF(D49>=E49,D49-E49,D49-E49) -> 0 | G49: =SUM(G50:G53) -> 0
B50: 1321 | C50: Partes de capital | F50: =IF(D50>=E50,D50-E50,D50-E50) -> 0
B51: 1322 | C51: Obrigações e outros títulos de participação | F51: =IF(D51>=E51,D51-E51,D51-E51) -> 0
B52: 1323 | C52: Empréstimos | F52: =IF(D52>=E52,D52-E52,D52-E52) -> 0
B53: 1324 | C53: Adiantamentos por conta de empresas subsidiárias | F53: =IF(D53>=E53,D53-E53,D53-E53) -> 0
B54: 133 | C54: Outros investimentos financeiros | D54: =SUM(D55:D59) -> 0 | E54: =SUM(E55:E59) -> 0 | F54: =IF(D54>=E54,D54-E54,D54-E54) -> 0 | G54: =SUM(G55:G59) -> 0
B55: 1331 | C55: Investimentos em outras empresas | F55: =IF(D55>=E55,D55-E55,D55-E55) -> 0
B56: 1332 | C56: Investimentos em imóveis | F56: =IF(D56>=E56,D56-E56,D56-E56) -> 0
B57: 1333 | C57: Fundos | F57: =IF(D57>=E57,D57-E57,D57-E57) -> 0
B58: 1334 | C58: Outros investimentos financeiros | F58: =IF(D58>=E58,D58-E58,D58-E58) -> 0
B59: 1335 | C59: Adiantamentos por conta de investimentos financeiros | F59: =IF(D59>=E59,D59-E59,D59-E59) -> 0
B60: 14 | C60: Imobilizações em curso | D60: =D61+SUM(D65:D67) -> 0 | E60: =E61+SUM(E65:E67) -> 0 | F60: =IF(D60>=E60,D60-E60,D60-E60) -> 0 | G60: =SUM(G62:G67) -> 0
B61: 141 | C61: Obras em curso | D61: =SUM(D62:D64) -> 0 | E61: =SUM(E62:E64) -> 0 | F61: =IF(D61>=E61,D61-E61,D61-E61) -> 0 | G61: =SUM(G62:G64) -> 0
B62: 1411 | C62: Obras em curso | F62: =IF(D62>=E62,D62-E62,D62-E62) -> 0
B63: 1412 | C63: Imobilizado por recepcionar | F63: =IF(D63>=E63,D63-E63,D63-E63) -> 0
B64: 1413 | C64: Obras em curso | F64: =IF(D64>=E64,D64-E64,D64-E64) -> 0
B65: 147 | C65: Adiantamentos por conta de imobilizações corpóreas | F65: =IF(D65>=E65,D65-E65,D65-E65) -> 0
B66: 148 | C66: Adiantamentos por conta de imobilizações incorpóreas | F66: =IF(D66>=E66,D66-E66,D66-E66) -> 0
B67: 149 | C67: Adiantamentos por conta de investimentos financeiros | F67: =IF(D67>=E67,D67-E67,D67-E67) -> 0
B68: 18 | C68: Amortizações Acumuladas | D68: =D69+D77+D83 -> 53258116 | E68: =E69+E77+E83 -> 6.1298162e+09 | F68: =IF(D68>=E68,D68-E68,D68-E68) -> -6.0765581e+09 | G68: =G69+G77+G83 -> 0
B69: 181 | C69: Imobilizações corpóreas | D69: =SUM(D70:D76) -> 53258116 | E69: =SUM(E70:E76) -> 5.869016e+09 | F69: =IF(D69>=E69,D69-E69,D69-E69) -> -5.8157579e+09 | G69: =SUM(G70:G76) -> 0
B70: 1811 | C70: Terrenos e recursos naturais | D70: 0 | F70: =IF(D70>=E70,D70-E70,D70-E70) -> 0
B71: 1812 | C71: Edíficios e outras construções | D71: 0 | E71: 1.7052554e+09 | F71: =IF(D71>=E71,D71-E71,D71-E71) -> -1.7052554e+09
B72: 1813 | C72: Equipamento básico | D72: 0 | E72: 2.5126595e+09 | F72: =IF(D72>=E72,D72-E72,D72-E72) -> -2.5126595e+09
B73: 1814 | C73: Equipamento de carga e transporte | D73: 0 | E73: 6.1876292e+08 | F73: =IF(D73>=E73,D73-E73,D73-E73) -> -6.1876292e+08
B74: 1815 | C74: Equipamento administrativo | D74: 0 | E74: 5.4314702e+08 | F74: =IF(D74>=E74,D74-E74,D74-E74) -> -5.4314702e+08
B75: 1816 | C75: Taras e vasilhame | F75: =IF(D75>=E75,D75-E75,D75-E75) -> 0
B76: 1819 | C76: Outras imobilizações corpóreas | D76: 53258116 | E76: 4.8919115e+08 | F76: =IF(D76>=E76,D76-E76,D76-E76) -> -4.3593303e+08
B77: 182 | C77: Imobilizações incorpóreas | D77: =-SUM(D78:D82) -> 0 | E77: =SUM(E78:E82) -> 2.6080022e+08 | F77: =IF(D77>=E77,D77-E77,D77-E77) -> -2.6080022e+08 | G77: =SUM(G78:G82) -> 0
B78: 1821 | C78: Trespasses | D78: 0 | F78: =IF(D78>=E78,D78-E78,D78-E78) -> 0
B79: 1822 | C79: Despesas de investigação e desenvolvimento | D79: 0 | E79: 1.3370129e+08 | F79: =IF(D79>=E79,D79-E79,D79-E79) -> -1.3370129e+08
B80: 1823 | C80: Propriedade industrial e outros direitos e contratos | D80: 0 | E80: 2742431.1 | F80: =IF(D80>=E80,D80-E80,D80-E80) -> -2742431.1
B81: 1824 | C81: Despesas de constituição | D81: 0 | F81: =IF(D81>=E81,D81-E81,D81-E81) -> 0
B82: 1829 | C82: Outras imobilizações incorpóreas | D82: 0 | E82: 1.243565e+08 | F82: =IF(D82>=E82,D82-E82,D82-E82) -> -1.243565e+08
B83: 183 | C83: Investimentos financeiros em imóveis | D83: =D84+D85 -> 0 | E83: =E84+E85 -> 0 | F83: =IF(D83>=E83,D83-E83,D83-E83) -> 0 | G83: =G84+G85 -> 0
B84: 1831 | C84: Terrenos e recursos naturais | F84: =IF(D84>=E84,D84-E84,D84-E84) -> 0
B85: 1832 | C85: Edifícios e outras construções | F85: =IF(D85>=E85,D85-E85,D85-E85) -> 0
B86: 19 | C86: Provisões para investimentos financeiros | D86: =SUM(D87:D91) -> 0 | E86: =SUM(E87:E91) -> 0 | F86: =IF(D86>=E86,D86-E86,D86-E86) -> 0 | G86: =SUM(G87:G91) -> 0
B87: 191 | C87: Empresas subsidiárias | F87: =IF(D87>=E87,D87-E87,D87-E87) -> 0
B88: 192 | C88: Empresas associadas | F88: =IF(D88>=E88,D88-E88,D88-E88) -> 0
B89: 193 | C89: Outras empresas | F89: =IF(D89>=E89,D89-E89,D89-E89) -> 0
B90: 194 | C90: Fundos | F90: =IF(D90>=E90,D90-E90,D90-E90) -> 0
B91: 199 | C91: Outros investimentos financeiros | F91: =IF(D91>=E91,D91-E91,D91-E91) -> 0
B92: 2 | C92: Existências | D92: =D93+D99+D105+D108+D112+D115+D119+D123+D126 -> 0 | E92: =E93+E99+E105+E108+E112+E115+E119+E123+E126 -> 0 | F92: =IF(D92>=E92,D92-E92,D92-E92) -> 0 | G92: =G93+G99+G105+G108+G112+G115+G119+G123-G126 -> 0
B93: 21 | C93: Compras | D93: =SUM(D94:D98) -> 0 | E93: =SUM(E94:E98) -> 0 | F93: =IF(D93>=E93,D93-E93,D93-E93) -> 0 | G93: =SUM(G94:G98) -> 0
B94: 211 | C94: Materias-primas, subsidiárias e de consumo | F94: =IF(D94>=E94,D94-E94,D94-E94) -> 0
B95: 212 | C95: Mercadorias | F95: =IF(D95>=E95,D95-E95,D95-E95) -> 0
B96: 217 | C96: Devoluções de compras | F96: =IF(D96>=E96,D96-E96,D96-E96) -> 0
B97: 218 | C97: Descontos e abatimentos em compras | F97: =IF(D97>=E97,D97-E97,D97-E97) -> 0
B98: 215 | C98: Outros materiais | F98: =IF(D98>=E98,D98-E98,D98-E98) -> 0
B99: 22 | C99: Matérias-primas, subsidiárias e de consumo | D99: =SUM(D100:D104) -> 0 | E99: =SUM(E100:E104) -> 0 | F99: =IF(D99>=E99,D99-E99,D99-E99) -> 0 | G99: =SUM(G100:G104) -> 0
B100: 221 | C100: Matérias-primas | F100: =IF(D100>=E100,D100-E100,D100-E100) -> 0
B101: 222 | C101: Matérias Subsidiárias | F101: =IF(D101>=E101,D101-E101,D101-E101) -> 0
B102: 223 | C102: Materiais diversos | F102: =IF(D102>=E102,D102-E102,D102-E102) -> 0
...

Sheet Activos Não Correntes
B2: OBS: NÃO PREENCHER OS CAMPOS EM AZUL. PREENCHIMENTO AUTOMÁTICO.
E3: Ano Corrente | G3: Ano Anterior | L3: Ano Corrente | N3: Ano Anterior
C4: 1.1 | D4: Activos Não Correntes | E4: =IF(ISERROR($E$5+$E$16+$E$26+$E$30+$E$38+$E$45+$E$55),"",$E$5+$E$16+$E$26+$E$30+$E$38+$E$45+$E$55) -> 3.4449505e+09 | G4: =IF(ISERROR($G$5+$G$16+$G$26+$G$30+$G$38+$G$45+$G$55),"",$G$5+$G$16+$G$26+$G$30+$G$38+$G$45+$G$55) -> 0 | J4: =C4 -> 1.1 | K4: Activos Não Correntes - Total
C5: 1.1.1 | D5: Imobilizações corpóreas | E5: =IF(ISERROR(SUM(E6:E15)),"",SUM(E6:E15)) -> 3.4238736e+09 | G5: =IF(ISERROR(SUM(G6:G15)),"",SUM(G6:G15)) -> 0 | J5: =C5 -> 1.1.1 | K5: =D5 -> Imobilizações corpóreas | L5: =IF(ISERROR($E$5),"",$E$5) -> 3.4238736e+09 | M5: =IF(ISERROR(L5/$P$5),"",L5/$P$5) -> 0.9938818 | N5: =IF(ISERROR($G$5),"",$G$5) -> 0 | O5: =IF(ISERROR(N5/$Q$5),"",N5/$Q$5) | P5: =IF(ISERROR(SUM($L$5:$L$13)),"",SUM($L$5:$L$13)) -> 3.4449505e+09 | Q5: =IF(ISERROR(SUM($N$5:$N$13)),"",SUM($N$5:$N$13)) -> 0
C6: 1.1.1.1 | D6: Terrenos e recursos naturais | E6: =Balancete!F8 -> 0 | F6: =IF(ISERROR(E6/$E$5),"",E6/$E$5) -> 0 | G6: =Balancete!G8 -> 0 | H6: =IF(ISERROR(G6/$G$5),"",G6/$G$5) | J6: =C16 -> 1.1.2 | K6: =D16 -> Imobilizações incorpóreas | L6: =IF(ISERROR($E$16),"",$E$16) -> 21076889 | M6: =IF(ISERROR(L6/$P$5),"",L6/$P$5) -> 0.0061181981 | N6: =IF(ISERROR($G$16),"",$G$16) -> 0 | O6: =IF(ISERROR(N6/$Q$5),"",N6/$Q$5)
C7: 1.1.1.2 | D7: Edifícios e outras construções | E7: =Balancete!F13 -> 4.3974829e+09 | F7: =IF(ISERROR(E7/$E$5),"",E7/$E$5) -> 1.284359 | G7: =Balancete!G13 -> 0 | H7: =IF(ISERROR(G7/$G$5),"",G7/$G$5) | J7: =C26 -> 1.1.3 | K7: =D26 -> Investimentos em Subsidiárias e Associadas | L7: =IF(ISERROR($E$26),"",$E$26) -> 0 | M7: =IF(ISERROR(L7/$P$5),"",L7/$P$5) -> 0 | N7: =IF(ISERROR($G$26),"",$G$26) -> 0 | O7: =IF(ISERROR(N7/$Q$5),"",N7/$Q$5)
C8: 1.1.1.3 | D8: Equipamento básico | E8: =Balancete!F17 -> 2.987458e+09 | F8: =IF(ISERROR(E8/$E$5),"",E8/$E$5) -> 0.87253747 | G8: =Balancete!G17 -> 0 | H8: =IF(ISERROR(G8/$G$5),"",G8/$G$5) | J8: =C30 -> 1.1.4 | K8: =D30 -> Outros Activos Financeiros | L8: =IF(ISERROR($E$30),"",$E$30) -> 0 | M8: =IF(ISERROR(L8/$P$5),"",L8/$P$5) -> 0 | N8: =IF(ISERROR($G$30),"",$G$30) -> 0 | O8: =IF(ISERROR(N8/$Q$5),"",N8/$Q$5)
C9: 1.1.1.4 | D9: Equipamento de transporte | E9: =Balancete!F21 -> 7.8204229e+08 | F9: =IF(ISERROR(E9/$E$5),"",E9/$E$5) -> 0.22840864 | G9: =Balancete!G21 -> 0 | H9: =IF(ISERROR(G9/$G$5),"",G9/$G$5) | J9: =C38 -> 1.1.5 | K9: =D38 -> Provisões para Investimentos Financeiros | L9: =IF(ISERROR($E$38),"",$E$38) -> 0 | M9: =IF(ISERROR(L9/$P$5),"",L9/$P$5) -> 0 | N9: =IF(ISERROR($G$38),"",$G$38) -> 0 | O9: =IF(ISERROR(N9/$Q$5),"",N9/$Q$5)
C10: 1.1.1.5 | D10: Equipamento administrativo | E10: =Balancete!F24 -> 6.3292314e+08 | F10: =IF(ISERROR(E10/$E$5),"",E10/$E$5) -> 0.18485587 | G10: =Balancete!G24 -> 0 | H10: =IF(ISERROR(G10/$G$5),"",G10/$G$5) | J10: =C45 -> 1.1.6 | K10: =D45 -> Outros Activos não Correntes | L10: =IF(ISERROR($E$45),"",$E$45) -> 0 | M10: =IF(ISERROR(L10/$P$5),"",L10/$P$5) -> 0 | N10: =IF(ISERROR($G$45),"",$G$45) -> 0 | O10: =IF(ISERROR(N10/$Q$5),"",N10/$Q$5)
C11: 1.1.1.6 | D11: Outras imobilizações corpóreas | E11: =Balancete!F32 -> 4.397251e+08 | F11: =IF(ISERROR(E11/$E$5),"",E11/$E$5) -> 0.12842913 | G11: =Balancete!G32 -> 0 | H11: =IF(ISERROR(G11/$G$5),"",G11/$G$5) | L11: =IF(ISERROR(E55),"",E55) -> 0 | M11: =IF(ISERROR(L11/$P$5),"",L11/$P$5) -> 0 | N11: =IF(ISERROR($G$55),"",$G$55) -> 0 | O11: =IF(ISERROR(N11/$Q$5),"",N11/$Q$5)
C12: 1.1.1.7 | D12: Taras e vasilhames | E12: =Balancete!F29 -> 0 | F12: =IF(ISERROR(E12/$E$5),"",E12/$E$5) -> 0 | G12: =Balancete!G29 -> 0 | H12: =IF(ISERROR(G12/$G$5),"",G12/$G$5)
C13: 1.1.1.8 | D13: Imobilizado em curso | E13: =Balancete!F61 -> 0 | F13: =IF(ISERROR(E13/$E$5),"",E13/$E$5) -> 0 | G13: =Balancete!G61 -> 0 | H13: =IF(ISERROR(G13/$G$5),"",G13/$G$5)
C14: 1.1.1.9 | D14: Adiantamentos por conta de imobilizações corpóres | E14: =Balancete!F65 -> 0 | G14: =Balancete!F65 -> 0 | H14: =IF(ISERROR(G14/$G$5),"",G14/$G$5) | J14: Direitos Realizáveis a Longo Prazo
C15: 1.1.1.10 | D15: Amortizações acumuladas | E15: =Balancete!F69 -> -5.8157579e+09 | F15: =IF(ISERROR(E15/$E$5),"",E15/$E$5) -> -1.6985901 | G15: =Balancete!G69 -> 0 | H15: =IF(ISERROR(G15/$G$5),"",G15/$G$5) | J15: =C5 -> 1.1.1 | K15: =D5 -> Imobilizações corpóreas | L15: =IF(ISERROR($E$5),"",$E$5) -> 3.4238736e+09 | M15: =IF(ISERROR(L15/$L$21),"",L15/$L$21) -> 0.9938818 | N15: =IF(ISERROR($G$5),"",$G$5) -> 0 | O15: =IF(ISERROR(N15/$N$21),"",N15/$N$21)
C16: 1.1.2 | D16: Imobilizações incorpóreas | E16: =IF(ISERROR(SUM(E17:E25)),"",SUM(E17:E25)) -> 21076889 | G16: =IF(ISERROR(SUM(G17:G25)),"",SUM(G17:G25)) -> 0 | J16: =C16 -> 1.1.2 | K16: =D16 -> Imobilizações incorpóreas | L16: =IF(ISERROR($E$16),"",$E$16) -> 21076889 | M16: =IF(ISERROR(L16/$L$21),"",L16/$L$21) -> 0.0061181981 | N16: =IF(ISERROR($G$16),"",$G$16) -> 0 | O16: =IF(ISERROR(N16/$N$21),"",N16/$N$21)
C17: 1.1.2.1 | D17: Trespasses | E17: =Balancete!F36 -> 0 | F17: =IF(ISERROR(E17/$E$16),"",E17/$E$16) -> 0 | G17: =Balancete!G36 -> 0 | J17: =C26 -> 1.1.3 | K17: =D26 -> Investimentos em Subsidiárias e Associadas | L17: =IF(ISERROR($E$26),"",$E$26) -> 0 | M17: =IF(ISERROR(L17/$L$21),"",L17/$L$21) -> 0 | N17: =IF(ISERROR($G$26),"",$G$26) -> 0 | O17: =IF(ISERROR(N17/$N$21),"",N17/$N$21)
C18: 1.1.2.2 | D18: Despesas de investigação e desenvolvimento | E18: =Balancete!F37 -> 1.3370129e+08 | F18: =IF(ISERROR(E18/$E$16),"",E18/$E$16) -> 6.343502 | G18: =Balancete!G37 -> 0 | J18: =C30 -> 1.1.4 | K18: =D30 -> Outros Activos Financeiros | L18: =IF(ISERROR($E$30),"",$E$30) -> 0 | M18: =IF(ISERROR(L18/$L$21),"",L18/$L$21) -> 0 | N18: =IF(ISERROR($G$30),"",$G$30) -> 0 | O18: =IF(ISERROR(N18/$N$21),"",N18/$N$21)
C19: 1.1.2.3 | D19: Propriedade industrial e outros direitos e contratos | E19: =Balancete!F38 -> 4887501 | F19: =IF(ISERROR(E19/$E$16),"",E19/$E$16) -> 0.23188911 | G19: =Balancete!G38 -> 0 | J19: =C38 -> 1.1.5 | K19: =D38 -> Provisões para Investimentos Financeiros | L19: =IF(ISERROR($E$38),"",$E$38) -> 0 | M19: =IF(ISERROR(L19/$L$21),"",L19/$L$21) -> 0 | N19: =IF(ISERROR($G$38),"",$G$38) -> 0 | O19: =IF(ISERROR(N19/$N$21),"",N19/$N$21)
C20: 1.1.2.4 | D20: Despesas de constituição | E20: =Balancete!F41 -> 0 | F20: =IF(ISERROR(E20/$E$16),"",E20/$E$16) -> 0 | G20: =Balancete!G41 -> 0 | J20: =C45 -> 1.1.6 | K20: =D45 -> Outros Activos não Correntes | L20: =IF(ISERROR($E$45),"",$E$45) -> 0 | M20: =IF(ISERROR(L20/$L$21),"",L20/$L$21) -> 0 | N20: =IF(ISERROR($G$45),"",$G$45) -> 0 | O20: =IF(ISERROR(N20/$N$21),"",N20/$N$21)
C21: 1.1.2.5 | D21: Outras imobilizações incorpóreas | E21: =Balancete!F42 -> 1.4328832e+08 | F21: =IF(ISERROR(E21/$E$16),"",E21/$E$16) -> 6.7983617 | G21: =Balancete!G42 -> 0 | J21: Total | L21: =IF(ISERROR(SUM($L$15:$L$20)),"",SUM($L$15:$L$20)) -> 3.4449505e+09 | N21: =IF(ISERROR(SUM($N$15:$N$20)),"",SUM($N$15:$N$20)) -> 0
C22: 1.1.2.6 | D22: Adiantamentos por conta de imobilizações incorpóres | E22: =Balancete!F66 -> 0 | F22: =IF(ISERROR(E22/$E$16),"",E22/$E$16) -> 0 | G22: =Balancete!G66 -> 0
C23: 1.1.2.7 | D23: Amortizações acumuladas | E23: =Balancete!F77 -> -2.6080022e+08 | F23: =IF(ISERROR(E23/$E$16),"",E23/$E$16) -> -12.373753 | G23: =Balancete!G77 -> 0 | J23: Valor Total do Ativo Não Corrente
C24: 1.1.2.8 | F24: =IF(ISERROR(E24/$E$16),"",E24/$E$16) -> 0 | J24: Total | L24: =IF(ISERROR(SUM($L$5:$L$13)),"",SUM($L$5:$L$13)) -> 3.4449505e+09 | N24: =IF(ISERROR(SUM($N$5:$N$13)),"",SUM($N$5:$N$13)) -> 0
C25: 1.1.2.9 | F25: =IF(ISERROR(E25/$E$16),"",E25/$E$16) -> 0
C26: 1.1.3 | D26: Investimentos em Subsidiárias e Associadas | E26: =IF(ISERROR(SUM(E27:E29)),"",SUM(E27:E29)) -> 0
C27: 1.1.3.1 | D27: Empresas subsidiárias | E27: =Balancete!F44 -> 0 | F27: =IF(ISERROR(E27/$E$26),"",E27/$E$26) | G27: =Balancete!G44 -> 0
C28: 1.1.3.2 | D28: Empresas associadas | E28: =Balancete!F49 -> 0 | F28: =IF(ISERROR(E28/$E$26),"",E28/$E$26) | G28: =Balancete!G49 -> 0
C29: 1.1.3.3 | F29: =IF(ISERROR(E29/$E$26),"",E29/$E$26)
C30: 1.1.4 | D30: Outros Activos Financeiros | E30: =IF(ISERROR(SUM(E31:E37)),"",SUM(E31:E37)) -> 0
C31: 1.1.4.1 | D31: Investimentos em outras empresas | E31: =Balancete!F55 -> 0 | F31: =IF(ISERROR(E31/$E$30),"",E31/$E$30) | G31: =Balancete!G55 -> 0
C32: 1.1.4.2 | D32: Investimentos em imóveis | E32: =Balancete!F56 -> 0 | F32: =IF(ISERROR(E32/$E$30),"",E32/$E$30) | G32: =Balancete!G56 -> 0
C33: 1.1.4.3 | D33: Fundos - Obrigações | E33: =Balancete!F57 -> 0 | F33: =IF(ISERROR(E33/$E$30),"",E33/$E$30) | G33: =Balancete!G57 -> 0
C34: 1.1.4.4 | D34: Outros investimentos financeiros | E34: =Balancete!F58 -> 0 | F34: =IF(ISERROR(E34/$E$30),"",E34/$E$30) | G34: =Balancete!G58 -> 0
C35: 1.1.4.5 | D35: Adiantamento por conta de investimentos financeiros | E35: =Balancete!F90 -> 0 | F35: =IF(ISERROR(E35/$E$30),"",E35/$E$30) | G35: =Balancete!G90 -> 0
C36: 1.1.4.6 | D36: Amortizações acumuladas - imóveis | E36: =Balancete!F83 -> 0 | F36: =IF(ISERROR(E36/$E$30),"",E36/$E$30) | G36: =Balancete!G83 -> 0
C37: 1.1.4.9 | F37: =IF(ISERROR(E37/$E$30),"",E37/$E$30)
C38: 1.1.5 | D38: Provisões para Investimentos Financeiros | E38: =IF(ISERROR(SUM(E39:E44)),"",SUM(E39:E44)) -> 0
C39: 1.1.5.1 | D39: Empresas subsidiárias | E39: =Balancete!F87 -> 0 | F39: =IF(ISERROR(E39/$E$38),"",E39/$E$38) | G39: =Balancete!G87 -> 0
C40: 1.1.5.2 | D40: Empresas associadas | E40: =Balancete!F88 -> 0 | F40: =IF(ISERROR(E40/$E$38),"",E40/$E$38) | G40: =Balancete!G88 -> 0
C41: 1.1.5.3 | D41: Outras empresas | E41: =Balancete!F89 -> 0 | F41: =IF(ISERROR(E41/$E$38),"",E41/$E$38) | G41: =Balancete!G89 -> 0
C42: 1.1.5.4 | D42: Fundos | E42: =Balancete!F90 -> 0 | F42: =IF(ISERROR(E42/$E$38),"",E42/$E$38) | G42: =Balancete!G90 -> 0
C43: 1.1.5.5 | D43: Outros investimentos financeiros | E43: =Balancete!F91 -> 0 | F43: =IF(ISERROR(E43/$E$38),"",E43/$E$38) | G43: =Balancete!G91 -> 0
C44: 1.1.5.9 | F44: =IF(ISERROR(E44/$E$38),"",E44/$E$38)
C45: 1.1.6 | D45: Outros Activos não Correntes

Sheet Activos Correntes
B2: OBS: NÃO PREENCHER OS CAMPOS EM AZUL. PREENCHIMENTO AUTOMÁTICO.
E3: Ano Corrente | G3: Ano Anterior | L3: Ano Corrente | N3: Ano Anterior
C4: 1.2 | D4: Activos Correntes (Bens e Direitos) | E4: =IF(ISERROR($E$5+$E$15+$E$27+$E$35+$E$50),"",$E$5+$E$15+$E$27+$E$35+$E$50) -> 1.5650931e+09 | G4: =IF(ISERROR($G$5+$G$15+$G$27+$G$35+$G$50),"",$G$5+$G$15+$G$27+$G$35+$G$50) -> 0 | J4: =C4 -> 1.2 | K4: Contas dos Activos Correntes - Total
C5: 1.2.1 | D5: Existências | E5: =IF(ISERROR(SUM(E6:E14)),"",SUM(E6:E14)) -> 0 | G5: =IF(ISERROR(SUM(G6:G14)),"",SUM(G6:G14)) -> 0 | J5: =C5 -> 1.2.1 | K5: =D5 -> Existências | L5: =IF(ISERROR($E$5),"",$E$5) -> 0 | M5: =IF(ISERROR(L5/$P$5),"",L5/$P$5) -> 0 | N5: =IF(ISERROR($G$5),"",$G$5) -> 0 | P5: =IF(ISERROR(SUM($L$5:$L$13)),"",SUM($L$5:$L$13)) -> 1.5650931e+09
C6: 1.2.1.1 | D6: Matérias-primas, subsidiárias e de consumo | E6: =Balancete!F99 -> 0 | F6: =IF(ISERROR(E6/$E$5),"",E6/$E$5) | G6: =Balancete!G99 -> 0 | J6: =C15 -> 1.2.2 | K6: =D15 -> Contas a Receber | L6: =IF(ISERROR($E$15),"",$E$15) -> 1.3402124e+09 | M6: =IF(ISERROR(L6/$P$5),"",L6/$P$5) -> 0.85631482 | N6: =IF(ISERROR($G$15),"",$G$15) -> 0
C7: 1.2.1.2 | D7: Produtos e trabalhos em curso | E7: =Balancete!F105 -> 0 | F7: =IF(ISERROR(E7/$E$5),"",E7/$E$5) | G7: =Balancete!G105 -> 0 | J7: =C27 -> 1.2.3 | K7: =D27 -> Disponibilidades | L7: =IF(ISERROR($E$27),"",$E$27) -> 52657493 | M7: =IF(ISERROR(L7/$P$5),"",L7/$P$5) -> 0.033644958 | N7: =IF(ISERROR($G$27),"",$G$27) -> 0
C8: 1.2.1.3 | D8: Produtos acabados e intermédios | E8: =Balancete!F130 -> 0 | F8: =IF(ISERROR(E8/$E$5),"",E8/$E$5) | G8: =Balancete!G130 -> 0 | J8: =C35 -> 1.2.4 | K8: =D35 -> Outros activos correntes | L8: =IF(ISERROR($E$35),"",$E$35) -> 1.7222319e+08 | M8: =IF(ISERROR(L8/$P$5),"",L8/$P$5) -> 0.11004022 | N8: =IF(ISERROR($G$35),"",$G$35) -> 0
C9: 1.2.1.4 | D9: Subprodutos, desperdícios, resíduos e refugos | E9: =Balancete!F112 -> 0 | F9: =IF(ISERROR(E9/$E$5),"",E9/$E$5) | G9: =Balancete!G112 -> 0 | J9: =C40 -> 1.2.5 | K9: =D40 -> Estado | L9: 0 | M9: =IF(ISERROR(L9/$P$5),"",L9/$P$5) -> 0 | N9: 0
C10: 1.2.1.5 | D10: Mercadorias | E10: =Balancete!F115 -> 0 | F10: =IF(ISERROR(E10/$E$5),"",E10/$E$5) | G10: =Balancete!G115 -> 0 | L10: =IF(ISERROR($E$50),"",$E$50) -> 0 | M10: =IF(ISERROR(L10/$P$5),"",L10/$P$5) -> 0 | N10: =IF(ISERROR($G$50),"",$G$50) -> 0
C11: 1.2.1.6 | D11: Matérias-primas, mercadorias e materiais em trânsito | E11: =Balancete!F119 -> 0 | F11: =IF(ISERROR(E11/$E$5),"",E11/$E$5) | G11: =Balancete!G119 -> 0 | L11: =IF(ISERROR(#REF!),"",#REF!) | M11: =IF(ISERROR(L11/$P$5),"",L11/$P$5) | N11: =IF(ISERROR(#REF!),"",#REF!)
C12: 1.2.1.7 | D12: Adiantamentos por conta de de compras | E12: =Balancete!F123 -> 0 | F12: =IF(ISERROR(E12/$E$5),"",E12/$E$5) | G12: =Balancete!G123 -> 0 | L12: =IF(ISERROR(#REF!),"",#REF!) | M12: =IF(ISERROR(L12/$P$5),"",L12/$P$5) | N12: =IF(ISERROR(#REF!),"",#REF!)
C13: 1.2.1.8 | D13: Provisão para depreciação de existências | E13: =Balancete!F126 -> 0 | F13: =IF(ISERROR(E13/$E$5),"",E13/$E$5) | G13: =Balancete!G126 -> 0 | L13: =IF(ISERROR(#REF!),"",#REF!) | M13: =IF(ISERROR(L13/$P$5),"",L13/$P$5) | N13: =IF(ISERROR(#REF!),"",#REF!)
C14: 1.2.1.9 | F14: =IF(ISERROR(E14/$E$5),"",E14/$E$5)
C15: 1.2.2 | D15: Contas a Receber | E15: =IF(ISERROR(SUM(E16:E26)),"",SUM(E16:E26)) -> 1.3402124e+09 | G15: =IF(ISERROR(SUM(G16:G26)),"",SUM(G16:G26)) -> 0 | J15: Direitos Realizáveis a Curto Prazo
C16: 1.2.2.1 | D16: Clientes-correntes | E16: =Balancete!F135 -> 3.7189837e+08 | F16: =IF(ISERROR(E16/$E$15),"",E16/$E$15) -> 0.2774921 | G16: =Balancete!G135 -> 0 | J16: =J5 -> 1.2.1 | K16: =K5 -> Existências | L16: =IF(ISERROR($E$5),"",$E$5) -> 0 | M16: =IF(ISERROR(L16/$L$19),"",L16/$L$19) -> 0 | N16: =IF(ISERROR($G$5),"",$G$5) -> 0
C17: 1.2.2.2 | D17: Clientes - títulos a receber | E17: =Balancete!F136 -> 0 | F17: =IF(ISERROR(E17/$E$15),"",E17/$E$15) -> 0 | G17: =Balancete!G136 -> 0 | J17: =J6 -> 1.2.2 | K17: =K6 -> Contas a Receber | L17: =IF(ISERROR($E$15),"",$E$15) -> 1.3402124e+09 | M17: =IF(ISERROR(L17/$L$19),"",L17/$L$19) -> 0.96219497 | N17: =IF(ISERROR($G$15),"",$G$15) -> 0
C18: 1.2.2.3 | D18: Clientes de cobrança duvidosa | E18: =Balancete!F138 -> 2.4283678e+08 | F18: =IF(ISERROR(E18/$E$15),"",E18/$E$15) -> 0.18119275 | G18: =Balancete!G138 -> 0 | J18: =J7 -> 1.2.3 | K18: =D27 -> Disponibilidades | L18: =IF(ISERROR($E$27),"",$E$27) -> 52657493 | M18: =IF(ISERROR(L18/$L$19),"",L18/$L$19) -> 0.037805032 | N18: =IF(ISERROR($G$27),"",$G$27) -> 0
C19: 1.2.2.4 | D19: Fornecedores - saldos devedores | E19: =Balancete!F144 -> 2.6343583e+08 | F19: =IF(ISERROR(E19/$E$15),"",E19/$E$15) -> 0.19656274 | G19: =Balancete!G144 -> 0 | J19: Total | L19: =IF(ISERROR(SUM($L$16:$L$18)),"",SUM($L$16:$L$18)) -> 1.3928699e+09 | N19: =IF(ISERROR(SUM($N$16:$N$18)),"",SUM($N$16:$N$18)) -> 0
C20: 1.2.2.5 | D20: Estado | E20: =E40 -> 6.4883625e+08 | F20: =IF(ISERROR(E20/$E$15),"",E20/$E$15) -> 0.4841294 | G20: =G40 -> 0
C21: 1.2.2.6 | D21: Participantes e participadas | E21: =Balancete!F177 -> 0 | F21: =IF(ISERROR(E21/$E$15),"",E21/$E$15) -> 0 | G21: =Balancete!G177 -> 0 | J21: Valor Total do Activo Corrente
C22: 1.2.2.7 | D22: Pessoal | E22: =Balancete!F180 -> 56041998 | F22: =IF(ISERROR(E22/$E$15),"",E22/$E$15) -> 0.041815757 | G22: =Balancete!G190+Balancete!G184 -> 0 | J22: Total | L22: =IF(ISERROR(SUM($L$5:$L$13)),"",SUM($L$5:$L$13)) -> 1.5650931e+09 | N22: =IF(ISERROR(SUM($N$5:$N$13)),"",SUM($N$5:$N$13)) -> 0
C23: 1.2.2.8 | D23: Devedores - venda de imobilizado | E23: =Balancete!F196 -> 0 | F23: =IF(ISERROR(E23/$E$15),"",E23/$E$15) -> 0 | G23: =Balancete!G196 -> 0
C24: 1.2.2.9 | D24: Outros devedores | E24: 0 | F24: =IF(ISERROR(E24/$E$15),"",E24/$E$15) -> 0 | G24: 0
C25: 1.2.2.10 | D25: Provisões para cobrança duvidosa | E25: =Balancete!F226 -> -2.4283678e+08 | F25: =IF(ISERROR(E25/$E$15),"",E25/$E$15) -> -0.18119275 | G25: =Balancete!G226 -> 0
C27: 1.2.3 | D27: Disponibilidades | E27: =IF(ISERROR(SUM(E28:E34)),"",SUM(E28:E34)) -> 52657493 | G27: =IF(ISERROR(SUM(G28:G34)),"",SUM(G28:G34)) -> 0
C28: 1.2.3.1 | D28: Títulos negociáveis | E28: =Balancete!F245 -> 0 | F28: =IF(ISERROR(E28/$E$27),"",E28/$E$27) -> 0 | G28: =Balancete!G245 -> 0
C29: 1.2.3.2 | D29: Saldos em bancos - a prazo | E29: =Balancete!F249 -> 2400000 | F29: =IF(ISERROR(E29/$E$27),"",E29/$E$27) -> 0.045577559 | G29: =Balancete!G249 -> 0
C30: 1.2.3.3 | D30: Saldos em bancos - a ordem | E30: =Balancete!F252 -> 49104474 | F30: =IF(ISERROR(E30/$E$27),"",E30/$E$27) -> 0.93252587 | G30: =Balancete!G252 -> 0
C31: 1.2.3.4 | D31: Caixa | E31: =Balancete!F255 -> 1153018.6 | F31: =IF(ISERROR(E31/$E$27),"",E31/$E$27) -> 0.021896572 | G31: =Balancete!G255 -> 0
C32: 1.2.3.5 | D32: Provisões | E32: =Balancete!F264 -> 0 | F32: =IF(ISERROR(E32/$E$27),"",E32/$E$27) -> 0 | G32: =Balancete!G264 -> 0
C33: 1.2.3.6 | D33: Conta transitória | E33: =Balancete!F261 -> 0 | F33: =IF(ISERROR(E33/$E$27),"",E33/$E$27) -> 0 | G33: =Balancete!G261 -> 0
C34: 1.2.3.7 | F34: =IF(ISERROR(E34/$E$27),"",E34/$E$27) -> 0
C35: 1.2.4 | D35: Outros activos correntes | E35: =IF(ISERROR(SUM(E36:E39)),"",SUM(E36:E39)) -> 1.7222319e+08 | G35: =IF(ISERROR(SUM(G36:G39)),"",SUM(G36:G39)) -> 0 | J35: =
C36: 1.2.4.1 | D36: Outros | E36: =Balancete!F207 -> 1.6523297e+08 | F36: =IF(ISERROR(E36/$E$35),"",E36/$E$35) -> 0.95941188 | G36: 0
C37: 1.2.4.2 | D37: Proveitos a faturar - encargos a repartir por exercícios futuros | F37: =IF(ISERROR(E37/$E$35),"",E37/$E$35) -> 0 | G37: =Balancete!G204 -> 0
C38: 1.2.4.3 | D38: Cartões Visa | E38: =Balancete!F211 -> 6990215 | F38: =IF(ISERROR(E38/$E$35),"",E38/$E$35) -> 0.040588117
C39: 1.2.4.4 | F39: =IF(ISERROR(E39/$E$35),"",E39/$E$35) -> 0
C40: 1.2.5 | D40: Estado | E40: =IF(ISERROR(SUM(E41:E49)),"",SUM(E41:E49)) -> 6.4883625e+08 | G40: =IF(ISERROR(SUM(G41:G49)),"",SUM(G41:G49)) -> 0
D41: Liquidação provisória de imposto industrial | E41: =Balancete!F152 -> 6.4883625e+08 | G41: 0
D42: IVA | E42: =Balancete!F158 -> 0 | G42: =Balancete!G158 -> 0
D43: Subsídio a preços | E43: =Balancete!F168 -> 0 | G43: =Balancete!G168 -> 0
D44: Outros impostos

Sheet Capital Próprio
B2: OBS: NÃO PREENCHER OS CAMPOS EM AZUL. PREENCHIMENTO AUTOMÁTICO.
E3: Ano Corrente | G3: Ano Anterior | L3: Ano Corrente | N3: Ano Anterior
C4: 2.1 | D4: Capital Próprio | E4: =IF(ISERROR($E$5+$E$11+$E$17+$E$25+$E$28),"",$E$5+$E$11+$E$17+$E$25+$E$28) -> 3.181566e+09 | G4: =IF(ISERROR($G$5+$G$11+$G$17+$G$25+$G$28),"",$G$5+$G$11+$G$17+$G$25+$G$28) -> 0 | J4: =C4 -> 2.1 | K4: Contas do Capital próprio
C5: 2.1.1 | D5: Capital | E5: =IF(ISERROR(SUM(E6:E10)),"",SUM(E6:E10)) -> 262500000 | G5: =IF(ISERROR(SUM(G6:G10)),"",SUM(G6:G10)) -> 0 | J5: =C5 -> 2.1.1 | K5: =D5 -> Capital | L5: =IF(ISERROR('Capital Próprio'!$E$5),"",'Capital Próprio'!$E$5) -> 262500000 | M5: =IF(ISERROR(L5/$N$5),"",L5/$N$5) | N5: =IF(ISERROR('Capital Próprio'!$G$5),"",'Capital Próprio'!$G$5) -> 0
C6: 2.1.1.1 | D6: Capital | E6: =-Balancete!F268 -> 262500000 | F6: =IF(ISERROR(E6/$E$5),"",E6/$E$5) -> 1 | G6: =-Balancete!G268 -> 0 | J6: =C11 -> 2.1.2 | K6: =D11 -> Reservas | L6: =IF(ISERROR('Capital Próprio'!$E$11),"",'Capital Próprio'!$E$11) -> 0 | M6: =IF(ISERROR(L6/$N$5),"",L6/$N$5) | N6: =IF(ISERROR('Capital Próprio'!$G$11),"",'Capital Próprio'!$G$11) -> 0
C7: 2.1.1.2 | D7: Acções/quotas próprias | E7: =Balancete!F270 -> 0 | F7: =IF(ISERROR(E7/$E$5),"",E7/$E$5) -> 0 | G7: =Balancete!G270 -> 0 | J7: =C17 -> 2.1.3 | K7: =D17 -> Resultados transitados | L7: =IF(ISERROR('Capital Próprio'!$E$17),"",'Capital Próprio'!$E$17) -> 4.5932662e+09 | M7: =IF(ISERROR(L7/$N$5),"",L7/$N$5) | N7: =IF(ISERROR('Capital Próprio'!$G$17),"",'Capital Próprio'!$G$17) -> 0
C8: 2.1.1.3 | D8: Prémios de emissão | E8: =Balancete!F274 -> 0 | F8: =IF(ISERROR(E8/$E$5),"",E8/$E$5) -> 0 | G8: =Balancete!G274 -> 0 | J8: =C25 -> 2.1.4 | K8: =D25 -> Resultados do exercício | L8: =IF(ISERROR('Capital Próprio'!$E$25),"",'Capital Próprio'!$E$25) -> -1.6742002e+09 | M8: =IF(ISERROR(L8/$N$5),"",L8/$N$5) | N8: =IF(ISERROR('Capital Próprio'!$G$25),"",'Capital Próprio'!$G$25) -> 0
C9: 2.1.1.4 | D9: Prestações suplementares | E9: =-Balancete!F276 -> 0 | F9: =IF(ISERROR(E9/$E$5),"",E9/$E$5) -> 0 | G9: =-Balancete!G276 -> 0 | L9: =IF(ISERROR('Capital Próprio'!#REF!),"",'Capital Próprio'!#REF!) | M9: =IF(ISERROR(L9/$N$5),"",L9/$N$5) | N9: =IF(ISERROR('Capital Próprio'!#REF!),"",'Capital Próprio'!#REF!)
C10: 2.1.1.5 | F10: =IF(ISERROR(E10/$E$5),"",E10/$E$5) -> 0 | L10: =IF(ISERROR('Capital Próprio'!#REF!),"",'Capital Próprio'!#REF!) | M10: =IF(ISERROR(L10/$N$5),"",L10/$N$5) | N10: =IF(ISERROR('Capital Próprio'!#REF!),"",'Capital Próprio'!#REF!)
C11: 2.1.2 | D11: Reservas | E11: =IF(ISERROR(SUM(E12:E16)),"",SUM(E12:E16)) -> 0 | G11: =IF(ISERROR(SUM(G12:G16)),"",SUM(G12:G16)) -> 0
C12: 2.1.2.1 | D12: Reserva legal | E12: =-Balancete!F278 -> 0 | F12: =IF(ISERROR(E12/$E$11),"",E12/$E$11) | G12: =-Balancete!G278 -> 0 | J12: Valor Total do Capital Próprio
C13: 2.1.2.2 | D13: Reservas de reavaliação | E13: =Balancete!F282 -> 0 | F13: =IF(ISERROR(E13/$E$11),"",E13/$E$11) | G13: =Balancete!G282 -> 0 | J13: Total | L13: =SUM(L5:L10) -> 3.181566e+09 | N13: =SUM(N5:N10) -> 0
C14: 2.1.2.3 | D14: Reservas com fins especiais | E14: =Balancete!F285 -> 0 | F14: =IF(ISERROR(E14/$E$11),"",E14/$E$11) | G14: =Balancete!G285 -> 0
C15: 2.1.2.4 | D15: Reservas livres | E15: =-Balancete!F287 -> 0 | F15: =IF(ISERROR(E15/$E$11),"",E15/$E$11) | G15: =-Balancete!G287 -> 0
C16: 2.1.2.5 | F16: =IF(ISERROR(E16/$E$11),"",E16/$E$11)
C17: 2.1.3 | D17: Resultados transitados | E17: =IF(ISERROR(SUM(E18:E24)),"",SUM(E18:E24)) -> 4.5932662e+09
C18: 2.1.3.1 | D18: Transferência dos resultados do exercício anterior | E18: =-Balancete!F289 -> 4.5932662e+09 | F18: =IF(ISERROR(E18/$E$17),"",E18/$E$17) -> 1
C19: 2.1.3.2 | D19: Aplicações de resultados | F19: =IF(ISERROR(E19/$E$17),"",E19/$E$17) -> 0
C20: 2.1.3.3 | D20: Erros fundamentais | F20: =IF(ISERROR(E20/$E$17),"",E20/$E$17) -> 0
C21: 2.1.3.4 | D21: Alterações de políticas contabilísticas | F21: =IF(ISERROR(E21/$E$17),"",E21/$E$17) -> 0
C22: 2.1.3.5 | D22: Efeito de impostos dos erros fundamentais e das alterações de políticas contabilísticas | F22: =IF(ISERROR(E22/$E$17),"",E22/$E$17) -> 0
C23: 2.1.3.6 | D23: Outros movimentos | F23: =IF(ISERROR(E23/$E$17),"",E23/$E$17) -> 0
C24: 2.1.3.7 | F24: =IF(ISERROR(E24/$E$17),"",E24/$E$17) -> 0
C25: 2.1.4 | D25: Resultados do exercício | E25: =IF(ISERROR(SUM(E26:E27)),"",SUM(E26:E27)) -> -1.6742002e+09 | G25: =IF(ISERROR(SUM(G26:G27)),"",SUM(G26:G27)) -> 0
C26: 2.1.4.1 | D26: Resultados do exercício | E26: =Balancete!F296 -> -1.6742002e+09 | F26: =IF(ISERROR(E26/$E$25),"",E26/$E$25) -> 1 | G26: =Balancete!G296 -> 0
C27: 2.1.4.2 | F27: =IF(ISERROR(E27/$E$25),"",E27/$E$25) -> 0
C170: 5738 | D170: Debêntures Securitizadas | E170: 467 | F170: =IF(ISERROR(E170/$E$78),"",E170/$E$78)
C171: 5739 | D171: Outros Títulos de Sociedades de Capital de Giro | E171: 45 | F171: =IF(ISERROR(E171/$E$78),"",E171/$E$78)
C172: 5718 | D172: Capital Subscrito a Integralizar | E172: 467 | F172: =IF(ISERROR(E172/$E$68),"",E172/$E$68)
C173: 5719 | D173: Capital Não Subscrito a Realizar | E173: 45 | F173: =IF(ISERROR(E173/$E$68),"",E173/$E$68)

Sheet Passivo Não Corrente
B2: OBS: NÃO PREENCHER OS CAMPOS EM AZUL. PREENCHIMENTO AUTOMÁTICO.
E3: Ano Corrente | G3: Ano Anterior | L3: Ano Corrente | N3: Ano Anterior
C4: 2.2 | D4: Passivo Não Corrente | E4: =IF(ISERROR($E$5+$E$11+$E$21+$E$31+$E$37+$E$41+$E$51),"",$E$5+$E$11+$E$21+$E$31+$E$37+$E$41+$E$51) -> 0 | G4: =IF(ISERROR($G$5+$G$11+$G$21+$G$31+$G$37+$G$41+$G$51),"",$G$5+$G$11+$G$21+$G$31+$G$37+$G$41+$G$51) -> 0 | J4: 2.2 | K4: Contas do Passivo Não Corrente
C5: 2.2.1 | D5: Empréstimos de médio e longo prazos | E5: =IF(ISERROR(SUM(E6:E10)),"",SUM(E6:E10)) -> 0 | G5: =IF(ISERROR(SUM(G6:G10)),"",SUM(G6:G10)) -> 0 | J5: =C5 -> 2.2.1 | K5: =D5 -> Empréstimos de médio e longo prazos | L5: =IF(ISERROR($E$5),"",$E$5) -> 0 | M5: =IF(ISERROR(L5/$N$5),"",L5/$N$5) | N5: =IF(ISERROR($E$5),"",$E$5) -> 0
C6: 2.2.1.1 | D6: Empréstimos bancários | F6: =IF(ISERROR(E6/$E$5),"",E6/$E$5) | J6: =C11 -> 2.2.2 | K6: =D11 -> Impostos diferidos | L6: =IF(ISERROR($E$11),"",$E$11) -> 0 | M6: =IF(ISERROR(L6/$N$5),"",L6/$N$5) | N6: =IF(ISERROR($E$11),"",$E$11) -> 0
C7: 2.2.1.2 | D7: Empréstimos por obrigações | F7: =IF(ISERROR(E7/$E$5),"",E7/$E$5) | J7: =C21 -> 2.2.3 | K7: =D21 -> Provisões para pensões | L7: =IF(ISERROR($E$21),"",$E$21) -> 0 | M7: =IF(ISERROR(L7/$N$5),"",L7/$N$5) | N7: =IF(ISERROR($E$21),"",$E$21) -> 0
C8: 2.2.1.3 | D8: Empréstimos por título de participação | F8: =IF(ISERROR(E8/$E$5),"",E8/$E$5) | J8: =C31 -> 2.2.4 | K8: =D31 -> Provisões para outros riscos e encagos | L8: =IF(ISERROR($E$31),"",$E$31) -> 0 | M8: =IF(ISERROR(L8/$N$5),"",L8/$N$5) | N8: =IF(ISERROR($G$31),"",$G$31) -> 0
C9: 2.2.1.4 | D9: Outros empréstimos | F9: =IF(ISERROR(E9/$E$5),"",E9/$E$5) | J9: =C37 -> 2.2.5 | K9: =D37 -> Outros passivos não correntes | L9: =IF(ISERROR($E$37),"",$E$37) -> 0 | M9: =IF(ISERROR(L9/$N$5),"",L9/$N$5) | N9: =IF(ISERROR($E$37),"",$E$37) -> 0
C10: 2.2.1.5 | F10: =IF(ISERROR(E10/$E$5),"",E10/$E$5) | L10: =IF(ISERROR($E$41),"",$E$41) -> 0 | M10: =IF(ISERROR(L10/$N$5),"",L10/$N$5) | N10: =IF(ISERROR($E$41),"",$E$41) -> 0
C11: 2.2.2 | D11: Impostos diferidos | E11: =IF(ISERROR(SUM(E12:E20)),"",SUM(E12:E20)) -> 0 | G11: =IF(ISERROR(SUM(G12:G20)),"",SUM(G12:G20)) -> 0 | L11: =IF(ISERROR(#REF!),"",#REF!) | M11: =IF(ISERROR(L11/$N$5),"",L11/$N$5) | N11: =IF(ISERROR(#REF!),"",#REF!)
C12: 2.2.2.1 | F12: =IF(ISERROR(E12/$E$11),"",E12/$E$11)
C13: 2.2.2.2 | F13: =IF(ISERROR(E13/$E$11),"",E13/$E$11) | J13: Obrigações Realizáveis a Longo Prazo
C14: 2.2.2.3 | F14: =IF(ISERROR(E14/$E$11),"",E14/$E$11) | J14: =C5 -> 2.2.1 | K14: =D5 -> Empréstimos de médio e longo prazos | L14: =IF(ISERROR($E$5),"",$E$5) -> 0 | M14: =IF(ISERROR(L14/$L$23),"",L14/$L$23)
C15: 2.2.2.4 | F15: =IF(ISERROR(E15/$E$11),"",E15/$E$11) | J15: =C11 -> 2.2.2 | K15: =D11 -> Impostos diferidos | L15: =IF(ISERROR($E$11),"",$E$11) -> 0 | M15: =IF(ISERROR(L15/$L$23),"",L15/$L$23)
C16: 2.2.2.5 | F16: =IF(ISERROR(E16/$E$11),"",E16/$E$11) | J16: =C21 -> 2.2.3 | K16: =D21 -> Provisões para pensões | L16: =IF(ISERROR($E$21),"",$E$21) -> 0 | M16: =IF(ISERROR(L16/$L$23),"",L16/$L$23)
C17: 2.2.2.6 | F17: =IF(ISERROR(E17/$E$11),"",E17/$E$11) | J17: =C31 -> 2.2.4 | K17: =D31 -> Provisões para outros riscos e encagos | L17: =IF(ISERROR($E$31),"",$E$31) -> 0 | M17: =IF(ISERROR(L17/$L$23),"",L17/$L$23) | N17: =IF(ISERROR($G$31),"",$G$31) -> 0
C18: 2.2.2.7 | F18: =IF(ISERROR(E18/$E$11),"",E18/$E$11) | J18: =C37 -> 2.2.5 | K18: =D37 -> Outros passivos não correntes | L18: =IF(ISERROR($E$37),"",$E$37) -> 0 | M18: =IF(ISERROR(L18/$L$23),"",L18/$L$23)
C19: 2.2.2.8 | F19: =IF(ISERROR(E19/$E$11),"",E19/$E$11) | L19: =IF(ISERROR($E$41),"",$E$41) -> 0 | M19: =IF(ISERROR(L19/$L$23),"",L19/$L$23)
C20: 2.2.2.9 | F20: =IF(ISERROR(E20/$E$11),"",E20/$E$11) | L20: =IF(ISERROR($E$51),"",$E$51) -> 0 | M20: =IF(ISERROR(L20/$L$23),"",L20/$L$23)
C21: 2.2.3 | D21: Provisões para pensões | E21: =IF(ISERROR(SUM(E22:E30)),"",SUM(E22:E30)) -> 0 | L21: =IF(ISERROR(#REF!),"",#REF!) | M21: =IF(ISERROR(L21/$L$23),"",L21/$L$23)
C22: 2.2.3.1 | D22: Provisões para pensões | E22: =-Balancete!F239 -> 0 | F22: =IF(ISERROR(E22/$E$21),"",E22/$E$21) | L22: =IF(ISERROR(#REF!),"",#REF!) | M22: =IF(ISERROR(L22/$L$23),"",L22/$L$23)
C23: 2.2.3.2 | F23: =IF(ISERROR(E23/$E$21),"",E23/$E$21) | J23: Total | L23: =IF(ISERROR(SUM($L$14:$L$22)),"",SUM($L$14:$L$22)) -> 0 | N23: =IF(ISERROR(SUM($N$14:$N$22)),"",SUM($N$14:$N$22)) -> 0
C24: 2.2.3.3 | F24: =IF(ISERROR(E24/$E$21),"",E24/$E$21)
C25: 2.2.3.4 | F25: =IF(ISERROR(E25/$E$21),"",E25/$E$21) | J25: Resultado de Exercícios Futuros
C26: 2.2.3.5 | F26: =IF(ISERROR(E26/$E$21),"",E26/$E$21) | L26: =IF(ISERROR(#REF!),"",#REF!) | M26: =IF(ISERROR(L26/$L$28),"",L26/$L$28)
C27: 2.2.3.6 | F27: =IF(ISERROR(E27/$E$21),"",E27/$E$21) | L27: =IF(ISERROR(#REF!),"",#REF!) | M27: =IF(ISERROR(L27/$L$28),"",L27/$L$28)
C28: 2.2.3.7 | F28: =IF(ISERROR(E28/$E$21),"",E28/$E$21) | J28: Total | L28: =IF(ISERROR(SUM($L$26:$L$27)),"",SUM($L$26:$L$27)) -> 0
C29: 2.2.3.8 | F29: =IF(ISERROR(E29/$E$21),"",E29/$E$21)
C30: 2.2.3.9 | F30: =IF(ISERROR(E30/$E$21),"",E30/$E$21) | J30: Valor Total do Passivo Não Corrente
C31: 2.2.4 | D31: Provisões para outros riscos e encagos | E31: =IF(ISERROR(SUM(E32:E36)),"",SUM(E32:E36)) -> 0 | G31: =IF(ISERROR(SUM(G32:G36)),"",SUM(G32:G36)) -> 0 | J31: Total | L31: =IF(ISERROR(SUM($L$5:$L$11)),"",SUM($L$5:$L$11)) -> 0 | N31: =IF(ISERROR(SUM($N$5:$N$11)),"",SUM($N$5:$N$11)) -> 0
C32: 2.2.4.1 | D32: Provisões para processos judiciais em curso | E32: =-Balancete!F240 -> 0 | F32: =IF(ISERROR(E32/$E$31),"",E32/$E$31) | G32: =-Balancete!H240 -> 0
C33: 2.2.4.2 | D33: Provisões para acidentes de trabalho | F33: =IF(ISERROR(E33/$E$31),"",E33/$E$31)
C34: 2.2.4.3 | D34: Provisões para garantias dadas a clientes | F34: =IF(ISERROR(E34/$E$31),"",E34/$E$31)
C35: 2.2.4.4 | D35: Provisões para outros riscos e encargos | E35: =-Balancete!F243 -> 0 | F35: =IF(ISERROR(E35/$E$31),"",E35/$E$31) | G35: =-Balancete!G243 -> 0
C36: 2.2.4.5 | F36: =IF(ISERROR(E36/$E$31),"",E36/$E$31)
C37: 2.2.5 | D37: Outros passivos não correntes | E37: =IF(ISERROR(SUM(E38:E40)),"",SUM(E38:E40)) -> 0
C38: 2.2.5.1 | D38: Subsídio ao investimento - não corrente | E38: =-Balancete!F217 -> 0 | F38: =IF(ISERROR(E38/$E$37),"",E38/$E$37)
C39: 2.2.5.2 | F39: =IF(ISERROR(E39/$E$37),"",E39/$E$37)
C40: 2.2.5.3 | F40: =IF(ISERROR(E40/$E$37),"",E40/$E$37)
C164: 5738 | D164: Debêntures Securitizadas | E164: 467 | F164: =IF(ISERROR(E164/'Capital Próprio'!$E$17),"",E164/'Capital Próprio'!$E$17) -> 1.0167057e-07
C165: 5739 | D165: Outros Títulos de Sociedades de Capital de Giro | E165: 45 | F165: =IF(ISERROR(E165/'Capital Próprio'!$E$17),"",E165/'Capital Próprio'!$E$17) -> 9.7969501e-09
C166: 5718 | D166: Capital Subscrito a Integralizar | E166: 467 | F166: =IF(ISERROR(E166/'Capital Próprio'!$E$11),"",E166/'Capital Próprio'!$E$11)
C167: 5719 | D167: Capital Não Subscrito a Realizar | E167: 45 | F167: =IF(ISERROR(E167/'Capital Próprio'!$E$11),"",E167/'Capital Próprio'!$E$11)

Sheet Passivo Corrente
B2: OBS: NÃO PREENCHER OS CAMPOS EM AZUL. PREENCHIMENTO AUTOMÁTICO.
E3: Ano Corrente | G3: Ano Anterior | L3: Ano Corrente | N3: Ano Anterior
C4: 2.3 | D4: Passivo Corrente | E4: =IF(ISERROR($E$5+$E$15+$E$25+$E$35+$E$45+$E$55+$E$65),"",$E$5+$E$15+$E$25+$E$35+$E$45+$E$55+$E$65) -> 1.9380363e+09 | G4: =IF(ISERROR($G$5+$G$15+$G$25+$G$35+$G$45+$G$55+$G$65),"",$G$5+$G$15+$G$25+$G$35+$G$45+$G$55+$G$65) -> -2846941.3 | J4: =C4 -> 2.3 | K4: Contas do Passivo Corrente - Total
C5: 2.3.1 | D5: Contas a pagar | E5: =IF(ISERROR(SUM(E6:E14)),"",SUM(E6:E14)) -> 1.006981e+09 | G5: =IF(ISERROR(SUM(G6:G14)),"",SUM(G6:G14)) -> -2553147.2 | J5: =C5 -> 2.3.1 | K5: =D5 -> Contas a pagar | L5: =IF(ISERROR($E$5),"",$E$5) -> 1.006981e+09 | M5: =IF(ISERROR(L5/$N$5),"",L5/$N$5) -> -394.40773 | N5: =IF(ISERROR($G$5),"",$G$5) -> -2553147.2
C6: 2.3.1.1 | D6: Fornecedores - correntes | E6: =-Balancete!F141 -> 2.2780068e+08 | F6: =IF(ISERROR(E6/$E$5),"",E6/$E$5) -> 0.22622143 | G6: =-Balancete!G141 -> 0 | J6: =C15 -> 2.3.2 | K6: =D15 -> Participantes e Participadas | L6: =IF(ISERROR($E$15),"",$E$15) -> 0 | M6: =IF(ISERROR(L6/$N$5),"",L6/$N$5) -> 0 | N6: =IF(ISERROR($G$15),"",$G$15) -> 0
C7: 2.3.1.2 | D7: Fornecedores - títulos a pagar | F7: =IF(ISERROR(E7/$E$5),"",E7/$E$5) -> 0 | J7: =C25 -> 2.3.3 | K7: =D25 -> Pessoal | L7: =IF(ISERROR($E$25),"",$E$25) -> 0 | M7: =IF(ISERROR(L7/$N$5),"",L7/$N$5) -> 0 | N7: =IF(ISERROR($G$25),"",$G$25) -> 0
C8: 2.3.1.3 | D8: Fornecedores - facturas em recepção e conferência | E8: =-Balancete!F143 -> 0 | F8: =IF(ISERROR(E8/$E$5),"",E8/$E$5) -> 0 | G8: =-Balancete!H143 -> 0 | J8: =C35 -> 2.3.4 | K8: =D35 -> Empréstimos de Curto Prazo | L8: =IF(ISERROR($E$35),"",$E$35) -> 0 | M8: =IF(ISERROR(L8/$N$5),"",L8/$N$5) -> 0 | N8: =IF(ISERROR($E$35),"",$E$35) -> 0
C9: 2.3.1.4 | D9: Clientes - saldos credores | E9: =-Balancete!F139 -> 2.9138622e+08 | F9: =IF(ISERROR(E9/$E$5),"",E9/$E$5) -> 0.28936615 | G9: =-Balancete!G139 -> 0 | J9: =C45 -> 2.3.5 | K9: =D45 -> Parte Correspondente dos Empréstimos de Médio e Longo Prazo | L9: =IF(ISERROR($E$45),"",$E$45) -> 0 | M9: =IF(ISERROR(L9/$N$5),"",L9/$N$5) -> 0 | N9: =IF(ISERROR($E$45),"",$E$45) -> 0
C10: 2.3.1.5 | D10: Estado | E10: =E55 -> 4.8779409e+08 | F10: =IF(ISERROR(E10/$E$5),"",E10/$E$5) -> 0.48441241 | G10: =-Balancete!G192 -> 0 | J10: =C55 -> 2.3.6 | K10: =D55 -> Estado | L10: =IF(ISERROR($E$55),"",$E$55) -> 4.8779409e+08 | M10: =IF(ISERROR(L10/$N$5),"",L10/$N$5) -> -191.056 | N10: =IF(ISERROR($G$55),"",G$55) -> 0
C11: 2.3.1.6 | D11: Subsídio de investimento - corrente | F11: =IF(ISERROR(E11/$E$5),"",E11/$E$5) -> 0 | J11: =C65 -> 2.3.7 | K11: =D65 -> Outros Passivos Correntes | L11: =IF(ISERROR($E$65),"",$E$65) -> 4.4326119e+08 | M11: =IF(ISERROR(L11/$N$5),"",L11/$N$5) -> -173.61365 | N11: =IF(ISERROR($G$65),"",$G$65) -> -293794.13
C12: 2.3.1.7 | D12: Outros credores | F12: =IF(ISERROR(E12/$E$5),"",E12/$E$5) -> 0 | G12: -2553147.2 | L12: =IF(ISERROR($E$74),"",$E$74) -> 0 | M12: =IF(ISERROR(L12/$N$5),"",L12/$N$5) -> 0 | N12: =IF(ISERROR($E$74),"",$E$74) -> 0
C13: 2.3.1.8 | F13: =IF(ISERROR(E13/$E$5),"",E13/$E$5) -> 0 | L13: =IF(ISERROR($E$84),"",$E$84) -> 0 | M13: =IF(ISERROR(L13/$N$5),"",L13/$N$5) -> 0 | N13: =IF(ISERROR($E$84),"",$E$84) -> 0
C14: 2.3.1.9 | F14: =IF(ISERROR(E14/$E$5),"",E14/$E$5) -> 0
C15: 2.3.2 | D15: Participantes e Participadas | E15: =IF(ISERROR(SUM(E16:E24)),"",SUM(E16:E24)) -> 0 | G15: =IF(ISERROR(SUM(G16:G24)),"",SUM(G16:G24)) -> 0 | J15: Obrigações Realizáveis a Curto Prazo
C16: 2.3.2.1 | D16: Entidades participantes | E16: 0 | F16: =IF(ISERROR(E16/$E$15),"",E16/$E$15) | J16: =C5 -> 2.3.1 | K16: =D5 -> Contas a pagar | L16: =IF(ISERROR($E$5),"",$E$5) -> 1.006981e+09 | M16: =IF(ISERROR(L16/$L$19),"",L16/$L$19) -> 2.0643567 | N16: =IF(ISERROR($G$5),"",$G$5) -> -2553147.2
C17: 2.3.2.2 | D17: Entidades participadas | F17: =IF(ISERROR(E17/$E$15),"",E17/$E$15) | J17: =C15 -> 2.3.2 | K17: =D15 -> Participantes e Participadas | L17: =IF(ISERROR($E$15),"",$E$15) -> 0 | M17: =IF(ISERROR(L17/$L$19),"",L17/$L$19) -> 0 | N17: =IF(ISERROR($G$15),"",$G$15) -> 0
C18: 2.3.2.3 | F18: =IF(ISERROR(E18/$E$15),"",E18/$E$15) | J18: =C25 -> 2.3.3 | K18: =D25 -> Pessoal | L18: =IF(ISERROR($E$25),"",$E$25) -> 0 | M18: =IF(ISERROR(L18/$L$19),"",L18/$L$19) -> 0 | N18: =IF(ISERROR($G$25),"",$G$25) -> 0
C19: 2.3.2.4 | F19: =IF(ISERROR(E19/$E$15),"",E19/$E$15) | J19: =C55 -> 2.3.6 | K19: =D55 -> Estado | L19: =IF(ISERROR($E$55),"",$E$55) -> 4.8779409e+08 | M19: =IF(ISERROR(L19/$L$19),"",L19/$L$19) -> 1 | N19: =IF(ISERROR($E$35),"",$E$35) -> 0
C20: 2.3.2.5 | F20: =IF(ISERROR(E20/$E$15),"",E20/$E$15) | J20: =C45 -> 2.3.5 | K20: =D45 -> Parte Correspondente dos Empréstimos de Médio e Longo Prazo | L20: =IF(ISERROR($E$45),"",$E$45) -> 0 | M20: =IF(ISERROR(L20/$L$19),"",L20/$L$19) -> 0 | N20: =IF(ISERROR($E$45),"",$E$45) -> 0
C21: 2.3.2.6 | F21: =IF(ISERROR(E21/$E$15),"",E21/$E$15) | M21: =IF(ISERROR(L21/$L$19),"",L21/$L$19) -> 0
C22: 2.3.2.7 | F22: =IF(ISERROR(E22/$E$15),"",E22/$E$15) | J22: Total | L22: =IF(ISERROR(SUM($L$16:$L$21)),"",SUM($L$16:$L$21)) -> 1.4947751e+09 | N22: =IF(ISERROR(SUM($N$16:$N$21)),"",SUM($N$16:$N$21)) -> -2553147.2
C23: 2.3.2.8 | F23: =IF(ISERROR(E23/$E$15),"",E23/$E$15)
C24: 2.3.2.9 | F24: =IF(ISERROR(E24/$E$15),"",E24/$E$15) | J24: Valor Total do Passivo Circulante
C25: 2.3.3 | D25: Pessoal | E25: =IF(ISERROR(SUM(E26:E34)),"",SUM(E26:E34)) -> 0 | G25: =-IF(ISERROR(SUM(G26:G34)),"",SUM(G26:G34)) -> 0 | J25: Total | L25: =IF(ISERROR(SUM($L$5:$L$13)),"",SUM($L$5:$L$13)) -> 1.9380363e+09 | N25: =IF(ISERROR(SUM($N$5:$N$13)),"",SUM($N$5:$N$13)) -> -2846941.3
C26: 2.3.3.1 | D26: Pessoal - remunerações | E26: =-Balancete!F181 -> 0 | F26: =IF(ISERROR(E26/$E$25),"",E26/$E$25) | G26: =-Balancete!G181 -> 0
C27: 2.3.3.2 | D27: Pessoal - Participação nos resultados | F27: =IF(ISERROR(E27/$E$25),"",E27/$E$25)
C28: 2.3.3.3 | D28: Pessoal - adiantamentos | F28: =IF(ISERROR(E28/$E$25),"",E28/$E$25) | G28: =-Balancete!G187 -> 0 | L28: =G4-313116786.31 -> -3.1596373e+08
C29: 2.3.3.4 | D29: Pessoal - Outros | F29: =IF(ISERROR(E29/$E$25),"",E29/$E$25)
C30: 2.3.3.5 | F30: =IF(ISERROR(E30/$E$25),"",E30/$E$25)
C31: 2.3.3.6 | F31: =IF(ISERROR(E31/$E$25),"",E31/$E$25)
C32: 2.3.3.7 | F32: =IF(ISERROR(E32/$E$25),"",E32/$E$25)
C33: 2.3.3.8 | F33: =IF(ISERROR(E33/$E$25),"",E33/$E$25)
C34: 2.3.3.9 | F34: =IF(ISERROR(E34/$E$25),"",E34/$E$25)
C35: 2.3.4 | D35: Empréstimos de Curto Prazo | E35: =IF(ISERROR(SUM(E36:E44)),"",SUM(E36:E44)) -> 0
C36: 2.3.4.1 | D36: Empréstimos bancários | F36: =IF(ISERROR(E36/$E$35),"",E36/$E$35)
C37: 2.3.4.2 | D37: Empréstimos por obrigações | F37: =IF(ISERROR(E37/$E$35),"",E37/$E$35)
C38: 2.3.4.3 | D38: Empréstimo por título de participação | F38: =IF(ISERROR(E38/$E$35),"",E38/$E$35)
C39: 2.3.4.4 | D39: Outros empréstimos | F39: =IF(ISERROR(E39/$E$35),"",E39/$E$35)
C40: 2.3.4.5 | F40: =IF(ISERROR(E40/$E$35),"",E40/$E$35)
C41: 2.3.4.6 | F41: =IF(ISERROR(E41/$E$35),"",E41/$E$35)
C42: 2.3.4.7 | F42: =IF(ISERROR(E42/$E$35),"",E42/$E$35)
C43: 2.3.4.8 | F43: =IF(ISERROR(E43/$E$35),"",E43/$E$35)
C44: 2.3.4.9 | F44: =IF(ISERROR(E44/$E$35),"",E44/$E$35)
C45: 2.3.5 | D45: Parte Correspondente dos Empréstimos de Médio e Longo Prazo | E45: =IF(ISERROR(SUM(E46:E54)),"",SUM(E46:E54)) -> 0
C46: 2.3.5.1 | F46: =IF(ISERROR(E46/$E$45),"",E46/$E$45)
C47: 2.3.5.2 | F47: =IF(ISERROR(E47/$E$45),"",E47/$E$45)
C48: 2.3.5.3 | F48: =IF(ISERROR(E48/$E$45),"",E48/$E$45)
C49: 2.3.5.4 | F49: =IF(ISERROR(E49/$E$45),"",E49/$E$45)
C50: 2.3.5.5 | F50: =IF(ISERROR(E50/$E$45),"",E50/$E$45)
C51: 2.3.5.6 | F51: =IF(ISERROR(E51/$E$45),"",E51/$E$45)
C52: 2.3.5.7 | F52: =IF(ISERROR(E52/$E$45),"",E52/$E$45)
C53: 2.3.5.8 | F53: =IF(ISERROR(E53/$E$45),"",E53/$E$45)
C54: 2.3.5.9 | F54: =IF(ISERROR(E54/$E$45),"",E54/$E$45) | J54: =E55-554079000 -> -66284907
C55: 2.3.6 | D55: Estado | E55: =IF(ISERROR(SUM(E56:E64)),"",SUM(E56:E64)) -> 4.8779409e+08 | G55: =IF(ISERROR(SUM(G56:G64)),"",SUM(G56:G64)) -> 0
C56: 2.3.6.1 | D56: Impostos sobre lucros | F56: =IF(ISERROR(E56/$E$55),"",E56/$E$55) -> 0 | G56: =-Balancete!G151 -> 0
C57: 2.3.6.2 | D57: Imposto de produção e consumo | E57: =Balancete!F154 -> 0 | F57: =IF(ISERROR(E57/$E$55),"",E57/$E$55) -> 0 | G57: =Balancete!H154 -> 0
C58: 2.3.6.3 | D58: Imposto de rendimento de trabalho | E58: =-Balancete!F155 -> 2.7373207e+08 | F58: =IF(ISERROR(E58/$E$55),"",E58/$E$55) -> 0.56116315 | G58: =-Balancete!G155 -> 0
C59: 2.3.6.4 | D59: Imposto sobre veículos motorizados | F59: =IF(ISERROR(E59/$E$55),"",E59/$E$55) -> 0
C60: 2.3.6.5 | D60: Retenções de impostos - Segurança social | F60: =IF(ISERROR(E60/$E$55),"",E60/$E$55) -> 0 | G60: =-Balancete!G171 -> 0
C61: 2.3.6.6 | D61: IVA a recuperar | E61: =-Balancete!F164 -> 0 | F61: =IF(ISERROR(E61/$E$55),"",E61/$E$55) -> 0 | G61: =-Balancete!H164 -> 0
C62: 2.3.6.7 | D62: Imposto predial | F62: =IF(ISERROR(E62/$E$55),"",E62/$E$55) -> 0
C63: 2.3.6.8 | D63: Outros impostos | E63: =-Balancete!F169 -> 2.1406203e+08 | F63: =IF(ISERROR(E63/$E$55),"",E63/$E$55) -> 0.43883685 | G63: =-Balancete!H169 -> 0
C64: 2.3.6.9 | F64: =IF(ISERROR(E64/$E$55),"",E64/$E$55) -> 0
C65: 2.3.7 | D65: Outros Passivos Correntes | E65: =IF(ISERROR(SUM(E66:E73)),"",SUM(E66:E73)) -> 4.4326119e+08 | G65: =IF(ISERROR(SUM(G66:G73)),"",SUM(G66:G73)) -> -293794.13 | J65: =G65-239598405 -> -2.398922e+08
C66: 2.3.7.1 | D66: Encargos a pagar | F66: =IF(ISERROR(E66/$E$65),"",E66/$E$65) -> 0 | G66: =-Balancete!G208 -> 0
C67: 2.3.7.2 | D67: Proveitos a pagar por exercícios futuros | E67: =-Balancete!F212 -> 0 | F67: =IF(ISERROR(E67/$E$65),"",E67/$E$65) -> 0 | G67: =-Balancete!G212 -> 0
C68: 2.3.7.4 | D68: Contas transitórias | E68: =-Balancete!F221 -> 0 | F68: =IF(ISERROR(E68/$E$65),"",E68/$E$65) -> 0 | G68: =-Balancete!G221 -> 0
C69: 2.3.7.5 | D69: Outros valores a pagar | E69: =-Balancete!F223 -> 4.4326119e+08 | F69: =IF(ISERROR(E69/$E$65),"",E69/$E$65) -> 1 | G69: =-Balancete!G223 -> 0
C70: 2.3.7.6 | D70: Juros | E70: =Balancete!F203 -> 0 | F70: =IF(ISERROR(E70/$E$65),"",E70/$E$65) -> 0 | G70: =Balancete!G203 -> 0
C71: 2.3.7.7 | D71: Acerto | F71: =IF(ISERROR(E71/$E$65),"",E71/$E$65) -> 0 | G71: -293794.13
C72: 2.3.7.8 | F72: =IF(ISERROR(E72/$E$65),"",E72/$E$65) -> 0
C73: 2.3.7.9 | F73: =IF(ISERROR(E73/$E$65),"",E73/$E$65) -> 0

Sheet Balanço Patrimonial
B2: OBS: PLANILHA AUTOMÁTICA. NÃO PREENCHER NENHUM CAMPO.
C4: ='Activos Não Correntes'!C4 -> 1.1 | D4: Contas do Activo Não Corrente | E4: Ano Corrente | G4: Ano Anterior | J4: ='Passivo Não Corrente'!J4 -> 2.2 | K4: Contas do Passivo Não Corrente | L4: Ano Corrente | N4: Ano Anterior
C5: ='Activos Não Correntes'!C5 -> 1.1.1 | D5: ='Activos Não Correntes'!D5 -> Imobilizações corpóreas | E5: =IF(ISERROR('Activos Não Correntes'!L5),"",'Activos Não Correntes'!L5) -> 3.4238736e+09 | F5: =IF(ISERROR('Activos Não Correntes'!M5),"",'Activos Não Correntes'!M5) -> 0.9938818 | G5: =IF(ISERROR('Activos Não Correntes'!N5),"",'Activos Não Correntes'!N5) -> 0 | J5: ='Passivo Não Corrente'!J5 -> 2.2.1 | K5: ='Passivo Não Corrente'!K5 -> Empréstimos de médio e longo prazos | L5: =IF(ISERROR('Passivo Não Corrente'!L5),"",'Passivo Não Corrente'!L5) -> 0 | M5: =IF(ISERROR('Passivo Não Corrente'!M5),"",'Passivo Não Corrente'!M5) | N5: =IF(ISERROR('Passivo Não Corrente'!N5),"",'Passivo Não Corrente'!N5) -> 0
C6: ='Activos Não Correntes'!C16 -> 1.1.2 | D6: ='Activos Não Correntes'!D16 -> Imobilizações incorpóreas | E6: =IF(ISERROR('Activos Não Correntes'!L6),"",'Activos Não Correntes'!L6) -> 21076889 | F6: =IF(ISERROR('Activos Não Correntes'!M6),"",'Activos Não Correntes'!M6) -> 0.0061181981 | G6: =IF(ISERROR('Activos Não Correntes'!N6),"",'Activos Não Correntes'!N6) -> 0 | J6: ='Passivo Não Corrente'!J6 -> 2.2.2 | K6: ='Passivo Não Corrente'!K6 -> Impostos diferidos | L6: =IF(ISERROR('Passivo Não Corrente'!L6),"",'Passivo Não Corrente'!L6) -> 0 | M6: =IF(ISERROR('Passivo Não Corrente'!M6),"",'Passivo Não Corrente'!M6) | N6: =IF(ISERROR('Passivo Não Corrente'!N6),"",'Passivo Não Corrente'!N6) -> 0
C7: ='Activos Não Correntes'!C26 -> 1.1.3 | D7: ='Activos Não Correntes'!D26 -> Investimentos em Subsidiárias e Associadas | E7: =IF(ISERROR('Activos Não Correntes'!L7),"",'Activos Não Correntes'!L7) -> 0 | F7: =IF(ISERROR('Activos Não Correntes'!M7),"",'Activos Não Correntes'!M7) -> 0 | G7: =IF(ISERROR('Activos Não Correntes'!N7),"",'Activos Não Correntes'!N7) -> 0 | J7: ='Passivo Não Corrente'!J7 -> 2.2.3 | K7: ='Passivo Não Corrente'!K7 -> Provisões para pensões | L7: =IF(ISERROR('Passivo Não Corrente'!L7),"",'Passivo Não Corrente'!L7) -> 0 | M7: =IF(ISERROR('Passivo Não Corrente'!M7),"",'Passivo Não Corrente'!M7) | N7: =IF(ISERROR('Passivo Não Corrente'!N7),"",'Passivo Não Corrente'!N7) -> 0
C8: ='Activos Não Correntes'!C30 -> 1.1.4 | D8: ='Activos Não Correntes'!D30 -> Outros Activos Financeiros | E8: =IF(ISERROR('Activos Não Correntes'!L8),"",'Activos Não Correntes'!L8) -> 0 | F8: =IF(ISERROR('Activos Não Correntes'!M8),"",'Activos Não Correntes'!M8) -> 0 | G8: =IF(ISERROR('Activos Não Correntes'!N8),"",'Activos Não Correntes'!N8) -> 0 | J8: ='Passivo Não Corrente'!J8 -> 2.2.4 | K8: ='Passivo Não Corrente'!K8 -> Provisões para outros riscos e encagos | L8: =IF(ISERROR('Passivo Não Corrente'!L8),"",'Passivo Não Corrente'!L8) -> 0 | M8: =IF(ISERROR('Passivo Não Corrente'!M8),"",'Passivo Não Corrente'!M8) | N8: =IF(ISERROR('Passivo Não Corrente'!N8),"",'Passivo Não Corrente'!N8) -> 0
C9: ='Activos Não Correntes'!C38 -> 1.1.5 | D9: ='Activos Não Correntes'!D38 -> Provisões para Investimentos Financeiros | E9: =IF(ISERROR('Activos Não Correntes'!L9),"",'Activos Não Correntes'!L9) -> 0 | F9: =IF(ISERROR('Activos Não Correntes'!M9),"",'Activos Não Correntes'!M9) -> 0 | G9: =IF(ISERROR('Activos Não Correntes'!N9),"",'Activos Não Correntes'!N9) -> 0 | J9: ='Passivo Não Corrente'!J9 -> 2.2.5 | K9: ='Passivo Não Corrente'!K9 -> Outros passivos não correntes | L9: =IF(ISERROR('Passivo Não Corrente'!L9),"",'Passivo Não Corrente'!L9) -> 0 | M9: =IF(ISERROR('Passivo Não Corrente'!M9),"",'Passivo Não Corrente'!M9) | N9: =IF(ISERROR('Passivo Não Corrente'!N9),"",'Passivo Não Corrente'!N9) -> 0
C10: ='Activos Não Correntes'!C45 -> 1.1.6 | D10: ='Activos Não Correntes'!D45 -> Outros Activos não Correntes | E10: =IF(ISERROR('Activos Não Correntes'!L20),"",'Activos Não Correntes'!L20) -> 0 | F10: =IF(ISERROR('Activos Não Correntes'!#REF!),"",'Activos Não Correntes'!#REF!) | G10: =IF(ISERROR('Activos Não Correntes'!N20),"",'Activos Não Correntes'!N20) -> 0 | J10: 0 | K10: 0 | L10: =IF(ISERROR('Passivo Não Corrente'!L10),"",'Passivo Não Corrente'!L10) -> 0 | M10: =IF(ISERROR('Passivo Não Corrente'!M10),"",'Passivo Não Corrente'!M10) | N10: =IF(ISERROR('Passivo Não Corrente'!N10),"",'Passivo Não Corrente'!N10) -> 0
C11: ='Activos Não Correntes'!C55 -> 0 | D11: ='Activos Não Correntes'!D55 -> 0 | E11: =IF(ISERROR('Activos Não Correntes'!L11),"",'Activos Não Correntes'!L11) -> 0 | F11: =IF(ISERROR('Activos Não Correntes'!M11),"",'Activos Não Correntes'!M11) -> 0 | G11: =IF(ISERROR('Activos Não Correntes'!N11),"",'Activos Não Correntes'!N11) -> 0 | J11: 0 | K11: 0 | L11: =IF(ISERROR('Passivo Não Corrente'!#REF!),"",'Passivo Não Corrente'!#REF!) | M11: =IF(ISERROR('Passivo Não Corrente'!#REF!),"",'Passivo Não Corrente'!#REF!) | N11: =IF(ISERROR('Passivo Não Corrente'!#REF!),"",'Passivo Não Corrente'!#REF!)
C12: ='Activos Correntes'!J12 -> 0 | D12: ='Activos Correntes'!K12 -> 0 | E12: =IF(ISERROR('Activos Não Correntes'!L12),"",'Activos Não Correntes'!L12) -> 0 | F12: =IF(ISERROR('Activos Não Correntes'!M12),"",'Activos Não Correntes'!M12) -> 0 | G12: =IF(ISERROR('Activos Não Correntes'!N12),"",'Activos Não Correntes'!N12) -> 0 | J12: ='Passivo Corrente'!J12 -> 0 | K12: ='Passivo Corrente'!K12 -> 0 | L12: =IF(ISERROR('Passivo Não Corrente'!#REF!),"",'Passivo Não Corrente'!#REF!) | M12: =IF(ISERROR('Passivo Não Corrente'!#REF!),"",'Passivo Não Corrente'!#REF!) | N12: =IF(ISERROR('Passivo Não Corrente'!#REF!),"",'Passivo Não Corrente'!#REF!)
C13: ='Activos Correntes'!J13 -> 0 | D13: ='Activos Correntes'!K13 -> 0 | E13: =IF(ISERROR('Activos Não Correntes'!L13),"",'Activos Não Correntes'!L13) -> 0 | F13: =IF(ISERROR('Activos Não Correntes'!M13),"",'Activos Não Correntes'!M13) -> 0 | G13: =IF(ISERROR('Activos Não Correntes'!N13),"",'Activos Não Correntes'!N13) -> 0 | J13: ='Passivo Corrente'!J13 -> 0 | K13: ='Passivo Corrente'!K13 -> 0 | L13: =IF(ISERROR('Passivo Não Corrente'!#REF!),"",'Passivo Não Corrente'!#REF!) | M13: =IF(ISERROR('Passivo Não Corrente'!#REF!),"",'Passivo Não Corrente'!#REF!) | N13: =IF(ISERROR('Passivo Não Corrente'!#REF!),"",'Passivo Não Corrente'!#REF!)
C14: Total | E14: =IF(ISERROR(SUM(E5:E13)),"",SUM(E5:E13)) -> 3.4449505e+09 | G14: =IF(ISERROR(SUM(G5:G13)),"",SUM(G5:G13)) -> 0 | J14: Total | L14: =IF(ISERROR(SUM(L5:L13)),"",SUM(L5:L13)) -> 0 | N14: =IF(ISERROR(SUM(N5:N13)),"",SUM(N5:N13)) -> 0
C15: Total apresentado pela entidade | E15: 3.4449505e+09 | G15: 1.8696976e+08 | J15: Total apresentado pela entidade | L15: 0 | N15: 52083465
C16: Diferença | E16: =E14-E15 -> 0 | G16: =G14-G15 -> -1.8696976e+08 | J16: Diferença | L16: =L14-L15 -> 0 | N16: =N14-N15 -> -52083465
C18: ='Activos Correntes'!C4 -> 1.2 | D18: Contas do Activo Corrente | J18: ='Passivo Corrente'!J4 -> 2.3 | K18: Contas do Passivo Corrente | L18: Ano Corrente | N18: Ano Anterior
C19: ='Activos Correntes'!C5 -> 1.2.1 | D19: ='Activos Correntes'!D5 -> Existências | E19: =IF(ISERROR('Activos Correntes'!L5),"",'Activos Correntes'!L5) -> 0 | F19: =IF(ISERROR('Activos Correntes'!M5),"",'Activos Correntes'!M5) -> 0 | G19: =IF(ISERROR('Activos Correntes'!N5),"",'Activos Correntes'!N5) -> 0 | J19: ='Passivo Corrente'!J5 -> 2.3.1 | K19: ='Passivo Corrente'!K5 -> Contas a pagar | L19: =IF(ISERROR('Passivo Corrente'!L5),"",'Passivo Corrente'!L5) -> 1.006981e+09 | M19: =IF(ISERROR('Passivo Não Corrente'!M5),"",'Passivo Não Corrente'!M5) | N19: =IF(ISERROR('Passivo Corrente'!N5),"",'Passivo Corrente'!N5) -> -2553147.2
C20: ='Activos Correntes'!C15 -> 1.2.2 | D20: ='Activos Correntes'!D15 -> Contas a Receber | E20: =IF(ISERROR('Activos Correntes'!L6),"",'Activos Correntes'!L6) -> 1.3402124e+09 | F20: =IF(ISERROR('Activos Correntes'!M6),"",'Activos Correntes'!M6) -> 0.85631482 | G20: =IF(ISERROR('Activos Correntes'!N6),"",'Activos Correntes'!N6) -> 0 | J20: ='Passivo Corrente'!J6 -> 2.3.2 | K20: ='Passivo Corrente'!K6 -> Participantes e Participadas | L20: =IF(ISERROR('Passivo Corrente'!L6),"",'Passivo Corrente'!L6) -> 0 | M20: =IF(ISERROR('Passivo Não Corrente'!M6),"",'Passivo Não Corrente'!M6) | N20: =IF(ISERROR('Passivo Corrente'!N6),"",'Passivo Corrente'!N6) -> 0
C21: ='Activos Correntes'!C27 -> 1.2.3 | D21: ='Activos Correntes'!D27 -> Disponibilidades | E21: =IF(ISERROR('Activos Correntes'!L7),"",'Activos Correntes'!L7) -> 52657493 | F21: =IF(ISERROR('Activos Correntes'!M7),"",'Activos Correntes'!M7) -> 0.033644958 | G21: =IF(ISERROR('Activos Correntes'!N7),"",'Activos Correntes'!N7) -> 0 | J21: ='Passivo Corrente'!J7 -> 2.3.3 | K21: ='Passivo Corrente'!K7 -> Pessoal | L21: =IF(ISERROR('Passivo Corrente'!L7),"",'Passivo Corrente'!L7) -> 0 | M21: =IF(ISERROR('Passivo Não Corrente'!M7),"",'Passivo Não Corrente'!M7) | N21: =IF(ISERROR('Passivo Corrente'!N7),"",'Passivo Corrente'!N7) -> 0
C22: ='Activos Correntes'!C35 -> 1.2.4 | D22: ='Activos Correntes'!D35 -> Outros activos correntes | E22: =IF(ISERROR('Activos Correntes'!L8),"",'Activos Correntes'!L8) -> 1.7222319e+08 | F22: =IF(ISERROR('Activos Correntes'!M8),"",'Activos Correntes'!M8) -> 0.11004022 | G22: =IF(ISERROR('Activos Correntes'!N8),"",'Activos Correntes'!N8) -> 0 | J22: ='Passivo Corrente'!J8 -> 2.3.4 | K22: ='Passivo Corrente'!K8 -> Empréstimos de Curto Prazo | L22: =IF(ISERROR('Passivo Corrente'!L8),"",'Passivo Corrente'!L8) -> 0 | M22: =IF(ISERROR('Passivo Não Corrente'!M8),"",'Passivo Não Corrente'!M8) | N22: =IF(ISERROR('Passivo Corrente'!N8),"",'Passivo Corrente'!N8) -> 0
C23: ='Activos Correntes'!C40 -> 1.2.5 | D23: ='Activos Correntes'!D40 -> Estado | E23: =IF(ISERROR('Activos Correntes'!L9),"",'Activos Correntes'!L9) -> 0 | F23: =IF(ISERROR('Activos Correntes'!M9),"",'Activos Correntes'!M9) -> 0 | G23: =IF(ISERROR('Activos Correntes'!N9),"",'Activos Correntes'!N9) -> 0 | J23: ='Passivo Corrente'!J9 -> 2.3.5 | K23: ='Passivo Corrente'!K9 -> Parte Correspondente dos Empréstimos de Médio e Longo Prazo | L23: =IF(ISERROR('Passivo Corrente'!L9),"",'Passivo Corrente'!L9) -> 0 | M23: =IF(ISERROR('Passivo Não Corrente'!M9),"",'Passivo Não Corrente'!M9) | N23: =IF(ISERROR('Passivo Corrente'!N9),"",'Passivo Corrente'!N9) -> 0
C24: ='Activos Correntes'!C50 -> 0 | D24: ='Activos Correntes'!D50 -> 0 | E24: =IF(ISERROR('Activos Correntes'!L10),"",'Activos Correntes'!L10) -> 0 | F24: =IF(ISERROR('Activos Correntes'!M10),"",'Activos Correntes'!M10) -> 0 | G24: =IF(ISERROR('Activos Correntes'!N10),"",'Activos Correntes'!N10) -> 0 | J24: ='Passivo Corrente'!J10 -> 2.3.6 | K24: ='Passivo Corrente'!K10 -> Estado | L24: =IF(ISERROR('Passivo Corrente'!L10),"",'Passivo Corrente'!L10) -> 4.8779409e+08 | M24: =IF(ISERROR('Passivo Não Corrente'!M10),"",'Passivo Não Corrente'!M10) | N24: =IF(ISERROR('Passivo Corrente'!N10),"",'Passivo Corrente'!N10) -> 0
J25: ='Passivo Corrente'!J11 -> 2.3.7 | K25: ='Passivo Corrente'!K11 -> Outros Passivos Correntes | L25: =IF(ISERROR('Passivo Corrente'!L11),"",'Passivo Corrente'!L11) -> 4.4326119e+08 | M25: =IF(ISERROR('Passivo Não Corrente'!#REF!),"",'Passivo Não Corrente'!#REF!) | N25: =IF(ISERROR('Passivo Corrente'!N11),"",'Passivo Corrente'!N11) -> -293794.13
J26: Total | L26: =IF(ISERROR(SUM(L19:L25)),"",SUM(L19:L25)) -> 1.9380363e+09 | N26: =IF(ISERROR(SUM(N19:N25)),"",SUM(N19:N25)) -> -2846941.3
J27: Total apresentado pela entidade | L27: 1828476000 | N27: 3.1311679e+08
J28: Diferença | L28: =L26-L27 -> 1.0956028e+08 | N28: =N26-N27 -> -3.1596373e+08
J30: ='Capital Próprio'!J4 -> 2.1 | K30: Contas do Capital Próprio | L30: Ano Corrente | N30: Ano Anterior
J31: ='Capital Próprio'!J5 -> 2.1.1 | K31: ='Capital Próprio'!K5 -> Capital | L31: =IF(ISERROR('Capital Próprio'!L5),"",'Capital Próprio'!L5) -> 262500000 | M31: =IF(ISERROR('Capital Próprio'!M5),"",'Capital Próprio'!M5) | N31: =IF(ISERROR('Capital Próprio'!N5),"",'Capital Próprio'!N5) -> 0
C32: Total | E32: =IF(ISERROR(SUM(E19:E31)),"",SUM(E19:E31)) -> 1.5650931e+09 | G32: =IF(ISERROR(SUM(G19:G31)),"",SUM(G19:G31)) -> 0 | J32: ='Capital Próprio'!J6 -> 2.1.2 | K32: ='Capital Próprio'!K6 -> Reservas | L32: =IF(ISERROR('Capital Próprio'!L6),"",'Capital Próprio'!L6) -> 0 | M32: =IF(ISERROR('Capital Próprio'!M6),"",'Capital Próprio'!M6) | N32: =IF(ISERROR('Capital Próprio'!N6),"",'Capital Próprio'!N6) -> 0
C33: Total apresentado pela entidade | E33: 1.5650931e+09 | G33: 8.3966785e+08 | J33: ='Capital Próprio'!J7 -> 2.1.3 | K33: ='Capital Próprio'!K7 -> Resultados transitados | L33: =IF(ISERROR('Capital Próprio'!L7),"",'Capital Próprio'!L7) -> 4.5932662e+09 | M33: =IF(ISERROR('Capital Próprio'!M7),"",'Capital Próprio'!M7) | N33: =IF(ISERROR('Capital Próprio'!N7),"",'Capital Próprio'!N7) -> 0
C34: Diferença | E34: =E32-E33 -> 0 | G34: =G32-G33 -> -8.3966785e+08 | J34: ='Capital Próprio'!J8 -> 2.1.4 | K34: ='Capital Próprio'!K8 -> Resultados do exercício | L34: =IF(ISERROR('Capital Próprio'!L8),"",'Capital Próprio'!L8) -> -1.6742002e+09 | M34: =IF(ISERROR('Capital Próprio'!M8),"",'Capital Próprio'!M8) | N34: =IF(ISERROR('Capital Próprio'!N8),"",'Capital Próprio'!N8) -> 0
L35: =IF(ISERROR('Capital Próprio'!L9),"",'Capital Próprio'!L9) | M35: =IF(ISERROR('Capital Próprio'!M9),"",'Capital Próprio'!M9)
C36: Total do Balanço Patrimonial | J36: Total | L36: =IF(ISERROR(SUM(L31:L35)),"",SUM(L31:L35)) -> 3.181566e+09 | N36: =IF(ISERROR(SUM(N31:N35)),"",SUM(N31:N35)) -> 0
C37: Activo | E37: =IF(ISERROR(E14+E32),"",E14+E32) -> 5.0100436e+09 | G37: =IF(ISERROR(G14+G32),"",G14+G32) -> 0 | J37: Total apresentado pela entidade | L37: 3.181566e+09 | N37: 6.6143736e+08
C38: Capital Próprio + Passivo | E38: =IF(ISERROR(L14+L26+L36),"",L14+L26+L36) -> 5.1196023e+09 | G38: =IF(ISERROR(N14+N26+N36),"",N14+N26+N36) -> -2846941.3 | J38: Diferença | L38: =L36-L37 -> 0 | N38: =N36-N37 -> -6.6143736e+08
C40: Resultado | E40: =IF(E37=E38,"CORRECTO","REVER") -> REVER | G40: =IF(G37=G38,"CORRECTO","REVER") -> REVER

Sheet Proveitos por Natureza
B2: OBS: NÃO PREENCHER OS CAMPOS EM AZUL. PREENCHIMENTO AUTOMÁTICO.
E3: Ano Corrente | G3: Ano Anterior | L3: Ano Corrente | N3: Ano Anterior
C4: 3 | D4: Proveitos e Ganhos por Natureza | E4: =IF(ISERROR($E$5+$E$15+$E$21+$E$31+$E$36+$E$40+$E$49+$E$53+$E$65),"",$E$5+$E$15+$E$21+$E$31+$E$36+$E$40+$E$49+$E$53+$E$65) -> 4.8672211e+09 | G4: =IF(ISERROR($G$5+$G$15+$G$21+$G$31+$G$36+$G$40+$G$49+$G$53+$G$65),"",$G$5+$G$15+$G$21+$G$31+$G$36+$G$40+$G$49+$G$53+$G$65) -> 0 | J4: 3 | K4: Contas de Proveitos e Ganhos por Natureza - Total
C5: 3.1 | D5: Vendas | E5: =IF(ISERROR(SUM(E6:E14)),"",SUM(E6:E14)) -> 0 | G5: =IF(ISERROR(SUM(G6:G14)),"",SUM(G6:G14)) -> 0 | J5: =C5 -> 3.1 | K5: =D5 -> Vendas | L5: =IF(ISERROR($E$5),"",$E$5) -> 0 | M5: =IF(ISERROR(L5/$N$5),"",L5/$N$5) | N5: =IF(ISERROR($G$5),"",$G$5) -> 0
C6: 3.1.1 | D6: Produtos acabados e intermédios | E6: =-Balancete!F302 -> 0 | F6: =IF(ISERROR(E6/$E$5),"",E6/$E$5) | G6: =-Balancete!G302 -> 0 | J6: =C15 -> 3.2 | K6: =D15 -> Prestações de Serviço | L6: =IF(ISERROR($E$15),"",$E$15) -> 1.7692123e+09 | M6: =IF(ISERROR(L6/$N$5),"",L6/$N$5) | N6: =IF(ISERROR($G$15),"",$G$15) -> 0
C7: 3.1.2 | D7: Subprodutos, desperdícios, resíduos e refugos | E7: =-Balancete!F303 -> 0 | F7: =IF(ISERROR(E7/$E$5),"",E7/$E$5) | G7: =-Balancete!G303 -> 0 | J7: =C21 -> 3.3 | K7: =D21 -> Outros Proveitos Operacionais | L7: =IF(ISERROR($E$21),"",$E$21) -> 3.0629189e+09 | M7: =IF(ISERROR(L7/$N$5),"",L7/$N$5) | N7: =IF(ISERROR($G$21),"",$G$21) -> 0
C8: 3.1.3 | D8: Mercadorias | E8: =-Balancete!F304 -> 0 | F8: =IF(ISERROR(E8/$E$5),"",E8/$E$5) | G8: =-Balancete!G304 -> 0 | J8: =C31 -> 3.4 | K8: =D31 -> Varição nos Produtos Acabados e Produtos em Vias de Fabrico | L8: =IF(ISERROR($E$31),"",$E$31) -> 0 | M8: =IF(ISERROR(L8/$N$5),"",L8/$N$5) | N8: =IF(ISERROR($G$31),"",$G$31) -> 0
C9: 3.1.4 | D9: Embalagens de consumo | E9: =-Balancete!F305 -> 0 | F9: =IF(ISERROR(E9/$E$5),"",E9/$E$5) | G9: =-Balancete!G305 -> 0 | J9: =C36 -> 3.5 | K9: =D36 -> Trabalhos para a Própria Empresa | L9: =IF(ISERROR($E$36),"",$E$36) -> 0 | M9: =IF(ISERROR(L9/$N$5),"",L9/$N$5) | N9: =IF(ISERROR($G$36),"",$G$36) -> 0
C10: 3.1.5 | D10: Subsídios a preços | E10: =-Balancete!F306 -> 0 | F10: =IF(ISERROR(E10/$E$5),"",E10/$E$5) | G10: =-Balancete!G306 -> 0 | J10: =C40 -> 3.6 | K10: =D40 -> Proveitos e Ganhos Financeiros Gerais | L10: =IF(ISERROR($E$40),"",$E$40) -> 10089891 | M10: =IF(ISERROR(L10/$N$5),"",L10/$N$5) | N10: =IF(ISERROR($G$40),"",$G$40) -> 0
C11: 3.1.6 | D11: Devoluções | E11: =-Balancete!F307 -> 0 | F11: =IF(ISERROR(E11/$E$5),"",E11/$E$5) | G11: =-Balancete!G307 -> 0 | J11: =C49 -> 3.7 | K11: =D49 -> Proveitos e Ganhos Financeiros em Susidiárias e Associadas | L11: =IF(ISERROR($E$49),"",$E$49) -> 0 | M11: =IF(ISERROR(L11/$N$5),"",L11/$N$5) | N11: =IF(ISERROR($G$49),"",$G$49) -> 0
C12: 3.1.7 | D12: Descontos e abatimentos | E12: =-Balancete!F308 -> 0 | F12: =IF(ISERROR(E12/$E$5),"",E12/$E$5) | G12: =-Balancete!G308 -> 0 | J12: =C53 -> 3.8 | K12: =D53 -> Outros Proveitos e Ganhos não Operacionais | L12: =IF(ISERROR($E$53),"",$E$53) -> 25000000 | M12: =IF(ISERROR(L12/$N$5),"",L12/$N$5) | N12: =IF(ISERROR($G$53),"",$G$53) -> 0
C13: 3.1.8 | F13: =IF(ISERROR(E13/$E$5),"",E13/$E$5) | J13: =C65 -> 3.9 | K13: =D65 -> Proveitos e Ganhos Extraordinários | L13: =IF(ISERROR($E$65),"",$E$65) -> 0 | M13: =IF(ISERROR(L13/$N$5),"",L13/$N$5) | N13: =IF(ISERROR($G$65),"",$G$65) -> 0
C14: 3.1.9 | F14: =IF(ISERROR(E14/$E$5),"",E14/$E$5)
C15: 3.2 | D15: Prestações de Serviço | E15: =IF(ISERROR(SUM(E16:E20)),"",SUM(E16:E20)) -> 1.7692123e+09 | G15: =IF(ISERROR(SUM(G16:G20)),"",SUM(G16:G20)) -> 0 | J15: Valor Total das Contas de Receitas
C16: 3.2.1 | D16: Serviços principais | E16: =-Balancete!F310 -> 8.3393805e+08 | F16: =IF(ISERROR(E16/$E$15),"",E16/$E$15) -> 0.4713612 | G16: =-Balancete!G310 -> 0 | J16: Total | L16: =IF(ISERROR(SUM($L$5:$L$13)),"",SUM($L$5:$L$13)) -> 4.8672211e+09 | N16: =IF(ISERROR(SUM($N$5:$N$13)),"",SUM($N$5:$N$13)) -> 0
C17: 3.2.2 | D17: Serviços Secundários | E17: =-Balancete!F311 -> 9.3527428e+08 | F17: =IF(ISERROR(E17/$E$15),"",E17/$E$15) -> 0.5286388 | G17: =-Balancete!G311 -> 0
C18: 3.2.3 | D18: Descontos e abatimentos | E18: =-Balancete!F312 -> 0 | F18: =IF(ISERROR(E18/$E$15),"",E18/$E$15) -> 0 | G18: =-Balancete!G312 -> 0
C19: 3.2.4 | F19: =IF(ISERROR(E19/$E$15),"",E19/$E$15) -> 0
C20: 3.2.9 | F20: =IF(ISERROR(E20/$E$15),"",E20/$E$15) -> 0
C21: 3.3 | D21: Outros Proveitos Operacionais | E21: =IF(ISERROR(SUM(E22:E30)),"",SUM(E22:E30)) -> 3.0629189e+09 | G21: =IF(ISERROR(SUM(G22:G30)),"",SUM(G22:G30)) -> 0
C22: 3.3.1 | D22: Serviços suplementares | E22: =-Balancete!F314 -> 600000 | F22: =IF(ISERROR(E22/$E$21),"",E22/$E$21) -> 0.00019589157 | G22: =-Balancete!G314 -> 0
C23: 3.3.2 | D23: Royalties | E23: =-Balancete!F319 -> 0 | F23: =IF(ISERROR(E23/$E$21),"",E23/$E$21) -> 0 | G23: =-Balancete!G319 -> 0
C24: 3.3.3 | D24: Subsídios à exploração | E24: =-Balancete!F320 -> 3.0623189e+09 | F24: =IF(ISERROR(E24/$E$21),"",E24/$E$21) -> 0.99980411 | G24: =-Balancete!G320 -> 0
C25: 3.3.4 | D25: Subsídios a investimentos | E25: =-Balancete!F321 -> 0 | F25: =IF(ISERROR(E25/$E$21),"",E25/$E$21) -> 0 | G25: =-Balancete!G321 -> 0
C26: 3.3.5 | D26: IVA | E26: =-Balancete!F322 -> 0 | F26: =IF(ISERROR(E26/$E$21),"",E26/$E$21) -> 0 | G26: =-Balancete!G322 -> 0
C27: 3.3.6 | D27: Outros proveitos e ganhos operacionais | E27: =-Balancete!F323 -> 0 | F27: =IF(ISERROR(E27/$E$21),"",E27/$E$21) -> 0 | G27: =-Balancete!G323 -> 0
C28: 3.3.7 | F28: =IF(ISERROR(E28/$E$21),"",E28/$E$21) -> 0
C29: 3.3.8 | F29: =IF(ISERROR(E29/$E$21),"",E29/$E$21) -> 0
C30: 3.3.9 | F30: =IF(ISERROR(E30/$E$21),"",E30/$E$21) -> 0
C31: 3.4 | D31: Varição nos Produtos Acabados e Produtos em Vias de Fabrico | E31: =IF(ISERROR(SUM(E32:E35)),"",SUM(E32:E35)) -> 0 | G31: =IF(ISERROR(SUM(G32:G35)),"",SUM(G32:G35)) -> 0
C32: 3.4.1 | D32: Produtos e trabalhos em curso | E32: =-Balancete!F325 -> 0 | F32: =IF(ISERROR(E32/$E$31),"",E32/$E$31) | G32: =-Balancete!G325 -> 0
C33: 3.4.2 | D33: Produtos acabados e intermédios | E33: =-Balancete!F326 -> 0 | F33: =IF(ISERROR(E33/$E$31),"",E33/$E$31) | G33: =-Balancete!G326 -> 0
C34: 3.4.3 | D34: Produtos intermédios | E34: =-Balancete!F327 -> 0 | F34: =IF(ISERROR(E34/$E$31),"",E34/$E$31) | G34: =-Balancete!G327 -> 0
C35: 3.4.4 | F35: =IF(ISERROR(E35/$E$31),"",E35/$E$31)
C36: 3.5 | D36: Trabalhos para a Própria Empresa | E36: =IF(ISERROR(SUM(E37:E39)),"",SUM(E37:E39)) -> 0 | G36: =IF(ISERROR(SUM(G37:G39)),"",SUM(G37:G39)) -> 0
C37: 3.5.1 | D37: Para imobilizado | E37: =-Balancete!F329 -> 0 | F37: =IF(ISERROR(E37/$E$36),"",E37/$E$36) | G37: =-Balancete!G329 -> 0
C38: 3.5.2 | D38: Para encargos a repartir por períodos futuros | E38: =-Balancete!F334 -> 0 | F38: =IF(ISERROR(E38/$E$36),"",E38/$E$36) | G38: =-Balancete!G334 -> 0
C39: 3.5.3 | F39: =IF(ISERROR(E39/$E$36),"",E39/$E$36)
C40: 3.6 | D40: Proveitos e Ganhos Financeiros Gerais | E40: =IF(ISERROR(SUM(E41:E48)),"",SUM(E41:E48)) -> 10089891 | G40: =IF(ISERROR(SUM(G41:G48)),"",SUM(G41:G48)) -> 0
C41: 3.6.1 | D41: Juros | E41: =-Balancete!F336 -> 168000 | F41: =IF(ISERROR(E41/$E$40),"",E41/$E$40) -> 0.016650328 | G41: =-Balancete!G336 -> 0
C42: 3.6.2 | D42: Diferenças de câmbio favoráveis | E42: =-Balancete!F341 -> 9921891.1 | F42: =IF(ISERROR(E42/$E$40),"",E42/$E$40) -> 0.98334967 | G42: =-Balancete!G341 -> 0
C43: 3.6.3 | D43: Descontos de pronto pagamento obtidos | E43: =-Balancete!F342 -> 0 | F43: =IF(ISERROR(E43/$E$40),"",E43/$E$40) -> 0 | G43: =-Balancete!G342 -> 0
C44: 3.6.4 | D44: Rendimentos de investimentos em imóveis | E44: =-Balancete!F343 -> 0 | F44: =IF(ISERROR(E44/$E$40),"",E44/$E$40) -> 0 | G44: =-Balancete!G343 -> 0
C45: 3.6.5 | D45: Rendimentos de participações de capital | E45: =-Balancete!F344 -> 0 | F45: =IF(ISERROR(E45/$E$40),"",E45/$E$40) -> 0 | G45: =-Balancete!G344 -> 0
C46: 3.6.6 | D46: Ganhos na alienação de aplicações financeiras | E46: =-Balancete!F348 -> 0 | F46: =IF(ISERROR(E46/$E$40),"",E46/$E$40) -> 0 | G46: =-Balancete!G348 -> 0
C47: 3.6.7 | D47: Redução de provisões | E47: =-Balancete!F351 -> 0 | F47: =IF(ISERROR(E47/$E$40),"",E47/$E$40) -> 0 | G47: =-Balancete!G351 -> 0
C48: 3.6.9 | F48: =IF(ISERROR(E48/$E$40),"",E48/$E$40) -> 0
C49: 3.7 | D49: Proveitos e Ganhos Financeiros em Susidiárias e Associadas | E49: =IF(ISERROR(SUM(E50:E52)),"",SUM(E50:E52)) -> 0 | G49: =IF(ISERROR(SUM(G50:G52)),"",SUM(G50:G52)) -> 0
C50: 3.7.1 | D50: Rendimento de participações de capital | E50: =-Balancete!F355 -> 0 | F50: =IF(ISERROR(E50/$E$49),"",E50/$E$49) | G50: =-Balancete!G355 -> 0
C51: 3.7.2 | F51: =IF(ISERROR(E51/$E$49),"",E51/$E$49)
C52: 3.7.3 | F52: =IF(ISERROR(E52/$E$49),"",E52/$E$49)
C53: 3.8 | D53: Outros Proveitos e Ganhos não Operacionais | E53: =IF(ISERROR(SUM(E54:E64)),"",SUM(E54:E64)) -> 25000000 | G53: =IF(ISERROR(SUM(G54:G64)),"",SUM(G54:G64)) -> 0
C54: 3.8.1 | D54: Redução de provisões | E54: =-Balancete!F357 -> 0 | F54: =IF(ISERROR(E54/$E$53),"",E54/$E$53) -> 0 | G54: =-Balancete!G357 -> 0
C55: 3.8.2 | D55: Anulação de provisões extraordinárias | E55: =-Balancete!F361 -> 0 | F55: =IF(ISERROR(E55/$E$53),"",E55/$E$53) -> 0 | G55: =-Balancete!G361 -> 0
C56: 3.8.3 | D56: Ganhos em imobilizações | E56: =-Balancete!F362 -> 25000000 | F56: =IF(ISERROR(E56/$E$53),"",E56/$E$53) -> 1 | G56: =-Balancete!G362 -> 0
C57: 3.8.4 | D57: Ganhos em existências | E57: =-Balancete!F363 -> 0 | F57: =IF(ISERROR(E57/$E$53),"",E57/$E$53) -> 0 | G57: =-Balancete!G363 -> 0
C58: 3.8.5 | D58: Recuperação de dívidas | E58: =-Balancete!F364 -> 0 | F58: =IF(ISERROR(E58/$E$53),"",E58/$E$53) -> 0 | G58: =-Balancete!G364 -> 0
C59: 3.8.6 | D59: Benefícios de penalidades contratuais | E59: =-Balancete!F365 -> 0 | F59: =IF(ISERROR(E59/$E$53),"",E59/$E$53) -> 0 | G59: =-Balancete!G365 -> 0
C60: 3.8.7 | D60: Descontinuidade de operações | E60: =-Balancete!F366 -> 0 | F60: =IF(ISERROR(E60/$E$53),"",E60/$E$53) -> 0 | G60: =-Balancete!G366 -> 0
C61: 3.8.8 | D61: Alterações de políticas contabilísticas | E61: =-Balancete!F367 -> 0 | F61: =IF(ISERROR(E61/$E$53),"",E61/$E$53) -> 0 | G61: =-Balancete!G367 -> 0
C62: 3.8.9 | D62: Correcções relativas a períodos anteriores | E62: =-Balancete!F368 -> 0 | F62: =IF(ISERROR(E62/$E$53),"",E62/$E$53) -> 0 | G62: =-Balancete!G368 -> 0
C63: 3.8.10 | D63: Outros ganhos e perdas não operacionais | E63: =-Balancete!F369 -> 0 | F63: =IF(ISERROR(E63/$E$53),"",E63/$E$53) -> 0 | G63: =-Balancete!G369 -> 0
C64: 3.8.11 | F64: =IF(ISERROR(E64/$E$53),"",E64/$E$53) -> 0
C65: 3.9 | D65: Proveitos e Ganhos Extraordinários | E65: =IF(ISERROR(SUM(E66:E72)),"",SUM(E66:E72)) -> 0 | G65: =IF(ISERROR(SUM(G66:G72)),"",SUM(G66:G72)) -> 0
C66: 3.9.1 | D66: Ganhos resultantes de catástrofes naturais | E66: =-Balancete!F371 -> 0 | F66: =IF(ISERROR(E66/$E$65),"",E66/$E$65) | G66: =-Balancete!G371 -> 0
C67: 3.9.2 | D67: Ganhos resultantes de convulsões políticas | E67: =-Balancete!F372 -> 0 | F67: =IF(ISERROR(E67/$E$65),"",E67/$E$65) | G67: =-Balancete!G372 -> 0
C68: 3.9.3 | D68: Ganhos resultantes de expropriações | E68: =-Balancete!F373 -> 0 | F68: =IF(ISERROR(E68/$E$65),"",E68/$E$65) | G68: =-Balancete!G373 -> 0
C69: 3.9.4 | D69: Ganhos resultantes de sinistros | E69: =-Balancete!F374 -> 0 | F69: =IF(ISERROR(E69/$E$65),"",E69/$E$65) | G69: =-Balancete!G374 -> 0
C70: 3.9.5 | D70: Subsídios | E70: =-Balancete!F375 -> 0 | F70: =IF(ISERROR(E70/$E$65),"",E70/$E$65) | G70: =-Balancete!G375 -> 0
C71: 3.9.6 | D71: Anulação de passivos não exigíveis | E71: =-Balancete!F376 -> 0 | F71: =IF(ISERROR(E71/$E$65),"",E71/$E$65) | G71: =-Balancete!G376 -> 0
C72: 3.9.7 | F72: =IF(ISERROR(E72/$E$65),"",E72/$E$65)

Sheet Custos por Natureza
B2: OBS: NÃO PREENCHER OS CAMPOS EM AZUL. PREENCHIMENTO AUTOMÁTICO.
E3: Ano Corrente | G3: Ano Anterior | L3: Ano Corrente | N3: Ano Anterior
C4: 4 | D4: Custos e Perdas por Natureza | E4: =IF(ISERROR($E$5+$E$15+$E$25+$E$35+$E$45+$E$55+$E$60+$E$73+$E$80),"",$E$5+$E$15+$E$25+$E$35+$E$45+$E$55+$E$60+$E$73+$E$80) -> 6.5414213e+09 | G4: =IF(ISERROR($G$5+$G$15+$G$25+$G$35+$G$45+$G$55+$G$60+$G$73+$G$80),"",$G$5+$G$15+$G$25+$G$35+$G$45+$G$55+$G$60+$G$73+$G$80) -> 0 | J4: 4 | K4: Custos e Perdas por Natureza - Total
C5: 4.1 | D5: Custo das Mercadorias Vendidas e das Matérias-primas Consumidas | E5: =IF(ISERROR(SUM(E6:E14)),"",SUM(E6:E14)) -> 1.7968478e+08 | G5: =IF(ISERROR(SUM(G6:G14)),"",SUM(G6:G14)) -> 0 | J5: =C5 -> 4.1 | K5: =D5 -> Custo das Mercadorias Vendidas e das Matérias-primas Consumidas | L5: =IF(ISERROR($E$5),"",$E$5) -> 1.7968478e+08 | M5: =IF(ISERROR(L5/$N$5),"",L5/$N$5) | N5: =IF(ISERROR($G$5),"",$G$5) -> 0
C6: 4.1.1 | D6: Matérias-primas | E6: =Balancete!F379 -> 1.7968478e+08 | F6: =IF(ISERROR(E6/$E$5),"",E6/$E$5) -> 1 | G6: =Balancete!G379 -> 0 | J6: =C15 -> 4.2 | K6: =D15 -> Custos com o Pessoal | L6: =IF(ISERROR($E$15),"",$E$15) -> 3.3178513e+09 | M6: =IF(ISERROR(L6/$N$5),"",L6/$N$5) | N6: =IF(ISERROR($G$15),"",$G$15) -> 0
C7: 4.1.2 | D7: Matérias subsidiárias | E7: =Balancete!F380 -> 0 | F7: =IF(ISERROR(E7/$E$5),"",E7/$E$5) -> 0 | G7: =Balancete!G380 -> 0 | J7: =C25 -> 4.3 | K7: =D25 -> Amortizações do Exercício | L7: =IF(ISERROR($E$25),"",$E$25) -> 5.0839795e+08 | M7: =IF(ISERROR(L7/$N$5),"",L7/$N$5) | N7: =IF(ISERROR($G$25),"",$G$25) -> 0
C8: 4.1.3 | D8: Materiais diversos | E8: =Balancete!F381 -> 0 | F8: =IF(ISERROR(E8/$E$5),"",E8/$E$5) -> 0 | G8: =Balancete!G381 -> 0 | J8: =C35 -> 4.4 | K8: =D35 -> Outros Custos e Perdas Operacionais | L8: =IF(ISERROR($E$35),"",$E$35) -> 1.5001827e+09 | M8: =IF(ISERROR(L8/$N$5),"",L8/$N$5) | N8: =IF(ISERROR($G$35),"",$G$35) -> 0
C9: 4.1.4 | D9: Embalagens de consumo | E9: =Balancete!F382 -> 0 | F9: =IF(ISERROR(E9/$E$5),"",E9/$E$5) -> 0 | G9: =Balancete!G382 -> 0 | J9: =C45 -> 4.5 | K9: =D45 -> Custos e Perdas Financeiras Gerais | L9: =IF(ISERROR($E$45),"",$E$45) -> 15878780 | M9: =IF(ISERROR(L9/$N$5),"",L9/$N$5) | N9: =IF(ISERROR($G$45),"",$G$45) -> 0
C10: 4.1.5 | D10: Outros materiais | E10: =Balancete!F383 -> 0 | F10: =IF(ISERROR(E10/$E$5),"",E10/$E$5) -> 0 | G10: =Balancete!G383 -> 0 | J10: =C55 -> 4.6 | K10: =D55 -> Custos e Perdas Financeiras para Filiais e Associadas | L10: =IF(ISERROR($E$55),"",$E$55) -> 0 | M10: =IF(ISERROR(L10/$N$5),"",L10/$N$5) | N10: =IF(ISERROR($G$55),"",$G$55) -> 0
C11: 4.1.6 | F11: =IF(ISERROR(E11/$E$5),"",E11/$E$5) -> 0 | J11: =C60 -> 4.7 | K11: =D60 -> Outros Custos e Perdas não Operacionais | L11: =IF(ISERROR($E$60),"",$E$60) -> 1.0194258e+09 | M11: =IF(ISERROR(L11/$N$5),"",L11/$N$5) | N11: =IF(ISERROR($G$60),"",$G$60) -> 0
C12: 4.1.7 | F12: =IF(ISERROR(E12/$E$5),"",E12/$E$5) -> 0 | J12: =C73 -> 4.8 | K12: =D73 -> Custos e Perdas Extraordinários | L12: =IF(ISERROR($E$73),"",$E$73) -> 0 | M12: =IF(ISERROR(L12/$N$5),"",L12/$N$5) | N12: =IF(ISERROR($G$73),"",$G$73) -> 0
C13: 4.1.8 | F13: =IF(ISERROR(E13/$E$5),"",E13/$E$5) -> 0 | L13: =IF(ISERROR($E$80),"",$E$80) -> 0 | M13: =IF(ISERROR(L13/$N$5),"",L13/$N$5) | N13: =IF(ISERROR($G$80),"",$G$80) -> 0
C14: 4.1.9 | F14: =IF(ISERROR(E14/$E$5),"",E14/$E$5) -> 0
C15: 4.2 | D15: Custos com o Pessoal | E15: =IF(ISERROR(SUM(E16:E24)),"",SUM(E16:E24)) -> 3.3178513e+09 | G15: =IF(ISERROR(SUM(G16:G24)),"",SUM(G16:G24)) -> 0 | J15: Total Contas de Custos e Perdas
C16: 4.2.1 | D16: Remunerações - órgãos sociais | E16: =Balancete!F385 -> 0 | F16: =IF(ISERROR(E16/$E$15),"",E16/$E$15) -> 0 | G16: =Balancete!G385 -> 0 | J16: Total | L16: =IF(ISERROR(SUM($L$5:$L$13)),"",SUM($L$5:$L$13)) -> 6.5414213e+09 | N16: =IF(ISERROR(SUM($N$5:$N$13)),"",SUM($N$5:$N$13)) -> 0
C17: 4.2.2 | D17: Remunerações - pessoal | E17: =Balancete!F386 -> 2.6529282e+09 | F17: =IF(ISERROR(E17/$E$15),"",E17/$E$15) -> 0.79959224 | G17: =Balancete!G386 -> 0
C18: 4.2.3 | D18: Pensões | E18: =Balancete!F387 -> 1.1206112e+08 | F18: =IF(ISERROR(E18/$E$15),"",E18/$E$15) -> 0.033775209 | G18: =Balancete!G387 -> 0
C19: 4.2.4 | D19: Prémios para pensões | E19: =Balancete!F388 -> 0 | F19: =IF(ISERROR(E19/$E$15),"",E19/$E$15) -> 0 | G19: =Balancete!G388 -> 0
C20: 4.2.5 | D20: Encargos sobre remunerações | E20: =Balancete!F389 -> 1.8558351e+08 | F20: =IF(ISERROR(E20/$E$15),"",E20/$E$15) -> 0.055934848 | G20: =Balancete!G389 -> 0
C21: 4.2.6 | D21: Seguros de acidentes de trabalho e doenças profissionais | E21: =Balancete!F390 -> 7513433.5 | F21: =IF(ISERROR(E21/$E$15),"",E21/$E$15) -> 0.002264548 | G21: =Balancete!G390 -> 0
C22: 4.2.7 | D22: Formações | E22: =Balancete!F391 -> 9835303.3 | F22: =IF(ISERROR(E22/$E$15),"",E22/$E$15) -> 0.0029643593 | G22: =Balancete!G391 -> 0
C23: 4.2.8 | D23: Subsídios e outros custos | E23: =Balancete!F392 -> 3.4992977e+08 | F23: =IF(ISERROR(E23/$E$15),"",E23/$E$15) -> 0.10546879 | G23: =Balancete!G392 -> 0
C24: 4.2.9 | F24: =IF(ISERROR(E24/$E$15),"",E24/$E$15) -> 0
C25: 4.3 | D25: Amortizações do Exercício | E25: =IF(ISERROR(SUM(E26:E34)),"",SUM(E26:E34)) -> 5.0839795e+08 | G25: =IF(ISERROR(SUM(G26:G34)),"",SUM(G26:G34)) -> 0
C26: 4.3.1 | D26: Imobilizações corpóreas | E26: =Balancete!F394 -> 4.9998089e+08 | F26: =IF(ISERROR(E26/$E$25),"",E26/$E$25) -> 0.98344395 | G26: =Balancete!G394 -> 0
C27: 4.3.2 | D27: Imobilizações incorpóreas | E27: =Balancete!F402 -> 8417063 | F27: =IF(ISERROR(E27/$E$25),"",E27/$E$25) -> 0.016556052 | G27: =Balancete!G402 -> 0
C28: 4.3.3 | F28: =IF(ISERROR(E28/$E$25),"",E28/$E$25) -> 0
C29: 4.3.4 | F29: =IF(ISERROR(E29/$E$25),"",E29/$E$25) -> 0
C30: 4.3.5 | F30: =IF(ISERROR(E30/$E$25),"",E30/$E$25) -> 0
C31: 4.3.6 | F31: =IF(ISERROR(E31/$E$25),"",E31/$E$25) -> 0
C32: 4.3.7 | F32: =IF(ISERROR(E32/$E$25),"",E32/$E$25) -> 0
C33: 4.3.8 | F33: =IF(ISERROR(E33/$E$25),"",E33/$E$25) -> 0
C34: 4.3.9 | F34: =IF(ISERROR(E34/$E$25),"",E34/$E$25) -> 0
C35: 4.4 | D35: Outros Custos e Perdas Operacionais | E35: =IF(ISERROR(SUM(E36:E44)),"",SUM(E36:E44)) -> 1.5001827e+09 | G35: =IF(ISERROR(SUM(G36:G44)),"",SUM(G36:G44)) -> 0
C36: 4.4.1 | D36: Subcontratos | E36: =Balancete!F409 -> 0 | F36: =IF(ISERROR(E36/$E$35),"",E36/$E$35) -> 0 | G36: =Balancete!G409 -> 0
C37: 4.4.2 | D37: Fornecimentos e serviços de terceiros | E37: =Balancete!F410 -> 1.4963019e+09 | F37: =IF(ISERROR(E37/$E$35),"",E37/$E$35) -> 0.9974131 | G37: =Balancete!G410 -> 0
C38: 4.4.3 | D38: Impostos | E38: =Balancete!F411 -> 3880817 | F38: =IF(ISERROR(E38/$E$35),"",E38/$E$35) -> 0.0025868963 | G38: =Balancete!G411 -> 0
C39: 4.4.4 | D39: Despesas confidenciais | E39: =Balancete!F412 -> 0 | F39: =IF(ISERROR(E39/$E$35),"",E39/$E$35) -> 0 | G39: =Balancete!G412 -> 0
C40: 4.4.5 | D40: Quotizações | E40: =Balancete!F413 -> 0 | F40: =IF(ISERROR(E40/$E$35),"",E40/$E$35) -> 0 | G40: =Balancete!G413 -> 0
C41: 4.4.6 | D41: Ofertas e amostras de existências | E41: =Balancete!F414 -> 0 | F41: =IF(ISERROR(E41/$E$35),"",E41/$E$35) -> 0 | G41: =Balancete!G414 -> 0
C42: 4.4.7 | D42: Outros custos e perdas operacionais | E42: =Balancete!F415 -> 0 | F42: =IF(ISERROR(E42/$E$35),"",E42/$E$35) -> 0 | G42: =Balancete!G415 -> 0
C43: 4.4.8 | F43: =IF(ISERROR(E43/$E$35),"",E43/$E$35) -> 0
C44: 4.4.9 | F44: =IF(ISERROR(E44/$E$35),"",E44/$E$35) -> 0
C45: 4.5 | D45: Custos e Perdas Financeiras Gerais | E45: =IF(ISERROR(SUM(E46:E54)),"",SUM(E46:E54)) -> 15878780 | G45: =IF(ISERROR(SUM(G46:G54)),"",SUM(G46:G54)) -> 0
C46: 4.5.1 | D46: Juros | E46: =Balancete!F417 -> 5589279.8 | F46: =IF(ISERROR(E46/$E$45),"",E46/$E$45) -> 0.3519968 | G46: =Balancete!G417 -> 0
C47: 4.5.2 | D47: Diferenças de câmbio desfavoráveis | E47: =Balancete!F422 -> 2003818.3 | F47: =IF(ISERROR(E47/$E$45),"",E47/$E$45) -> 0.12619473 | G47: =Balancete!G422 -> 0
C48: 4.5.3 | D48: Descontos de pronto pagamento concedidos | E48: =Balancete!F423 -> 0 | F48: =IF(ISERROR(E48/$E$45),"",E48/$E$45) -> 0 | G48: =Balancete!G423 -> 0
C49: 4.5.4 | D49: Amortizações de investimentos em imóveis | E49: =Balancete!F424 -> 0 | F49: =IF(ISERROR(E49/$E$45),"",E49/$E$45) -> 0 | G49: =Balancete!G424 -> 0
C50: 4.5.5 | D50: Provisões para aplicações financeiras | E50: =Balancete!F425 -> 0 | F50: =IF(ISERROR(E50/$E$45),"",E50/$E$45) -> 0 | G50: =Balancete!G425 -> 0
C51: 4.5.6 | D51: Perdas na alienação de aplicações financeiras | E51: =Balancete!F428 -> 0 | F51: =IF(ISERROR(E51/$E$45),"",E51/$E$45) -> 0 | G51: =Balancete!G428 -> 0
C52: 4.5.7 | D52: Serviços bancários | E52: =Balancete!F431 -> 8285682 | F52: =IF(ISERROR(E52/$E$45),"",E52/$E$45) -> 0.52180847 | G52: =Balancete!G431 -> 0
C53: 4.5.8 | F53: =IF(ISERROR(E53/$E$45),"",E53/$E$45) -> 0
C54: 4.5.9 | F54: =IF(ISERROR(E54/$E$45),"",E54/$E$45) -> 0
C55: 4.6 | D55: Custos e Perdas Financeiras para Filiais e Associadas | E55: =IF(ISERROR(SUM(E56:E59)),"",SUM(E56:E59)) -> 0 | G55: =IF(ISERROR(SUM(G56:G59)),"",SUM(G56:G59)) -> 0
C56: 4.6.1 | D56: Custos e perdas financeiras em filiais | E56: =Balancete!F433 -> 0 | F56: =IF(ISERROR(E56/$E$55),"",E56/$E$55) | G56: =Balancete!G433 -> 0
C57: 4.6.2 | D57: Custos e perdas financeiras em associadas | E57: =Balancete!F434 -> 0 | F57: =IF(ISERROR(E57/$E$55),"",E57/$E$55) | G57: =Balancete!G434 -> 0
C58: 4.6.3 | F58: =IF(ISERROR(E58/$E$55),"",E58/$E$55)
C59: 4.6.9 | F59: =IF(ISERROR(E59/$E$55),"",E59/$E$55)
C60: 4.7 | D60: Outros Custos e Perdas não Operacionais | E60: =IF(ISERROR(SUM(E61:E72)),"",SUM(E61:E72)) -> 1.0194258e+09 | G60: =IF(ISERROR(SUM(G61:G72)),"",SUM(G61:G72)) -> 0
C61: 4.7.1 | D61: Provisões do exercício | E61: =Balancete!F436 -> 5.1023464e+08 | F61: =IF(ISERROR(E61/$E$60),"",E61/$E$60) -> 0.5005118 | G61: =Balancete!G436 -> 0
C62: 4.7.2 | D62: Amortizações extraordinárias | E62: =Balancete!F440 -> 0 | F62: =IF(ISERROR(E62/$E$60),"",E62/$E$60) -> 0 | G62: =Balancete!G440 -> 0
C63: 4.7.3 | D63: Perdas em imobilizações | E63: =Balancete!F441 -> 0 | F63: =IF(ISERROR(E63/$E$60),"",E63/$E$60) -> 0 | G63: =Balancete!G441 -> 0
C64: 4.7.4 | D64: Perdas em existências | E64: =Balancete!F442 -> 0 | F64: =IF(ISERROR(E64/$E$60),"",E64/$E$60) -> 0 | G64: =Balancete!G442 -> 0
C65: 4.7.5 | D65: Dívidas incobráveis | E65: =Balancete!F443 -> 4.1549577e+08 | F65: =IF(ISERROR(E65/$E$60),"",E65/$E$60) -> 0.40757824 | G65: =Balancete!G443 -> 0
C66: 4.7.6 | D66: Multas e penalidades contratuais | E66: =Balancete!F444 -> 77000 | F66: =IF(ISERROR(E66/$E$60),"",E66/$E$60) -> 7.5532717e-05 | G66: =Balancete!G444 -> 0
C67: 4.7.7 | D67: Custos de reestruturação | E67: =Balancete!F445 -> 0 | G67: =Balancete!G445 -> 0
C68: 4.7.8 | D68: Descontinuidade de operações | E68: =Balancete!F446 -> 0 | G68: =Balancete!G446 -> 0
C69: 4.7.9 | D69: Alteração de políticas contabilísticas | E69: =Balancete!F447 -> 0 | G69: =Balancete!G447 -> 0
C70: 4.7.10 | D70: Correcções relativas a períodos anteriores | E70: =Balancete!F448 -> 93618388 | G70: =Balancete!G448 -> 0
C71: 4.7.11 | D71: Outros custos e eerdas não operacionais | E71: =Balancete!F449 -> 0 | G71: =Balancete!G449 -> 0
C72: 4.7.12
C73: 4.8 | D73: Custos e Perdas Extraordinários | E73: =IF(ISERROR(SUM(E74:E79)),"",SUM(E74:E79)) -> 0 | G73: =IF(ISERROR(SUM(G74:G79)),"",SUM(G74:G79)) -> 0
C74: 4.8.1 | D74: Perdas resultantes de catástrofes naturais | E74: =Balancete!F451 -> 0 | F74: =IF(ISERROR(E74/$E$73),"",E74/$E$73) | G74: =Balancete!G451 -> 0
C75: 4.8.2 | D75: Perdas resultantes de convulsões políticas | E75: =Balancete!F452 -> 0 | F75: =IF(ISERROR(E75/$E$73),"",E75/$E$73) | G75: =Balancete!G452 -> 0
C76: 4.8.3 | D76: Perdas resultantes de expropriações | E76: =Balancete!F453 -> 0 | F76: =IF(ISERROR(E76/$E$73),"",E76/$E$73) | G76: =Balancete!G453 -> 0
C77: 4.8.4 | D77: Perdas resultantes de sinistros | E77: =Balancete!F454 -> 0 | F77: =IF(ISERROR(E77/$E$73),"",E77/$E$73) | G77: =Balancete!G454 -> 0
C78: 4.8.5 | F78: =IF(ISERROR(E78/$E$73),"",E78/$E$73)
C79: 4.8.6 | F79: =IF(ISERROR(E79/$E$73),"",E79/$E$73)

Sheet DRE
B2: OBS: PLANILHA AUTOMÁTICA. NÃO PREENCHER NENHUM CAMPO.
E3: Ano Corrente | G3: Ano Anterior | L3: Ano Corrente | N3: Ano Anterior
C4: ='Proveitos por Natureza'!J4 -> 3 | D4: Contas de Proveitos e Ganhos por Natureza - Total | J4: ='Custos por Natureza'!J4 -> 4 | K4: Contas de Custos e Perdas por Natureza - Total
C5: ='Proveitos por Natureza'!J5 -> 3.1 | D5: ='Proveitos por Natureza'!K5 -> Vendas | E5: =IF(ISERROR('Proveitos por Natureza'!L5),"",'Proveitos por Natureza'!L5) -> 0 | F5: =IF(ISERROR(E5/$E$14),"",E5/$E$14) -> 0 | G5: =IF(ISERROR('Proveitos por Natureza'!N5),"",'Proveitos por Natureza'!N5) -> 0 | J5: ='Custos por Natureza'!J5 -> 4.1 | K5: ='Custos por Natureza'!K5 -> Custo das Mercadorias Vendidas e das Matérias-primas Consumidas | L5: =IF(ISERROR('Custos por Natureza'!L5),"",'Custos por Natureza'!L5) -> 1.7968478e+08 | M5: =IF(ISERROR(L5/$L$14),"",L5/$L$14) -> 0.027468768 | N5: =IF(ISERROR('Custos por Natureza'!N5),"",'Custos por Natureza'!N5) -> 0
C6: ='Proveitos por Natureza'!J6 -> 3.2 | D6: ='Proveitos por Natureza'!K6 -> Prestações de Serviço | E6: =IF(ISERROR('Proveitos por Natureza'!L6),"",'Proveitos por Natureza'!L6) -> 1.7692123e+09 | F6: =IF(ISERROR(E6/$E$14),"",E6/$E$14) -> 0.36349537 | G6: =IF(ISERROR('Proveitos por Natureza'!N6),"",'Proveitos por Natureza'!N6) -> 0 | J6: ='Custos por Natureza'!J6 -> 4.2 | K6: ='Custos por Natureza'!K6 -> Custos com o Pessoal | L6: =IF(ISERROR('Custos por Natureza'!L6),"",'Custos por Natureza'!L6) -> 3.3178513e+09 | M6: =IF(ISERROR(L6/$L$14),"",L6/$L$14) -> 0.50720649 | N6: =IF(ISERROR('Custos por Natureza'!N6),"",'Custos por Natureza'!N6) -> 0
C7: ='Proveitos por Natureza'!J7 -> 3.3 | D7: ='Proveitos por Natureza'!K7 -> Outros Proveitos Operacionais | E7: =IF(ISERROR('Proveitos por Natureza'!L7),"",'Proveitos por Natureza'!L7) -> 3.0629189e+09 | F7: =IF(ISERROR(E7/$E$14),"",E7/$E$14) -> 0.6292952 | G7: =IF(ISERROR('Proveitos por Natureza'!N7),"",'Proveitos por Natureza'!N7) -> 0 | J7: ='Custos por Natureza'!J7 -> 4.3 | K7: ='Custos por Natureza'!K7 -> Amortizações do Exercício | L7: =IF(ISERROR('Custos por Natureza'!L7),"",'Custos por Natureza'!L7) -> 5.0839795e+08 | M7: =IF(ISERROR(L7/$L$14),"",L7/$L$14) -> 0.077719799 | N7: =IF(ISERROR('Custos por Natureza'!N7),"",'Custos por Natureza'!N7) -> 0
C8: ='Proveitos por Natureza'!J8 -> 3.4 | D8: ='Proveitos por Natureza'!K8 -> Varição nos Produtos Acabados e Produtos em Vias de Fabrico | E8: =IF(ISERROR('Proveitos por Natureza'!L8),"",'Proveitos por Natureza'!L8) -> 0 | F8: =IF(ISERROR(E8/$E$14),"",E8/$E$14) -> 0 | G8: =IF(ISERROR('Proveitos por Natureza'!N8),"",'Proveitos por Natureza'!N8) -> 0 | J8: ='Custos por Natureza'!J8 -> 4.4 | K8: ='Custos por Natureza'!K8 -> Outros Custos e Perdas Operacionais | L8: =IF(ISERROR('Custos por Natureza'!L8),"",'Custos por Natureza'!L8) -> 1.5001827e+09 | M8: =IF(ISERROR(L8/$L$14),"",L8/$L$14) -> 0.22933589 | N8: =IF(ISERROR('Custos por Natureza'!N8),"",'Custos por Natureza'!N8) -> 0
C9: ='Proveitos por Natureza'!J9 -> 3.5 | D9: ='Proveitos por Natureza'!K9 -> Trabalhos para a Própria Empresa | E9: =IF(ISERROR('Proveitos por Natureza'!L9),"",'Proveitos por Natureza'!L9) -> 0 | F9: =IF(ISERROR(E9/$E$14),"",E9/$E$14) -> 0 | G9: =IF(ISERROR('Proveitos por Natureza'!N9),"",'Proveitos por Natureza'!N9) -> 0 | J9: ='Custos por Natureza'!J9 -> 4.5 | K9: ='Custos por Natureza'!K9 -> Custos e Perdas Financeiras Gerais | L9: =IF(ISERROR('Custos por Natureza'!L9),"",'Custos por Natureza'!L9) -> 15878780 | M9: =IF(ISERROR(L9/$L$14),"",L9/$L$14) -> 0.0024274205 | N9: =IF(ISERROR('Custos por Natureza'!N9),"",'Custos por Natureza'!N9) -> 0
C10: ='Proveitos por Natureza'!J10 -> 3.6 | D10: ='Proveitos por Natureza'!K10 -> Proveitos e Ganhos Financeiros Gerais | E10: =IF(ISERROR('Proveitos por Natureza'!L10),"",'Proveitos por Natureza'!L10) -> 10089891 | F10: =IF(ISERROR(E10/$E$14),"",E10/$E$14) -> 0.0020730291 | G10: =IF(ISERROR('Proveitos por Natureza'!N10),"",'Proveitos por Natureza'!N10) -> 0 | J10: ='Custos por Natureza'!J10 -> 4.6 | K10: ='Custos por Natureza'!K10 -> Custos e Perdas Financeiras para Filiais e Associadas | L10: =IF(ISERROR('Custos por Natureza'!L10),"",'Custos por Natureza'!L10) -> 0 | M10: =IF(ISERROR(L10/$L$14),"",L10/$L$14) -> 0 | N10: =IF(ISERROR('Custos por Natureza'!N10),"",'Custos por Natureza'!N10) -> 0
C11: ='Proveitos por Natureza'!J11 -> 3.7 | D11: ='Proveitos por Natureza'!K11 -> Proveitos e Ganhos Financeiros em Susidiárias e Associadas | E11: =IF(ISERROR('Proveitos por Natureza'!L11),"",'Proveitos por Natureza'!L11) -> 0 | F11: =IF(ISERROR(E11/$E$14),"",E11/$E$14) -> 0 | G11: =IF(ISERROR('Proveitos por Natureza'!N11),"",'Proveitos por Natureza'!N11) -> 0 | J11: ='Custos por Natureza'!J11 -> 4.7 | K11: ='Custos por Natureza'!K11 -> Outros Custos e Perdas não Operacionais | L11: =IF(ISERROR('Custos por Natureza'!L11),"",'Custos por Natureza'!L11) -> 1.0194258e+09 | M11: =IF(ISERROR(L11/$L$14),"",L11/$L$14) -> 0.15584164 | N11: =IF(ISERROR('Custos por Natureza'!N11),"",'Custos por Natureza'!N11) -> 0
C12: ='Proveitos por Natureza'!J12 -> 3.8 | D12: ='Proveitos por Natureza'!K12 -> Outros Proveitos e Ganhos não Operacionais | E12: =IF(ISERROR('Proveitos por Natureza'!L12),"",'Proveitos por Natureza'!L12) -> 25000000 | F12: =IF(ISERROR(E12/$E$14),"",E12/$E$14) -> 0.0051364011 | G12: =IF(ISERROR('Proveitos por Natureza'!N12),"",'Proveitos por Natureza'!N12) -> 0 | J12: ='Custos por Natureza'!J12 -> 4.8 | K12: ='Custos por Natureza'!K12 -> Custos e Perdas Extraordinários | L12: =IF(ISERROR('Custos por Natureza'!L12),"",'Custos por Natureza'!L12) -> 0 | M12: =IF(ISERROR(L12/$L$14),"",L12/$L$14) -> 0 | N12: =IF(ISERROR('Custos por Natureza'!N12),"",'Custos por Natureza'!N12) -> 0
C13: ='Proveitos por Natureza'!J13 -> 3.9 | D13: ='Proveitos por Natureza'!K13 -> Proveitos e Ganhos Extraordinários | E13: =IF(ISERROR('Proveitos por Natureza'!L13),"",'Proveitos por Natureza'!L13) -> 0 | F13: =IF(ISERROR(E13/$E$14),"",E13/$E$14) -> 0 | G13: =IF(ISERROR('Proveitos por Natureza'!N13),"",'Proveitos por Natureza'!N13) -> 0 | J13: ='Custos por Natureza'!J13 -> 0 | K13: ='Custos por Natureza'!K13 -> 0 | L13: =IF(ISERROR('Custos por Natureza'!L13),"",'Custos por Natureza'!L13) -> 0 | M13: =IF(ISERROR(L13/$L$14),"",L13/$L$14) -> 0 | N13: =IF(ISERROR('Custos por Natureza'!N13),"",'Custos por Natureza'!N13) -> 0
C14: Contas de Resultado Credora (Receitas) - Resultado | E14: =IF(ISERROR(SUM(E5:E13)),"",SUM(E5:E13)) -> 4.8672211e+09 | G14: =IF(ISERROR(SUM(G5:G13)),"",SUM(G5:G13)) -> 0 | J14: Contas de Resultado Devedoras (Custos e Despesas) - Resultado | L14: =IF(ISERROR(SUM(L5:L13)),"",SUM(L5:L13)) -> 6.5414213e+09 | N14: =IF(ISERROR(SUM(N5:N13)),"",SUM(N5:N13)) -> 0
C16: Demonstração do Resultado do Exercício (DRE)
C17: Proveitos por Natureza | E17: =IF(ISERROR($E$14),"",$E$14) -> 4.8672211e+09 | F17: =IF(ISERROR($E$17/$I$17),"",$E$17/$I$17) -> 0.42662579 | G17: =IF(ISERROR($G$14),"",$G$14) -> 0 | I17: =IF(ISERROR(SUM(E17:E18)),"",SUM(E17:E18)) -> 1.1408642e+10
C18: Custos por Natureza | E18: =IF(ISERROR($L$14),"",$L$14) -> 6.5414213e+09 | F18: =IF(ISERROR($E$18/$I$17),"",$E$18/$I$17) -> 0.57337421 | G18: =IF(ISERROR($N$14),"",$N$14) -> 0
C19: Resultado do Exercício | E19: =IF(ISERROR(E17-E18),"",E17-E18) -> -1.6742002e+09 | G19: =IF(ISERROR(G17-G18),"",G17-G18) -> 0
C21: Resultados Operacionais | E21: =SUM(E5:E7)-SUM(L5:L8) -> -6.7398551e+08 | G21: =SUM(G5:G7)-SUM(N5:N8) -> 0
C22: Resultados Financeiros | E22: =E10-L9 -> -5788889 | G22: =G10-N9 -> 0
C23: Resultados Não Operacionais | E23: =E12-L11 -> -9.944258e+08 | G23: =-(G12-N11) -> 0
C24: Resultados Antes de Impostps | E24: =E21+E22+E23 -> -1.6742002e+09 | G24: =G21+G22+G23 -> 0
C25: Imposto sobre o Rendimento | G25: 4562353
C26: Resultados Líquidos das Actividades Correntes | E26: =E24-E25 -> -1.6742002e+09 | G26: =G24-G25 -> -4562353
C27: Resultados Líquidos do Exercício

Sheet Gráficos
B2: OBS: PLANILHA AUTOMÁTICA. NÃO PREENCHER NENHUM CAMPO.
C4: 1 - ATIVO CIRCULANTE
C14: 1.1 - ATIVO NÃO CIRCULANTE
C24: 1.2 - PASSIVO CIRCULANTE
C34: 1.3 - PASSIVO NÃO CIRCULANTE
L35: Balanço Patrimonial
L36: =IF(ISERROR('Activos Correntes'!$D$4),"",'Activos Correntes'!$D$4) -> Activos Correntes (Bens e Direitos) | M36: =IF(ISERROR('Activos Correntes'!$E$4),"",'Activos Correntes'!$E$4) -> 1.5650931e+09 | N36: =IF(ISERROR($M$36/$M$40),"",$M$36/$M$40) -> 0.22525549
L37: =IF(ISERROR('Activos Não Correntes'!$D$4),"",'Activos Não Correntes'!$D$4) -> Activos Não Correntes | M37: =IF(ISERROR('Activos Não Correntes'!$E$4),"",'Activos Não Correntes'!$E$4) -> 3.4449505e+09 | N37: =IF(ISERROR($M$37/$M$40),"",$M$37/$M$40) -> 0.49581331
L38: =IF(ISERROR('Passivo Corrente'!$D$4),"",'Passivo Corrente'!$D$4) -> Passivo Corrente | M38: =IF(ISERROR('Passivo Corrente'!$E$4),"",'Passivo Corrente'!$E$4) -> 1.9380363e+09 | N38: =IF(ISERROR($M$38/$M$40),"",$M$38/$M$40) -> 0.2789312
L39: =IF(ISERROR('Passivo Não Corrente'!$D$4),"",'Passivo Não Corrente'!$D$4) -> Passivo Não Corrente | M39: =IF(ISERROR('Passivo Não Corrente'!$E$4),"",'Passivo Não Corrente'!$E$4) -> 0 | N39: =IF(ISERROR($M$39/$M$40),"",$M$39/$M$40) -> 0
M40: =IF(ISERROR(SUM($M$36:$M$39)),"",SUM($M$36:$M$39)) -> 6.9480799e+09
C44: 1.4 - BALANÇO Patrimonial
C54: 2 - RECEITAS - DRE
C64: 2.1 - DESPESAS (DRE)
C74: 2.2 - DEMONSTRAÇÃO DE RESULTADO DE EXERCÍCIO (DRE)

Sheet Indicadores de Endividamento
B2: OBS: PLANILHA AUTOMÁTICA. NÃO PREENCHER NENHUM CAMPO.
C4: Endividamento por capital de terceiros | F4: Análise | U4: =IF(ISERROR(SUM(U5:U6)),"",SUM(U5:U6)) -> 1.9380363e+09
C5: Passivo Corrente | D5: =IF(ISERROR('Passivo Corrente'!$E$4),"",'Passivo Corrente'!$E$4) -> 1.9380363e+09 | F5: =IF($D$8<=1,"A empresa não possui extrema dependência de capital de terceiro, o que melhora a solvência","A empresa possui extrema dependência de capital de terceiros o que pode denotar insolvência, porém em alguns segmentos o índice de endividamento de capital de terceiros é comum e necessário no mercado, recomendamos uma análise mais profunda") -> A empresa não possui extrema dependência de capital de terceiro, o que melhora a solvência | U5: =IF(ISERROR(D22),"",D22) -> 1.9380363e+09
C6: Exigível a Longo Prazo | D6: =IF(ISERROR('Passivo Não Corrente'!$L$23),"",'Passivo Não Corrente'!$L$23) -> 0 | U6: =IF(ISERROR(#REF!),"",#REF!)
C7: Capital Próprio | D7: =IF(ISERROR('Capital Próprio'!$E$4),"",'Capital Próprio'!$E$4) -> 3.181566e+09
C8: Resultado | D8: =IF(ISERROR(ROUND(SUM(D5:D6)/D7,2)),"",ROUND(SUM(D5:D6)/D7,2)) -> 0.61
C10: Endividamento Financeiro x Capital de Terceiros | F10: Análise
C11: Obrigações Financeiras | D11: =IF(ISERROR('Passivo Corrente'!L6+'Passivo Não Corrente'!L6),"",'Passivo Corrente'!L6+'Passivo Não Corrente'!L6) -> 0 | F11: =IF(ISERROR("O percentual que a empresa possui referente a dívidas com estabelecimentos bancários no país e no exterior em relação ao capital de terceiros é de " & ($D$14)),"","O percentual que a empresa possui referente a dívidas com estabelecimentos bancários no país e no exterior em relação ao capital de terceiros é de " & ($D$14)) -> O percentual que a empresa possui referente a dívidas com estabelecimentos bancários no país e no exterior em relação ao capital de terceiros é de 0%
C12: Passivo Corrente | D12: =IF(ISERROR('Passivo Corrente'!E4),"",'Passivo Corrente'!E4) -> 1.9380363e+09
C13: Exigível a Longo Prazo | D13: =IF(ISERROR('Passivo Não Corrente'!$L$23),"",'Passivo Não Corrente'!$L$23) -> 0
C14: Resultado | D14: =IF(ISERROR(ROUND((D11/SUM(D12:D13))*100,2)&"%"),"",ROUND((D11/SUM(D12:D13))*100,2)&"%") -> 0%
C16: Endividamento Financeiro x Capital Próprio | F16: Análise
C17: Obrigações Financeiras | D17: =IF(ISERROR('Passivo Corrente'!L6+'Passivo Não Corrente'!L6),"",'Passivo Corrente'!L6+'Passivo Não Corrente'!L6) -> 0 | F17: =IF(ISERROR("O percentual que empresa possui referente a dívidas com estabelecimentos bancários no país e no exterior em relação ao capital próprio é de " & ($D$19)),"","O percentual que empresa possui referente a dívidas com estabelecimentos bancários no país e no exterior em relação ao capital próprio é de " & ($D$19)) -> O percentual que empresa possui referente a dívidas com estabelecimentos bancários no país e no exterior em relação ao capital próprio é de 0%
C18: Capital Próprio | D18: =IF(ISERROR('Capital Próprio'!$E$4),"",'Capital Próprio'!$E$4) -> 3.181566e+09
C19: Resultado | D19: =IF(ISERROR(ROUND((D17/D18)*100,2)&"%"),"",ROUND((D17/D18)*100,2)&"%") -> 0%
C21: Composição do Endividamento | F21: Análise
C22: Passivo Corrente | D22: =IF(ISERROR('Passivo Corrente'!$E$4),"",'Passivo Corrente'!$E$4) -> 1.9380363e+09 | F22: =IF($D$24<=50%,"A empresa possui menos de 50% do Capital de Terceiros comprometido no curto prazo, ou seja, possui uma folga para pagamento. Quanto menor melhor.","A empresa possui mais de 50% do Capital de Terceiros comprometido no curto prazo, ou seja, possui uma grande quantidade de pagamentos a serem feitas ainda no exercício. Quanto maior mais arriscado.") -> A empresa possui mais de 50% do Capital de Terceiros comprometido no curto prazo, ou seja, possui uma grande quantidade de pagamentos a serem feitas ainda no exercício. Quanto maior mais arriscado.
C23: Passivo Não Corrente | D23: =IF(ISERROR('Passivo Não Corrente'!E4),"",'Passivo Não Corrente'!E4) -> 0
C24: Resultado | D24: =IF(ISERROR(ROUND((D22/SUM(D22:D23))*100,2)&"%"),"",ROUND((D22/SUM(D22:D23))*100,2)&"%") -> 100%
C26: Imobilização Capital Próprio | F26: Análise
C27: Activo Não Corrente | D27: =IF(ISERROR('Activos Não Correntes'!$L$24),"",'Activos Não Correntes'!$L$24) -> 3.4449505e+09 | F27: =IF(ISERROR("O Capital Próprio financia " & ($D$29) & " do activo não corrente da empresa, o que indica menor necessidade de capital de terceiros para manutenção dos negócios"),"","O Capital Próprio financia " & ($D$29) & " do activo não corrente da empresa, o que indica menor necessidade de capital de terceiros para manutenção dos negócios") -> O Capital Próprio financia 108,28% do activo não corrente da empresa, o que indica menor necessidade de capital de terceiros para manutenção dos negócios
C28: Capital Próprio | D28: =IF(ISERROR('Capital Próprio'!$E$4),"",'Capital Próprio'!$E$4) -> 3.181566e+09
C29: Resultado | D29: =IF(ISERROR(ROUND((D27*100)/D28,2) & "%"),"",ROUND((D27*100)/D28,2) & "%") -> 108,28%

Sheet Indicadores de Liquidez
B2: OBS: PLANILHA AUTOMÁTICA. NÃO PREENCHER NENHUM CAMPO.
C4: Liquidez Corrente | E4: Análise
C5: Activo Corrente | D5: =IF(ISERROR('Activos Correntes'!E4),"",'Activos Correntes'!E4) -> 1.5650931e+09 | E5: =IF($D$7>=1,"A empresa possui recursos para honrar seus compromissos de curto prazo.","A empresa não possui recursos para honrar seus compromissos de curto prazo") -> A empresa não possui recursos para honrar seus compromissos de curto prazo
C6: Passivo Corrente | D6: =IF(ISERROR('Passivo Corrente'!$E$4),"",'Passivo Corrente'!$E$4) -> 1.9380363e+09
C7: Total de Liquidez Corrente | D7: =IF(ISERROR(ROUND(D5/D6,2)),"",ROUND(D5/D6,2)) -> 0.81
C9: Liquidez Imediata | E9: Análise
C10: Disponibilidades | D10: =IF(ISERROR('Activos Correntes'!L5),"",'Activos Correntes'!L5) -> 0 | E10: =IF($D$12>=1,"A empresa possui recursos financeiros disponíveis para honrar seus compromisso de curto prazo.","A empresa não possui recursos financeiros disponíveis para honrar seus compromisso de curto prazo, ficando dependente da operação e demais recursos.") -> A empresa não possui recursos financeiros disponíveis para honrar seus compromisso de curto prazo, ficando dependente da operação e demais recursos.
C11: Passivo Corrente | D11: =IF(ISERROR('Passivo Corrente'!$E$4),"",'Passivo Corrente'!$E$4) -> 1.9380363e+09
C12: Total de Liquidez Imediata | D12: =IF(ISERROR(ROUND(D10/D11,2)),"",ROUND(D10/D11,2)) -> 0
C14: Liquidez Seca | E14: Análise
C15: Activo Corrente | D15: =IF(ISERROR('Activos Correntes'!$E$4),"",'Activos Correntes'!$E$4) -> 1.5650931e+09 | E15: =IF($D$18>=1,"A empresa tem recursos suficientes para arcar com os compromisso de curto prazo sem depender da venda de seus estoques.","A empresa não possui recursos suficientes para arcar com os compromissos de curto prazo sem que dependa da venda de seus estoques.") -> A empresa não possui recursos suficientes para arcar com os compromissos de curto prazo sem que dependa da venda de seus estoques.
C16: Existências | D16: =IF(ISERROR('Activos Correntes'!$L$7),"",'Activos Correntes'!$L$7) -> 52657493
C17: Passivo Corrente | D17: =IF(ISERROR('Passivo Corrente'!$E$4),"",'Passivo Corrente'!$E$4) -> 1.9380363e+09
C18: Total de Liquidez Seca | D18: =IF(ISERROR(ROUND((D15-D16)/D17,2)),"",ROUND((D15-D16)/D17,2)) -> 0.78
C20: Liquidez Geral | E20: Análise
C21: Activo Corrente | D21: =IF(ISERROR('Activos Correntes'!$E$4),"",'Activos Correntes'!$E$4) -> 1.5650931e+09 | E21: =IF($D$25>=1,"A empresa possui recursos suficientes para arcar com todos os seus compromissos.","A empresa não possui recursos o suficiente para arcar com os seus compromissos.") -> A empresa possui recursos suficientes para arcar com todos os seus compromissos.
C22: Activo Realizável a Longo Prazo | D22: =IF(ISERROR('Activos Não Correntes'!$L$21),"",'Activos Não Correntes'!$L$21) -> 3.4449505e+09
C23: Passivo Corrente | D23: =IF(ISERROR('Passivo Corrente'!$E$4),"",'Passivo Corrente'!$E$4) -> 1.9380363e+09
C24: Passivo Não Corrente | D24: =IF(ISERROR('Passivo Não Corrente'!$E$4),"",'Passivo Não Corrente'!$E$4) -> 0
C25: Total de Liquidez Corrente | D25: =IF(ISERROR(ROUND((D21+D22)/(D23+D24),2)),"",ROUND((D21+D22)/(D23+D24),2)) -> 2.59
D26: =IF(ISERROR(#REF!+#REF!),"",#REF!+#REF!)

Sheet Indicadores da Operação
B2: OBS: PLANILHA AUTOMÁTICA. NÃO PREENCHER NENHUM CAMPO.
C4: Prazo Médio de Recebimento de Vendas | F4: Análise
C5: Contas a Receber | D5: =IF(ISERROR('Activos Correntes'!$L$6),"",'Activos Correntes'!$L$6) -> 1.3402124e+09 | F5: =IF(ISERROR("O prazo médio para o recebimento das vendas ao longo do ano é de " &ROUND($D$7,2) & " dias"),"","O prazo médio para o recebimento das vendas ao longo do ano é de " &ROUND($D$7,2) & " dias") -> O prazo médio para o recebimento das vendas ao longo do ano é de 100,5 dias
C6: Receitas de Vendas | D6: =IF(ISERROR(SUM(DRE!E5:E12)),"",SUM(DRE!E5:E12)) -> 4.8672211e+09
C7: Resultado | D7: =IF(ISERROR(ROUND((D5*365)/D6,2)),"",ROUND((D5*365)/D6,2)) -> 100.5
C9: Prazo Médio de Renovação dos Estoques | F9: Análise
C10: Existências | D10: =IF(ISERROR('Activos Correntes'!$L$5),"",'Activos Correntes'!$L$5) -> 0 | F10: =IF(ISERROR("O prazo médio de renovação do estoque ao longo do ano é de " & ROUND($D$12,2) & " dias"),"","O prazo médio de renovação do estoque ao longo do ano é de " & ROUND($D$12,2) & " dias") -> O prazo médio de renovação do estoque ao longo do ano é de 0 dias
C11: Custo de Produtos Vendidos | D11: =IF(ISERROR('Custos por Natureza'!$L$5),"",'Custos por Natureza'!$L$5) -> 1.7968478e+08
C12: Resultado | D12: =IF(ISERROR(ROUND((D10*365)/D11,2)),"",ROUND((D10*365)/D11,2)) -> 0
C14: Prazo Médio de Pagamento de Compras | F14: Análise
C15: Fornecedores | D15: =IF(ISERROR('Passivo Corrente'!$L$5),"",'Passivo Corrente'!$L$5) -> 1.006981e+09 | F15: =IF(ISERROR("O prazo médio de pagamento dos fornecedores ao longo do ano é de " & ROUND($D$17,2) & " dias"),"","O prazo médio de pagamento dos fornecedores ao longo do ano é de " & ROUND($D$17,2) & " dias") -> O prazo médio de pagamento dos fornecedores ao longo do ano é de 2045,52 dias
C16: Compras (CMV) | D16: =IF(ISERROR(DRE!$L$5),"",DRE!$L$5) -> 1.7968478e+08
C17: Resultado | D17: =IF(ISERROR(ROUND((D15*365)/D16,2)),"",ROUND((D15*365)/D16,2)) -> 2045.52
C19: Ciclo Financeiro | F19: Análise
C20: Prazo Médio de Recebimento de Vendas | D20: =IF(ISERROR($D$7),"",$D$7) -> 100.5 | F20: =IF(ISERROR("A empresa demora " & ROUND($D$23,2) & " dias para que os recursos aplicados na operação retornem ao caixa. Quanto maior o ciclo, maior a necessidade de capital para manter as atividades."),"","A empresa demora " & ROUND($D$23,2) & " dias para que os recursos aplicados na operação retornem ao caixa. Quanto maior o ciclo, maior a necessidade de capital para manter as atividades.") -> A empresa demora -1945,02 dias para que os recursos aplicados na operação retornem ao caixa. Quanto maior o ciclo, maior a necessidade de capital para manter as atividades.
C21: Prazo Médio Renovação dos Estoques | D21: =IF(ISERROR($D$12),"",$D$12) -> 0
C22: Prazo Médio de Pagamento de Compras | D22: =IF(ISERROR($D$17),"",$D$17) -> 2045.52
C23: Resultado | D23: =IF(ISERROR(D20+D21-D22),"",D20+D21-D22) -> -1945.02
C25: Ciclo Operacional | F25: Análise
C26: Prazo Médio de Recebimento de Vendas | D26: =IF(ISERROR($D$7),"",$D$7) -> 100.5 | F26: =IF(ISERROR("A empresa demora " & ROUND($D$28,2) & " para receber o valor da venda, contando desde o dia da compra da mercadoria."),"","A empresa demora " & ROUND($D$28,2) & " para receber o valor da venda, contando desde o dia da compra da mercadoria.") -> A empresa demora 100,5 para receber o valor da venda, contando desde o dia da compra da mercadoria.
C27: Prazo Médio Renovação dos Estoques | D27: =IF(ISERROR($D$12),"",$D$12) -> 0
C28: Resultado | D28: =IF(ISERROR(D26+D27),"",D26+D27) -> 100.5

Sheet Indicadores de Rentabilidade
B2: OBS: PLANILHA AUTOMÁTICA. NÃO PREENCHER NENHUM CAMPO.
C4: ROE | F4: Análise
C5: Resultado Líquido do Exercício | D5: =IF(ISERROR(DRE!$E$19),"",DRE!$E$19) -> -1.6742002e+09 | F5: =IF(ISERROR("A empresa gera um retorno de" & $D$7 & " sobre o capital próprio investido"),"","A empresa gera um retorno de" & $D$7 & " sobre o capital próprio investido") -> A empresa gera um retorno de-52,62% sobre o capital próprio investido
C6: Capital Próprio | D6: =IF(ISERROR('Capital Próprio'!$E$4),"",'Capital Próprio'!$E$4) -> 3.181566e+09
C7: Resultado | D7: =IF(ISERROR(ROUND((D5*100)/D6,2)&"%"),"",ROUND((D5*100)/D6,2)&"%") -> -52,62%
C9: ROA | F9: Interpretação do índice
C10: Resultado Líquido do Exercício | D10: =IF(ISERROR(DRE!$E$19),"",DRE!$E$19) -> -1.6742002e+09 | F10: =IF(ISERROR("A empresa tem uma rentabilidade de" & ($D$12) & " sobre o seu activo total"),"","A empresa tem uma rentabilidade de" & ($D$12) & " sobre o seu activo total") -> A empresa tem uma rentabilidade de-33,42% sobre o seu activo total
C11: Activo Total | D11: =IF(ISERROR('Activos Correntes'!$L$22+'Activos Não Correntes'!$L$24),"",'Activos Correntes'!$L$22+'Activos Não Correntes'!$L$24) -> 5.0100436e+09
C12: Resultado | D12: =IF(ISERROR((ROUND((D10*100)/D11,2))&"%"),"",((ROUND((D10*100)/D11,2)&"%"))) -> -33,42%
C14: Giro do Activo | F14: Análise
C15: Receita Líquida de Vendas | D15: =IF(ISERROR('Proveitos por Natureza'!E4),"",'Proveitos por Natureza'!E4) -> 4.8672211e+09 | F15: =IF(ISERROR("A cada Kz 1,00 de Activo da empresa foi produzido de receita Kz "&ROUND($D$17,2)),"","A cada Kz 1,00 de Activo da empresa foi produzido de receita Kz "&ROUND($D$17,2)) -> A cada Kz 1,00 de Activo da empresa foi produzido de receita Kz 0,97
C16: Activo Total | D16: =IF(ISERROR('Activos Correntes'!$L$22+'Activos Não Correntes'!$L$24),"",'Activos Correntes'!$L$22+'Activos Não Correntes'!$L$24) -> 5.0100436e+09
C17: Resultado | D17: =IF(ISERROR(D15/D16),"",D15/D16) -> 0.97149277
C19: Margem Líquida | F19: Análise
C20: Resultado Líquido do Exercício | D20: =IF(ISERROR(DRE!$E$19),"",DRE!$E$19) -> -1.6742002e+09 | F20: =IF(ISERROR("A empresa consegue gerar " & ($D$22) & " da receita líquida em lucro líquido"),"", "A empresa consegue gerar " & ($D$22) & " da receita líquida em lucro líquido") -> A empresa consegue gerar -34,4% da receita líquida em lucro líquido
C21: Receita Líquida | D21: =IF(ISERROR('Proveitos por Natureza'!$L$16),"",'Proveitos por Natureza'!$L$16) -> 4.8672211e+09
C22: Resultado | D22: =IF(ISERROR(ROUND((D20*100)/D21,2)&"%"),"",ROUND((D20*100)/D21,2)&"%") -> -34,4%

Sheet Avaliação da Conta
B2: ="A Questão Principal Encontra-se no "&VLOOKUP(MAX(C7,C8,C9,C10),W35:X39,2,0) -> A Questão Principal Encontra-se no Nível - 2 | D2: =VLOOKUP(W33,$X$35:$Y$39,2,FALSE) -> 2 - Em Termos com Recomendações - A Conta poderá ser considerada em Termos, contudo, deverão ser feitas recomendações para a melhoria da apresentação da mesma.
B4: ="Percentagem das Questões por "&VLOOKUP(MAX(C7,C8,C9,C10),W35:X39,2,0) -> Percentagem das Questões por Nível - 2 | C4: =VLOOKUP($W$33,$X$35:$Z$39,3,FALSE) -> 55,56% | D4: Comentários do Técnico:
B5: =C4*100 -> 55.56 | C5: =IF(B5<25,1,IF(B5<50,2,IF(B5<75,3,IF(B5<100,4,"")))) -> 3
B6: Nível das Questões | C6: Total Questões p/ Nível | D6: % Questões p/ Nível | E6: Feedback das Questões Identificadas
B7: Nível - 1 | C7: =COUNTIF($G$35:$G$61,"=1") -> 11 | D7: =VLOOKUP(B7,X35:Z39,3,FALSE) -> 40,74% | E7: 1 - Em Termos - Deverá ser devolvida aos Gestores da Entidade.
B8: Nível - 2 | C8: =COUNTIF($G$35:$G$61,"=2") -> 15 | D8: =VLOOKUP(B8,X35:Z39,3,FALSE) -> 55,56% | E8: 2 - Em Termos com Recomendações - A Conta poderá ser considerada em Termos, contudo, deverão ser feitas recomendações para a melhoria da apresentação da mesma.
B9: Nível - 3 | C9: =COUNTIF($G$35:$G$61,"=3") -> 1 | D9: =VLOOKUP(B9,X35:Z39,3,FALSE) -> 3,7% | E9: 3 - Não em Termos - A Conta não está em Termos e deve constar do programa de auditorias para o ano seguinte e seguir para contraditório.
B13: QUADRO 1 - Demonstração Numérica - Quantitativa
B15: Rubrica | C15: Valor Declarado | D15: Consolidado TC | E15: Diferença | F15: Média | G15: Comparação
E16: =Tabela14[[#This Row],[Valor Declarado]]-Tabela14[[#This Row],[Consolidado TC]] -> 0 | F16: =IFERROR(AVERAGE(C16,D16),"")
B17: 1 - Total do Activo (BP) | C17: ='Balanço Patrimonial'!E15+'Balanço Patrimonial'!E33 -> 5.0100436e+09 | D17: ='Balanço Patrimonial'!E14+'Balanço Patrimonial'!E33 -> 5.0100436e+09 | E17: =Tabela14[[#This Row],[Valor Declarado]]-Tabela14[[#This Row],[Consolidado TC]] -> 0 | F17: =IFERROR(AVERAGE(C17,D17),"") -> 5.0100436e+09 | G17: =IF(OR(E17=0,ABS(E17)<=15%*D17),"Correcto","Incorrecto") -> Correcto
B18: 2 - Capital Próprio + Passivo (BP) | C18: ='Balanço Patrimonial'!L15+'Balanço Patrimonial'!L27+'Balanço Patrimonial'!L37 -> 5.010042e+09 | D18: ='Balanço Patrimonial'!L14+'Balanço Patrimonial'!L26+'Balanço Patrimonial'!L36 -> 5.1196023e+09 | E18: =Tabela14[[#This Row],[Valor Declarado]]-Tabela14[[#This Row],[Consolidado TC]] -> -1.0956028e+08 | F18: =IFERROR(AVERAGE(C18,D18),"") -> 5.0648222e+09 | G18: =IF(OR(E18=0,ABS(E18)<=15%*D18),"Correcto","Incorrecto") -> Correcto
B19: 3 - Resultados Líquidos do Exercício (BP) | C19: 92061415 | D19: =ABS('Balanço Patrimonial'!L34) -> 1.6742002e+09 | E19: =Tabela14[[#This Row],[Valor Declarado]]-Tabela14[[#This Row],[Consolidado TC]] -> -1.5821388e+09 | F19: =IFERROR(AVERAGE(C19,D19),"") -> 8.831308e+08 | G19: =IF(OR(E19=0,ABS(E19)<=15%*D19),"Correcto","Incorrecto") -> Incorrecto
B20: 4 - Resultados Líquidos do Exercício (DRE) | C20: 92061415 | D20: =ABS(DRE!E19) -> 1.6742002e+09 | E20: =Tabela14[[#This Row],[Valor Declarado]]-Tabela14[[#This Row],[Consolidado TC]] -> -1.5821388e+09 | F20: =IFERROR(AVERAGE(C20,D20),"") -> 8.831308e+08 | G20: =IF(OR(E20=0,ABS(E20)<=15%*D20),"Correcto","Incorrecto") -> Incorrecto
B21: 5 - Caixa e depósitos (Activos correntes) (BP) | C21: 26063796 | D21: ='Balanço Patrimonial'!E21 -> 52657493 | E21: =Tabela14[[#This Row],[Valor Declarado]]-Tabela14[[#This Row],[Consolidado TC]] -> -26593697 | F21: =IFERROR(AVERAGE(C21,D21),"") -> 39360644 | G21: =IF(OR(E21=0,ABS(E21)<=15%*D21),"Correcto","Incorrecto") -> Incorrecto
B22: 6 - Somatório da síntese das reconciliações bancárias (SRB). | E22: =Tabela14[[#This Row],[Valor Declarado]]-Tabela14[[#This Row],[Consolidado TC]] -> 0 | F22: =IFERROR(AVERAGE(C22,D22),"") | G22: =IF(OR(E22=0,ABS(E22)<=15%*D22),"Correcto","Incorrecto") -> Correcto
B23: 7 - Saldo “Investimentos financeiros” (Activos não Correntes) (BP) | C23: 0 | D23: ='Balanço Patrimonial'!E7+'Balanço Patrimonial'!E8 -> 0 | E23: =Tabela14[[#This Row],[Valor Declarado]]-Tabela14[[#This Row],[Consolidado TC]] -> 0 | F23: =IFERROR(AVERAGE(C23,D23),"") -> 0 | G23: =IF(OR(E23=0,ABS(E23)<=15%*D23),"Correcto","Incorrecto") -> Correcto
B24: 8 - Valor Total do Mapa Investimentos Financeiros | E24: =Tabela14[[#This Row],[Valor Declarado]]-Tabela14[[#This Row],[Consolidado TC]] -> 0 | F24: =IFERROR(AVERAGE(C24,D24),"") | G24: =IF(OR(E24=0,ABS(E24)<=15%*D24),"Correcto","Incorrecto") -> Correcto
E25: =Tabela14[[#This Row],[Valor Declarado]]-Tabela14[[#This Row],[Consolidado TC]] -> 0 | F25: =IFERROR(AVERAGE(C25,D25),"") | G25: =IF(OR(E25=0,ABS(E25)<=15%*D25),"Correcto","Incorrecto") -> Correcto
E26: =Tabela14[[#This Row],[Valor Declarado]]-Tabela14[[#This Row],[Consolidado TC]] -> 0 | F26: =IFERROR(AVERAGE(C26,D26),"") | G26: =IF(OR(E26=0,ABS(E26)<=15%*D26),"Correcto","Incorrecto") -> Correcto
E27: =Tabela14[[#This Row],[Valor Declarado]]-Tabela14[[#This Row],[Consolidado TC]] -> 0 | F27: =IFERROR(AVERAGE(C27,D27),"") | G27: =IF(OR(E27=0,ABS(E27)<=15%*D27),"Correcto","Incorrecto") -> Correcto
E28: =Tabela14[[#This Row],[Valor Declarado]]-Tabela14[[#This Row],[Consolidado TC]] -> 0 | F28: =IFERROR(AVERAGE(C28,D28,E28),"") -> 0 | G28: =IF(OR(E28=0,ABS(E28)<=15%*D28),"Correcto","Incorrecto") -> Correcto
B29: 5 - Valoração | E29: =Tabela14[[#This Row],[Valor Declarado]]-Tabela14[[#This Row],[Consolidado TC]] -> 0 | F29: =IFERROR(AVERAGE(C29,D29,E29),"") -> 0 | G29: {=IF(AND(G17:G28="Correcto"),"Sem Gravidade","Grave")} -> Grave
B32: QUADRO 2 - Questões Identificadas - (Qualitativa) | W32: =VLOOKUP(W33,$X$35:$Y$39,2,FALSE) -> 2 - Em Termos com Recomendações - A Conta poderá ser considerada em Termos, contudo, deverão ser feitas recomendações para a melhoria da apresentação da mesma.
B33: Questões Identificadas | D33: Normas Não Observadas | F33: Classificação das Questões | G33: Pontuação | H33: Tipo de Responsabilidade | W33: =VLOOKUP(MAX(C7,C8,C9,C10),W35:X39,2,0) -> Nível - 2
B35: 1 - Envio da prestação de contas fora do prazo legalmente estabelecido | D35: Nº 1 do artigo 73º da Lei nº 13/10 de 9 de Julho, conjugado com o artigo 2º da Resolução… | F35: Grave | G35: =N35 -> 2 | H35: =IF(OR(F35="Grave",F35="Muito Grave"),"Sancionatória - Multa nos termos do artigo 29º, nº 1, alínea g) da Lei nº 13/10, de 9 de Julho.","") -> Sancionatória - Multa nos termos do artigo 29º, nº 1, alínea g) da Lei nº 13/10, de 9 de Julho. | L35: =REPT(G35,1) -> 2 | N35: =IFERROR(VLOOKUP(F35,$O$35:$P$61,2,FALSE),"") -> 2 | O35: Sem Gravidade | P35: 1 | U35: =V35/$V$38*100 -> 40.740741 | V35: =W35*100% -> 11 | W35: =C7 -> 11 | X35: Nível - 1 | Y35: =E7 -> 1 - Em Termos - Deverá ser devolvida aos Gestores da Entidade. | Z35: =ROUND(U35,2)&"%" -> 40,74%
B36: 2 - Não envio da prestação de contas | D36: Nº 1 do artigo 73º da Lei nº 13/10 de 9 de Julho, conjugado com o artigo 2º da Resolução… | F36: Sem Gravidade | G36: =N36 -> 1 | H36: =IF(OR(F36="Grave",F36="Muito Grave"),"Sancionatória - Multa nos termos do artigo 29º, nº 1, alínea g) da Lei nº 13/10, de 9 de Julho.","") | L36: =REPT(G36,1) -> 1 | N36: =IFERROR(VLOOKUP(F36,$O$35:$P$61,2,FALSE),"") -> 1 | O36: Grave | P36: 2 | U36: =V36/$V$38*100 -> 55.555556 | V36: =W36*100% -> 15 | W36: =C8 -> 15 | X36: Nível - 2 | Y36: =E8 -> 2 - Em Termos com Recomendações - A Conta poderá ser considerada em Termos, contudo, deverão ser feitas recomendações para a melhoria da apresentação da mesma. | Z36: =ROUND(U36,2)&"%" -> 55,56%
B37: 3- Não remessa dos documentos requeridos nos instrutivos da Resolução | D37: nº 1 do artigo 3º da Resolução… | F37: Grave | G37: =N37 -> 2 | H37: =IF(OR(F37="Grave",F37="Muito Grave"),"Sancionatória - Multa nos termos do artigo 29º, nº 1, alínea g) da Lei nº 13/10, de 9 de Julho.","") -> Sancionatória - Multa nos termos do artigo 29º, nº 1, alínea g) da Lei nº 13/10, de 9 de Julho. | L37: =REPT(G37,1) -> 2 | N37: =IFERROR(VLOOKUP(F37,$O$35:$P$61,2,FALSE),"") -> 2 | O37: Muito Grave | P37: 3 | U37: =V37/$V$38*100 -> 3.7037037 | V37: =W37*100% -> 1 | W37: =C9 -> 1 | X37: Nível - 3 | Y37: =E9 -> 3 - Não em Termos - A Conta não está em Termos e deve constar do programa de auditorias para o ano seguinte e seguir para contraditório. | Z37: =ROUND(U37,2)&"%" -> 3,7%
B38: 4- Falta de ordenação documental da prestação de contas mantendo inalterada a designação de cada modelo | D38: nº 2 das Instruções Gerais de Preenchimento dos Modelos estabelecidos na Resolução… | F38: =G29 -> Grave | G38: =N38 -> 2 | H38: =IF(OR(F38="Grave",F38="Muito Grave"),"Sancionatória - Multa nos termos do artigo 29º, nº 1, alínea g) da Lei nº 13/10, de 9 de Julho.","") -> Sancionatória - Multa nos termos do artigo 29º, nº 1, alínea g) da Lei nº 13/10, de 9 de Julho. | L38: =REPT(G38,1) -> 2 | N38: =IFERROR(VLOOKUP(F38,$O$35:$P$61,2,FALSE),"") -> 2 | U38: =SUM(U35:U37) -> 100 | V38: =SUM(V34:V37) -> 27
B39: 5- Falta de submissão de determinados modelos de prestação de contas, na eventualidade de se apurar movimentações | D39: Instruções específicas previstas na Resolução… | F39: Sem Gravidade | G39: =N39 -> 1 | H39: =IF(OR(F39="Grave",F39="Muito Grave"),"Sancionatória - Multa nos termos do artigo 29º, nº 1, alínea g) da Lei nº 13/10, de 9 de Julho.","") | L39: =REPT(G39,1) -> 1 | N39: =IFERROR(VLOOKUP(F39,$O$35:$P$61,2,FALSE),"") -> 1
B40: 6- Não envio de todos os contratos celebrados ou mapas financeiros relativos aos contratos de locação financeira | D40: Instruções específicas previstas na Resolução… | F40: Grave | G40: =N40 -> 2 | H40: =IF(OR(F40="Grave",F40="Muito Grave"),"Sancionatória - Multa nos termos do artigo 29º, nº 1, alínea g) da Lei nº 13/10, de 9 de Julho.","") -> Sancionatória - Multa nos termos do artigo 29º, nº 1, alínea g) da Lei nº 13/10, de 9 de Julho. | L40: =REPT(G40,1) -> 2 | N40: =IFERROR(VLOOKUP(F40,$O$35:$P$61,2,FALSE),"") -> 2
B41: 7- Falta de inclusão dos dados de cada responsável pela gestão | D41: nº 3 das Instruções Específicas previstas na Resolução… | F41: =G29 -> Grave | G41: =N41 -> 2 | H41: =IF(OR(F41="Grave",F41="Muito Grave"),"Sancionatória - Multa nos termos do artigo 29º, nº 1, alínea g) da Lei nº 13/10, de 9 de Julho.","") -> Sancionatória - Multa nos termos do artigo 29º, nº 1, alínea g) da Lei nº 13/10, de 9 de Julho. | L41: =REPT(G41,1) -> 2 | N41: =IFERROR(VLOOKUP(F41,$O$35:$P$61,2,FALSE),"") -> 2
B42: 8 - Falta de envio dos mapas constitutivos das Demostrações Financeiras | D42: nº 4 das Instruções específicas previstas na Resolução | F42: Sem Gravidade | G42: =N42 -> 1 | H42: =IF(OR(F42="Grave",F42="Muito Grave"),"Sancionatória - Multa nos termos do artigo 29º, nº 1, alínea g) da Lei nº 13/10, de 9 de Julho.","") | L42: =REPT(G42,1) -> 1 | N42: =IFERROR(VLOOKUP(F42,$O$35:$P$61,2,FALSE),"") -> 1
B43: 9- Não observância das instruções de preenchimento dos modelos, com relevância pela falta de consistência dos dados | D43: Instruções específicas de preenchimento de cada modelo de prestação de contas | F43: Grave | G43: =N43 -> 2 | H43: =IF(OR(F43="Grave",F43="Muito Grave"),"Sancionatória - Multa nos termos do artigo 29º, nº 1, alínea g) da Lei nº 13/10, de 9 de Julho.","") -> Sancionatória - Multa nos termos do artigo 29º, nº 1, alínea g) da Lei nº 13/10, de 9 de Julho. | L43: =REPT(G43,1) -> 2 | N43: =IFERROR(VLOOKUP(F43,$O$35:$P$61,2,FALSE),"") -> 2
B44: 10 - Falta de detalhamento e organização do Balanço Patrimonial de acordo com a estrutura prevista( Activo, Capital Próprio e Passivo), e por classes de contas, incluindo a correcta ordenação pelo grau de liquidez e exigibilidade | D44: Normas técnicas de estruturação e apresentação das Demonstrações Financeiras | F44: Sem Gravidade | G44: =N44 -> 1 | H44: =IF(OR(F44="Grave",F44="Muito Grave"),"Sancionatória - Multa nos termos do artigo 29º, nº 1, alínea g) da Lei nº 13/10, de 9 de Julho.","") | L44: =REPT(G44,1) -> 1 | N44: =IFERROR(VLOOKUP(F44,$O$35:$P$61,2,FALSE),"") -> 1
B45: 11- Ausência de assinatura do técnico e do responsável da àrea, bem como falta de homologação do responsável máximo da entidade prestadora de contas, na guia remessa. | D45: nº 3, 4 e 5 das Instruções Gerais estabelecidas na Resolução…. | F45: Grave | G45: =N45 -> 2 | H45: =IF(OR(F45="Grave",F45="Muito Grave"),"Sancionatória - Multa nos termos do artigo 29º, nº 1, alínea g) da Lei nº 13/10, de 9 de Julho.","") -> Sancionatória - Multa nos termos do artigo 29º, nº 1, alínea g) da Lei nº 13/10, de 9 de Julho. | L45: =REPT(G45,1) -> 2 | N45: =IFERROR(VLOOKUP(F45,$O$35:$P$61,2,FALSE),"") -> 2
B46: 12 - Falta de detalhamento e organização da Demonstração de resultados, não reflectindo correctamente a estrutura por classes de contas ( Proveitos e Custos) e não diferenciando as variantes por natureza e por funções. | D46: Normas Técnicas de estruturação e apresentação da Demonstração de Resultados conforme o PGC | F46: Sem Gravidade | G46: =N46 -> 1 | H46: =IF(OR(F46="Grave",F46="Muito Grave"),"Sancionatória - Multa nos termos do artigo 29º, nº 1, alínea g) da Lei nº 13/10, de 9 de Julho.","") | L46: =REPT(G46,1) -> 1 | N46: =IFERROR(VLOOKUP(F46,$O$35:$P$61,2,FALSE),"") -> 1
B47: 13 - Falta de elaboração adequada da Demostração dos Fluxos de Caixa | D47: Normas Técnicas de estruturação e apresentação da Demonstração de Fluxos de Caixa conforme o PGC | F47: Grave | G47: =N47 -> 2 | H47: =IF(OR(F47="Grave",F47="Muito Grave"),"Sancionatória - Multa nos termos do artigo 29º, nº 1, alínea g) da Lei nº 13/10, de 9 de Julho.","") -> Sancionatória - Multa nos termos do artigo 29º, nº 1, alínea g) da Lei nº 13/10, de 9 de Julho. | L47: =REPT(G47,1) -> 2 | N47: =IFERROR(VLOOKUP(F47,$O$35:$P$61,2,FALSE),"") -> 2
B48: 14 - Falta de envio de documentos adicionais | D48: Instruções específicas da Resolução…. | F48: Sem Gravidade | G48: =N48 -> 1 | H48: =IF(OR(F48="Grave",F48="Muito Grave"),"Sancionatória - Multa nos termos do artigo 29º, nº 1, alínea g) da Lei nº 13/10, de 9 de Julho.","") | L48: =REPT(G48,1) -> 1 | N48: =IFERROR(VLOOKUP(F48,$O$35:$P$61,2,FALSE),"") -> 1
B49: 15 - Situações que possam alterar o resultado financeiro do exercicio | D49: Normas Técnicas de estruturação e apresentação da Demonstração de Resultados conforme o PGC | F49: Grave | G49: =N49 -> 2 | H49: =IF(OR(F49="Grave",F49="Muito Grave"),"Sancionatória - Multa nos termos do artigo 29º, nº 1, alínea g) da Lei nº 13/10, de 9 de Julho.","") -> Sancionatória - Multa nos termos do artigo 29º, nº 1, alínea g) da Lei nº 13/10, de 9 de Julho. | L49: =REPT(G49,1) -> 2 | N49: =IFERROR(VLOOKUP(F49,$O$35:$P$61,2,FALSE),"") -> 2
B50: 16 - Execução de contratos sem concessão do visto do Tribunal de Contas | D50: nº 3 do artigo 8º da Lei nº 13/10, de 9 de Julho | F50: Sem Gravidade | G50: =N50 -> 1 | H50: =IF(OR(F50="Grave",F50="Muito Grave"),"Sancionatória - Multa nos termos do artigo 29º, nº 1, alínea g) da Lei nº 13/10, de 9 de Julho.","") | L50: =REPT(G50,1) -> 1 | N50: =IFERROR(VLOOKUP(F50,$O$35:$P$61,2,FALSE),"") -> 1
B51: 17 - Execução de contratos devolvidos pelo Tribunal para melhor instrução | D51: nº2 do artigo 66º da Lei nº 13/10, de 9 de Julho | F51: Grave | G51: =N51 -> 2 | H51: =IF(OR(F51="Grave",F51="Muito Grave"),"Sancionatória - Multa nos termos do artigo 29º, nº 1, alínea g) da Lei nº 13/10, de 9 de Julho.","") -> Sancionatória - Multa nos termos do artigo 29º, nº 1, alínea g) da Lei nº 13/10, de 9 de Julho. | L51: =REPT(G51,1) -> 2 | N51: =IFERROR(VLOOKUP(F51,$O$35:$P$61,2,FALSE),"") -> 2
B52: 18 - Pagamentos ou adiantamentos iniciais não respeitando normas | D52: Norma anual de execução do Orçamento | F52: Sem Gravidade | G52: =N52 -> 1 | H52: =IF(OR(F52="Grave",F52="Muito Grave"),"Sancionatória - Multa nos termos do artigo 29º, nº 1, alínea g) da Lei nº 13/10, de 9 de Julho.","") | L52: =REPT(G52,1) -> 1 | N52: =IFERROR(VLOOKUP(F52,$O$35:$P$61,2,FALSE),"") -> 1
B53: 19 - Falta de redução a escritos de contratos obrigatòrios | D53: Artigo 107º da Lei nº 41/20, de 23 de Dezembro (Lei dos Contratos Públicos) | F53: Sem Gravidade | G53: =N53 -> 1 | H53: =IF(OR(F53="Grave",F53="Muito Grave"),"Sancionatória - Multa nos termos do artigo 29º, nº 1, alínea g) da Lei nº 13/10, de 9 de Julho.","") | L53: =REPT(G53,1) -> 1 | N53: =IFERROR(VLOOKUP(F53,$O$35:$P$61,2,FALSE),"") -> 1
... B60: 26- Falta de prestação de informações pedidas, remessa de documentos ou comparência | D60: Artigo 18º da Lei nº 13/10, de 9 de Julho | F60: Grave | G60: =N60 -> 2 | H60: =IF(OR(F60="Grave",F60="Muito Grave"),"Sancionatória - Multa nos termos do artigo 29º, nº 1, alínea g) da Lei nº 13/10, de 9 de Julho.","") -> Sancionatória - Multa nos termos do artigo 29º, nº 1, alínea g) da Lei nº 13/10, de 9 de Julho. | L60: =REPT(G60,1) -> 2 | N60: =IFERROR(VLOOKUP(F60,$O$35:$P$61,2,FALSE),"") -> 2
B61: 27- Demonstração Numérica irregular | F61: =G29 -> Grave | G61: =N61 -> 2 | H61: =IF(OR(F61="Grave",F61="Muito Grave"),"Sancionatória - Multa nos termos do artigo 29º, nº 1, alínea g) da Lei nº 13/10, de 9 de Julho.","") -> Sancionatória - Multa nos termos do artigo 29º, nº 1, alínea g) da Lei nº 13/10, de 9 de Julho. | L61: =REPT(G61,1) -> 2 | N61: =IFERROR(VLOOKUP(F61,$O$35:$P$61,2,FALSE),"") -> 2
B62: 28- Indicador de Liquidez | H62: =IF(OR(F62="Grave",F62="Muito Grave"),"Sancionatória - Multa nos termos do artigo 29º, nº 1, alínea g) da Lei nº 13/10, de 9 de Julho.","")
B63: 29- Indicador de endividamento | H63: =IF(OR(F63="Grave",F63="Muito Grave"),"Sancionatória - Multa nos termos do artigo 29º, nº 1, alínea g) da Lei nº 13/10, de 9 de Julho.","")
B64: 30- Indicador de Rentabilidade | H64: =IF(OR(F64="Grave",F64="Muito Grave"),"Sancionatória - Multa nos termos do artigo 29º, nº 1, alínea g) da Lei nº 13/10, de 9 de Julho.","")
H65: =IF(OR(F65="Grave",F65="Muito Grave"),"Sancionatória - Multa nos termos do artigo 29º, nº 1, alínea g) da Lei nº 13/10, de 9 de Julho.","")

Sheet Auxiliar DFC
D4: ANÁLISE DOS FLUXOS DE CAIXA DA ENTIDADE
B6: Código | C6: Descrição | D6: Período N | H6: Período N-1
D7: Caixa | E7: Bancos | F7: Títulos | G7: Total | H7: Total
B8: 01 | C8: Actividades Operacionais
B9: 01111 | C9: Recebimentos de Clientes
B10: 01122 | C10: Pagamentos a Fornecedores
B11: 01123 | C11: Pagamentos ao Pessoal
B12: 01221 | C12: Pagamento do Imposto sobre o Rendimento
B13: 01211 | C13: Recebimento do Imposto sobre o Rendimento
B14: 01212 | C14: Outros Recebimentos Relativos à Actividade Operacional
B15: 01222 | C15: Outros Pagamentos Relativos à Actividade Operacional
B17: 02 | C17: Actividades de Investimeto
C18: Pagamento Respeitantes a:
B19: 02011 | C19: Activos Fixos Tangíveis
B20: 02012 | C20: Activos Intangíveis
B21: 02013 | C21: Investimentos Financeiros
B22: 02014 | C22: Outros Activos
C23: Recebimentos Provenientes de:
B24: 02021 | C24: Activos Fixos Tangíveis
B25: 02022 | C25: Activos Intangíveis
B26: 02023 | C26: Investimentos Financeiros
B27: 02024 | C27: Outros Activos
B28: 02025 | C28: Subsídios de Investimento
B29: 02026 | C29: Juros e Rendimentos Similares
B30: 02027 | C30: Dividendos
B32: 03 | C32: Actividades de Financiamento
C33: Recebimentos Provenientes de:
B34: 03011 | C34: Financiamentos Obtidos
B35: 03012 | C35: Realizações de Capital e de Outros Instrumentos de Capital Próprio
B36: 03013 | C36: Cobertura de Prejuízos
B37: 03014 | C37: Doações
B38: 03015 | C38: Outras Operações de Financiamento
C39: Pagamentos Respeitantes a:
B40: 03021 | C40: Financiamentos Obtidos
B41: 03022 | C41: Juros e Gastos Similares
B42: 03023 | C42: Dividendos
B43: 03024 | C43: Reduções de Capital e de Outros Instrumentos de Capital Próprio
B44: 03025 | C44: Outras Operações de Financiamento
B46: 04 | C46: Efeitos das Diferenças de Câmbio
B47: 041 | C47: Diferenças de Câmbio Positivas
B48: 042 | C48: Diferenças de Câmbio Negativas
B50: 09 | C50: Contas Reflectidas
B51: 091 | C51: Actividades Operacionais
B52: 092 | C52: Actividades de Investimento
B53: 093 | C53: Actvidades de Financiamento
B54: 094 | C54: Diferenças de Câmbio

Sheet Investimentos
B5: Designação | C5: Ano de Início | D5: Financiamentos Previstos | E5: Exercícios Anteriores | H5: Exercício Corrente | K5: Valores Acumulados | O5: Exercícios Futuros Financiamentos Previstos
E6: Previções | F6: Financiamento | G6: Realizações | H6: Previsões | I6: Financiamento | J6: Realizações | K6: Previsões | L6: Financiamento | M6: Realizações | N6: %
B7: 1 | C7: 2 | D7: 3 | E7: 4 | F7: 5 | G7: 6 | H7: 7 | I7: 8 | J7: 9 | K7: 10 | L7: 11 | M7: 12 | N7: 13 | O7: 14

Sheet Impressão
B2: OBS: NÃO PREENCHER OS CAMPOS EM AZUL. PREENCHIMENTO AUTOMÁTICO.
C4: RELATÓRIO DE IMPRESSÃO:
C5: Análise de Balanço Patrimonial
C8: 1.1 - Activos não Correntes
C9: 1.2 - Activos Correntes
C10: 2.1 - Passivo não Corrente e Capital Próprio
C11: 2.2 - Passivo Corrente
C12: 3 - Balanço Patrimonial
C13: 4 - Proveitos por Natureza
C14: 5 - Custos por Natureza
C15: 6 - Demonstração de Resultados - DRE
C16: 7 - Gráficos
C18: 1.1 - ACTIVOS NÃO CORRENTES
C19: ='Activos Não Correntes'!J4 -> 1.1 | D19: Contas dos Activos não Correntes - Total
C20: =IF(ISERROR('Activos Não Correntes'!J5),"",'Activos Não Correntes'!J5) -> 1.1.1 | D20: =IF(ISERROR('Activos Não Correntes'!K5),"",'Activos Não Correntes'!K5) -> Imobilizações corpóreas | E20: =IF(ISERROR('Activos Não Correntes'!L5),"",'Activos Não Correntes'!L5) -> 3.4238736e+09 | F20: =IF(ISERROR('Activos Não Correntes'!M5),"",'Activos Não Correntes'!M5) -> 0.9938818 | G20: =IF(ISERROR('Activos Não Correntes'!J9),"",'Activos Não Correntes'!J9) -> 1.1.5 | H20: =IF(ISERROR('Activos Não Correntes'!K9),"",'Activos Não Correntes'!K9) -> Provisões para Investimentos Financeiros | I20: =IF(ISERROR('Activos Não Correntes'!L9),"",'Activos Não Correntes'!L9) -> 0 | J20: =IF(ISERROR('Activos Não Correntes'!M9),"",'Activos Não Correntes'!M9) -> 0
C21: =IF(ISERROR('Activos Não Correntes'!J6),"",'Activos Não Correntes'!J6) -> 1.1.2 | D21: =IF(ISERROR('Activos Não Correntes'!K6),"",'Activos Não Correntes'!K6) -> Imobilizações incorpóreas | E21: =IF(ISERROR('Activos Não Correntes'!L6),"",'Activos Não Correntes'!L6) -> 21076889 | F21: =IF(ISERROR('Activos Não Correntes'!M6),"",'Activos Não Correntes'!M6) -> 0.0061181981 | G21: =IF(ISERROR('Activos Não Correntes'!J10),"",'Activos Não Correntes'!J10) -> 1.1.6 | H21: =IF(ISERROR('Activos Não Correntes'!K10),"",'Activos Não Correntes'!K10) -> Outros Activos não Correntes | I21: =IF(ISERROR('Activos Não Correntes'!L10),"",'Activos Não Correntes'!L10) -> 0 | J21: =IF(ISERROR('Activos Não Correntes'!M10),"",'Activos Não Correntes'!M10) -> 0
C22: =IF(ISERROR('Activos Não Correntes'!J7),"",'Activos Não Correntes'!J7) -> 1.1.3 | D22: =IF(ISERROR('Activos Não Correntes'!K7),"",'Activos Não Correntes'!K7) -> Investimentos em Subsidiárias e Associadas | E22: =IF(ISERROR('Activos Não Correntes'!L7),"",'Activos Não Correntes'!L7) -> 0 | F22: =IF(ISERROR('Activos Não Correntes'!M7),"",'Activos Não Correntes'!M7) -> 0 | G22: =IF(ISERROR('Activos Não Correntes'!J11),"",'Activos Não Correntes'!J11) -> 0 | H22: =IF(ISERROR('Activos Não Correntes'!K11),"",'Activos Não Correntes'!K11) -> 0 | I22: =IF(ISERROR('Activos Não Correntes'!L11),"",'Activos Não Correntes'!L11) -> 0 | J22: =IF(ISERROR('Activos Não Correntes'!M11),"",'Activos Não Correntes'!M11) -> 0
C23: =IF(ISERROR('Activos Não Correntes'!J8),"",'Activos Não Correntes'!J8) -> 1.1.4 | D23: =IF(ISERROR('Activos Não Correntes'!K8),"",'Activos Não Correntes'!K8) -> Outros Activos Financeiros | E23: =IF(ISERROR('Activos Não Correntes'!L8),"",'Activos Não Correntes'!L8) -> 0 | F23: =IF(ISERROR('Activos Não Correntes'!M8),"",'Activos Não Correntes'!M8) -> 0 | G23: =IF(ISERROR('Activos Não Correntes'!J12),"",'Activos Não Correntes'!J12) -> 0 | H23: =IF(ISERROR('Activos Não Correntes'!K12),"",'Activos Não Correntes'!K12) -> 0 | I23: =IF(ISERROR('Activos Não Correntes'!L12),"",'Activos Não Correntes'!L12) -> 0 | J23: =IF(ISERROR('Activos Não Correntes'!M12),"",'Activos Não Correntes'!M12) -> 0
C24: =IF(ISERROR('Activos Não Correntes'!#REF!),"",'Activos Não Correntes'!#REF!) | D24: =IF(ISERROR('Activos Não Correntes'!#REF!),"",'Activos Não Correntes'!#REF!) | E24: =IF(ISERROR('Activos Não Correntes'!#REF!),"",'Activos Não Correntes'!#REF!) | F24: =IF(ISERROR('Activos Não Correntes'!#REF!),"",'Activos Não Correntes'!#REF!) | G24: =IF(ISERROR('Activos Não Correntes'!J24),"",'Activos Não Correntes'!J24) -> Total | I24: =IF(ISERROR('Activos Não Correntes'!L24),"",'Activos Não Correntes'!L24) -> 3.4449505e+09
C26: 1.2 - ACTIVOS CORRENTES
C27: ='Activos Correntes'!J4 -> 1.2 | D27: Contas dos Activos Correntes - Total
C28: =IF(ISERROR('Activos Correntes'!J5),"",'Activos Correntes'!J5) -> 1.2.1 | D28: =IF(ISERROR('Activos Correntes'!K5),"",'Activos Correntes'!K5) -> Existências | E28: =IF(ISERROR('Activos Correntes'!L5),"",'Activos Correntes'!L5) -> 0 | F28: =IF(ISERROR('Activos Correntes'!M5),"",'Activos Correntes'!M5) -> 0 | G28: =IF(ISERROR('Activos Correntes'!J10),"",'Activos Correntes'!J10) -> 0 | H28: =IF(ISERROR('Activos Correntes'!K10),"",'Activos Correntes'!K10) -> 0 | I28: =IF(ISERROR('Activos Correntes'!L10),"",'Activos Correntes'!L10) -> 0 | J28: =IF(ISERROR('Activos Correntes'!M10),"",'Activos Correntes'!M10) -> 0
C29: =IF(ISERROR('Activos Correntes'!J6),"",'Activos Correntes'!J6) -> 1.2.2 | D29: =IF(ISERROR('Activos Correntes'!K6),"",'Activos Correntes'!K6) -> Contas a Receber | E29: =IF(ISERROR('Activos Correntes'!L6),"",'Activos Correntes'!L6) -> 1.3402124e+09 | F29: =IF(ISERROR('Activos Correntes'!M6),"",'Activos Correntes'!M6) -> 0.85631482 | G29: =IF(ISERROR('Activos Correntes'!J11),"",'Activos Correntes'!J11) -> 0 | H29: =IF(ISERROR('Activos Correntes'!K11),"",'Activos Correntes'!K11) -> 0 | I29: =IF(ISERROR('Activos Correntes'!L11),"",'Activos Correntes'!L11) | J29: =IF(ISERROR('Activos Correntes'!M11),"",'Activos Correntes'!M11)
C30: =IF(ISERROR('Activos Correntes'!J7),"",'Activos Correntes'!J7) -> 1.2.3 | D30: =IF(ISERROR('Activos Correntes'!K7),"",'Activos Correntes'!K7) -> Disponibilidades | E30: =IF(ISERROR('Activos Correntes'!L7),"",'Activos Correntes'!L7) -> 52657493 | F30: =IF(ISERROR('Activos Correntes'!M7),"",'Activos Correntes'!M7) -> 0.033644958 | G30: =IF(ISERROR('Activos Correntes'!J12),"",'Activos Correntes'!J12) -> 0 | H30: =IF(ISERROR('Activos Correntes'!K12),"",'Activos Correntes'!K12) -> 0 | I30: =IF(ISERROR('Activos Correntes'!L12),"",'Activos Correntes'!L12) | J30: =IF(ISERROR('Activos Correntes'!M12),"",'Activos Correntes'!M12)
C31: =IF(ISERROR('Activos Correntes'!J8),"",'Activos Correntes'!J8) -> 1.2.4 | D31: =IF(ISERROR('Activos Correntes'!K8),"",'Activos Correntes'!K8) -> Outros activos correntes | E31: =IF(ISERROR('Activos Correntes'!L8),"",'Activos Correntes'!L8) -> 1.7222319e+08 | F31: =IF(ISERROR('Activos Correntes'!M8),"",'Activos Correntes'!M8) -> 0.11004022 | G31: =IF(ISERROR('Activos Correntes'!J13),"",'Activos Correntes'!J13) -> 0 | H31: =IF(ISERROR('Activos Correntes'!K13),"",'Activos Correntes'!K13) -> 0 | I31: =IF(ISERROR('Activos Correntes'!L13),"",'Activos Correntes'!L13) | J31: =IF(ISERROR('Activos Correntes'!M13),"",'Activos Correntes'!M13)
C32: =IF(ISERROR('Activos Correntes'!J9),"",'Activos Correntes'!J9) -> 1.2.5 | D32: =IF(ISERROR('Activos Correntes'!K9),"",'Activos Correntes'!K9) -> Estado | E32: =IF(ISERROR('Activos Correntes'!L9),"",'Activos Correntes'!L9) -> 0 | F32: =IF(ISERROR('Activos Correntes'!M9),"",'Activos Correntes'!M9) -> 0 | G32: =IF(ISERROR('Activos Correntes'!J22),"",'Activos Correntes'!J22) -> Total | I32: =IF(ISERROR('Activos Correntes'!L22),"",'Activos Correntes'!L22) -> 1.5650931e+09
C34: 2.1 - PASSIVO NÃO CORRENTE E CAPITAL PRÓPRIO
C35: ='Passivo Não Corrente'!C4 -> 2.2 | D35: Contas do Passivo não Corrente - Total | G35: ='Capital Próprio'!J4 -> 2.1 | H35: Contas do Capital Próprio - Total
C36: =IF(ISERROR('Passivo Não Corrente'!J5),"",'Passivo Não Corrente'!J5) -> 2.2.1 | D36: =IF(ISERROR('Passivo Não Corrente'!K5),"",'Passivo Não Corrente'!K5) -> Empréstimos de médio e longo prazos | E36: =IF(ISERROR('Passivo Não Corrente'!L5),"",'Passivo Não Corrente'!L5) -> 0 | F36: =IF(ISERROR('Passivo Não Corrente'!M5),"",'Passivo Não Corrente'!M5) | G36: Capital Próprio | I36: =SUM(I37:I41) -> 3.181566e+09
C37: =IF(ISERROR('Passivo Não Corrente'!J6),"",'Passivo Não Corrente'!J6) -> 2.2.2 | D37: =IF(ISERROR('Passivo Não Corrente'!K6),"",'Passivo Não Corrente'!K6) -> Impostos diferidos | E37: =IF(ISERROR('Passivo Não Corrente'!L6),"",'Passivo Não Corrente'!L6) -> 0 | F37: =IF(ISERROR('Passivo Não Corrente'!M6),"",'Passivo Não Corrente'!M6) | G37: ='Capital Próprio'!J5 -> 2.1.1 | H37: ='Capital Próprio'!K5 -> Capital | I37: ='Capital Próprio'!L5 -> 262500000 | J37: ='Capital Próprio'!M5
C38: =IF(ISERROR('Passivo Não Corrente'!J7),"",'Passivo Não Corrente'!J7) -> 2.2.3 | D38: =IF(ISERROR('Passivo Não Corrente'!K7),"",'Passivo Não Corrente'!K7) -> Provisões para pensões | E38: =IF(ISERROR('Passivo Não Corrente'!L7),"",'Passivo Não Corrente'!L7) -> 0 | F38: =IF(ISERROR('Passivo Não Corrente'!M7),"",'Passivo Não Corrente'!M7) | G38: ='Capital Próprio'!J6 -> 2.1.2 | H38: ='Capital Próprio'!K6 -> Reservas | I38: ='Capital Próprio'!L6 -> 0 | J38: ='Capital Próprio'!M6
C39: =IF(ISERROR('Passivo Não Corrente'!J8),"",'Passivo Não Corrente'!J8) -> 2.2.4 | D39: =IF(ISERROR('Passivo Não Corrente'!K8),"",'Passivo Não Corrente'!K8) -> Provisões para outros riscos e encagos | E39: =IF(ISERROR('Passivo Não Corrente'!L8),"",'Passivo Não Corrente'!L8) -> 0 | F39: =IF(ISERROR('Passivo Não Corrente'!M8),"",'Passivo Não Corrente'!M8) | G39: ='Capital Próprio'!J7 -> 2.1.3 | H39: ='Capital Próprio'!K7 -> Resultados transitados | I39: ='Capital Próprio'!L7 -> 4.5932662e+09 | J39: ='Capital Próprio'!M7
C40: =IF(ISERROR('Passivo Não Corrente'!J9),"",'Passivo Não Corrente'!J9) -> 2.2.5 | D40: =IF(ISERROR('Passivo Não Corrente'!K9),"",'Passivo Não Corrente'!K9) -> Outros passivos não correntes | E40: =IF(ISERROR('Passivo Não Corrente'!L9),"",'Passivo Não Corrente'!L9) -> 0 | F40: =IF(ISERROR('Passivo Não Corrente'!M9),"",'Passivo Não Corrente'!M9) | G40: ='Capital Próprio'!J8 -> 2.1.4 | H40: ='Capital Próprio'!K8 -> Resultados do exercício | I40: ='Capital Próprio'!L8 -> -1.6742002e+09 | J40: ='Capital Próprio'!M8
C41: =IF(ISERROR('Passivo Não Corrente'!J10),"",'Passivo Não Corrente'!J10) -> 0 | D41: =IF(ISERROR('Passivo Não Corrente'!K10),"",'Passivo Não Corrente'!K10) -> 0 | E41: =IF(ISERROR('Passivo Não Corrente'!L10),"",'Passivo Não Corrente'!L10) -> 0 | F41: =IF(ISERROR('Passivo Não Corrente'!M10),"",'Passivo Não Corrente'!M10) | G41: ='Capital Próprio'!J9 -> 0 | H41: ='Capital Próprio'!K9 -> 0 | I41: ='Capital Próprio'!L9 | J41: ='Capital Próprio'!M9
C42: Total Passivo não Corrente | E42: =SUM(E36:E41) -> 0 | G42: Total | I42: =E42+I36 -> 3.181566e+09
C44: 2.2 - PASSIVO CORRENTE
C45: ='Passivo Corrente'!J4 -> 2.3 | D45: Contas do Passivo Corrente - Total
C46: =IF(ISERROR('Passivo Corrente'!J5),"",'Passivo Corrente'!J5) -> 2.3.1 | D46: =IF(ISERROR('Passivo Corrente'!K5),"",'Passivo Corrente'!K5) -> Contas a pagar | E46: =IF(ISERROR('Passivo Corrente'!L5),"",'Passivo Corrente'!L5) -> 1.006981e+09 | F46: =IF(ISERROR('Passivo Corrente'!M5),"",'Passivo Corrente'!M5) -> -394.40773 | G46: =IF(ISERROR('Passivo Corrente'!J10),"",'Passivo Corrente'!J10) -> 2.3.6 | H46: =IF(ISERROR('Passivo Corrente'!K10),"",'Passivo Corrente'!K10) -> Estado | I46: =IF(ISERROR('Passivo Corrente'!L10),"",'Passivo Corrente'!L10) -> 4.8779409e+08 | J46: =IF(ISERROR('Passivo Corrente'!M10),"",'Passivo Corrente'!M10) -> -191.056
C47: =IF(ISERROR('Passivo Corrente'!J6),"",'Passivo Corrente'!J6) -> 2.3.2 | D47: =IF(ISERROR('Passivo Corrente'!K6),"",'Passivo Corrente'!K6) -> Participantes e Participadas | E47: =IF(ISERROR('Passivo Corrente'!L6),"",'Passivo Corrente'!L6) -> 0 | F47: =IF(ISERROR('Passivo Corrente'!M6),"",'Passivo Corrente'!M6) -> 0 | G47: =IF(ISERROR('Passivo Corrente'!J11),"",'Passivo Corrente'!J11) -> 2.3.7 | H47: =IF(ISERROR('Passivo Corrente'!K11),"",'Passivo Corrente'!K11) -> Outros Passivos Correntes | I47: =IF(ISERROR('Passivo Corrente'!L11),"",'Passivo Corrente'!L11) -> 4.4326119e+08 | J47: =IF(ISERROR('Passivo Corrente'!M11),"",'Passivo Corrente'!M11) -> -173.61365
C48: =IF(ISERROR('Passivo Corrente'!J7),"",'Passivo Corrente'!J7) -> 2.3.3 | D48: =IF(ISERROR('Passivo Corrente'!K7),"",'Passivo Corrente'!K7) -> Pessoal | E48: =IF(ISERROR('Passivo Corrente'!L7),"",'Passivo Corrente'!L7) -> 0 | F48: =IF(ISERROR('Passivo Corrente'!M7),"",'Passivo Corrente'!M7) -> 0 | G48: =IF(ISERROR('Passivo Corrente'!J12),"",'Passivo Corrente'!J12) -> 0 | H48: =IF(ISERROR('Passivo Corrente'!K12),"",'Passivo Corrente'!K12) -> 0 | I48: =IF(ISERROR('Passivo Corrente'!L12),"",'Passivo Corrente'!L12) -> 0 | J48: =IF(ISERROR('Passivo Corrente'!M12),"",'Passivo Corrente'!M12) -> 0
C49: =IF(ISERROR('Passivo Corrente'!J8),"",'Passivo Corrente'!J8) -> 2.3.4 | D49: =IF(ISERROR('Passivo Corrente'!K8),"",'Passivo Corrente'!K8) -> Empréstimos de Curto Prazo | E49: =IF(ISERROR('Passivo Corrente'!L8),"",'Passivo Corrente'!L8) -> 0 | F49: =IF(ISERROR('Passivo Corrente'!M8),"",'Passivo Corrente'!M8) -> 0 | G49: =IF(ISERROR('Passivo Corrente'!J13),"",'Passivo Corrente'!J13) -> 0 | H49: =IF(ISERROR('Passivo Corrente'!K13),"",'Passivo Corrente'!K13) -> 0 | I49: =IF(ISERROR('Passivo Corrente'!L13),"",'Passivo Corrente'!L13) -> 0 | J49: =IF(ISERROR('Passivo Corrente'!M13),"",'Passivo Corrente'!M13) -> 0
C50: =IF(ISERROR('Passivo Corrente'!J9),"",'Passivo Corrente'!J9) -> 2.3.5 | D50: =IF(ISERROR('Passivo Corrente'!K9),"",'Passivo Corrente'!K9) -> Parte Correspondente dos Empréstimos de Médio e Longo Prazo | E50: =IF(ISERROR('Passivo Corrente'!L9),"",'Passivo Corrente'!L9) -> 0 | F50: =IF(ISERROR('Passivo Corrente'!M9),"",'Passivo Corrente'!M9) -> 0 | G50: =IF(ISERROR('Passivo Corrente'!J25),"",'Passivo Corrente'!J25) -> Total | I50: =IF(ISERROR('Passivo Corrente'!L25),"",'Passivo Corrente'!L25) -> 1.9380363e+09
C53: 3 - BALANÇO PATRIMONIAL
C54: Resultado Total
C55: Ativo | E55: ='Balanço Patrimonial'!E37:F37 -> 5.0100436e+09
C56: Passivo | E56: ='Balanço Patrimonial'!E38:F38 -> 5.1196023e+09
C58: 4 - PROVEITOS POR NATUREZA - DRE
C59: 3 | D59: Contas de Proveitos e Ganhos por Natureza - Total
C60: =IF(ISERROR('Proveitos por Natureza'!J5),"",'Proveitos por Natureza'!J5) -> 3.1 | D60: =IF(ISERROR('Proveitos por Natureza'!K5),"",'Proveitos por Natureza'!K5) -> Vendas | E60: =IF(ISERROR('Proveitos por Natureza'!L5),"",'Proveitos por Natureza'!L5) -> 0 | F60: =IF(ISERROR('Proveitos por Natureza'!M5),"",'Proveitos por Natureza'!M5) | G60: =IF(ISERROR('Proveitos por Natureza'!J10),"",'Proveitos por Natureza'!J10) -> 3.6 | H60: =IF(ISERROR('Proveitos por Natureza'!K10),"",'Proveitos por Natureza'!K10) -> Proveitos e Ganhos Financeiros Gerais | I60: =IF(ISERROR('Proveitos por Natureza'!L10),"",'Proveitos por Natureza'!L10) -> 10089891 | J60: =IF(ISERROR('Proveitos por Natureza'!M10),"",'Proveitos por Natureza'!M10)
C61: =IF(ISERROR('Proveitos por Natureza'!J6),"",'Proveitos por Natureza'!J6) -> 3.2 | D61: =IF(ISERROR('Proveitos por Natureza'!K6),"",'Proveitos por Natureza'!K6) -> Prestações de Serviço | E61: =IF(ISERROR('Proveitos por Natureza'!L6),"",'Proveitos por Natureza'!L6) -> 1.7692123e+09 | F61: =IF(ISERROR('Proveitos por Natureza'!M6),"",'Proveitos por Natureza'!M6) | G61: =IF(ISERROR('Proveitos por Natureza'!J11),"",'Proveitos por Natureza'!J11) -> 3.7 | H61: =IF(ISERROR('Proveitos por Natureza'!K11),"",'Proveitos por Natureza'!K11) -> Proveitos e Ganhos Financeiros em Susidiárias e Associadas | I61: =IF(ISERROR('Proveitos por Natureza'!L11),"",'Proveitos por Natureza'!L11) -> 0 | J61: =IF(ISERROR('Proveitos por Natureza'!M11),"",'Proveitos por Natureza'!M11)
C62: =IF(ISERROR('Proveitos por Natureza'!J7),"",'Proveitos por Natureza'!J7) -> 3.3 | D62: =IF(ISERROR('Proveitos por Natureza'!K7),"",'Proveitos por Natureza'!K7) -> Outros Proveitos Operacionais | E62: =IF(ISERROR('Proveitos por Natureza'!L7),"",'Proveitos por Natureza'!L7) -> 3.0629189e+09 | F62: =IF(ISERROR('Proveitos por Natureza'!M7),"",'Proveitos por Natureza'!M7) | G62: =IF(ISERROR('Proveitos por Natureza'!J12),"",'Proveitos por Natureza'!J12) -> 3.8 | H62: =IF(ISERROR('Proveitos por Natureza'!K12),"",'Proveitos por Natureza'!K12) -> Outros Proveitos e Ganhos não Operacionais | I62: =IF(ISERROR('Proveitos por Natureza'!L12),"",'Proveitos por Natureza'!L12) -> 25000000 | J62: =IF(ISERROR('Proveitos por Natureza'!M12),"",'Proveitos por Natureza'!M12)
C63: =IF(ISERROR('Proveitos por Natureza'!J8),"",'Proveitos por Natureza'!J8) -> 3.4 | D63: =IF(ISERROR('Proveitos por Natureza'!K8),"",'Proveitos por Natureza'!K8) -> Varição nos Produtos Acabados e Produtos em Vias de Fabrico | E63: =IF(ISERROR('Proveitos por Natureza'!L8),"",'Proveitos por Natureza'!L8) -> 0 | F63: =IF(ISERROR('Proveitos por Natureza'!M8),"",'Proveitos por Natureza'!M8) | G63: =IF(ISERROR('Proveitos por Natureza'!J13),"",'Proveitos por Natureza'!J13) -> 3.9 | H63: =IF(ISERROR('Proveitos por Natureza'!K13),"",'Proveitos por Natureza'!K13) -> Proveitos e Ganhos Extraordinários | I63: =IF(ISERROR('Proveitos por Natureza'!L13),"",'Proveitos por Natureza'!L13) -> 0 | J63: =IF(ISERROR('Proveitos por Natureza'!M13),"",'Proveitos por Natureza'!M13)
C64: =IF(ISERROR('Proveitos por Natureza'!J9),"",'Proveitos por Natureza'!J9) -> 3.5 | D64: =IF(ISERROR('Proveitos por Natureza'!K9),"",'Proveitos por Natureza'!K9) -> Trabalhos para a Própria Empresa | E64: =IF(ISERROR('Proveitos por Natureza'!L9),"",'Proveitos por Natureza'!L9) -> 0 | F64: =IF(ISERROR('Proveitos por Natureza'!M9),"",'Proveitos por Natureza'!M9) | G64: =IF(ISERROR('Proveitos por Natureza'!J16),"",'Proveitos por Natureza'!J16) -> Total | I64: =IF(ISERROR('Proveitos por Natureza'!L16),"",'Proveitos por Natureza'!L16) -> 4.8672211e+09
C66: 5 - CUSTOS POR NATUREZA - DRE
C67: 4 | D67: Contas de Custos e Perdas por Natureza - Total
C68: =IF(ISERROR('Custos por Natureza'!J5),"",'Custos por Natureza'!J5) -> 4.1 | D68: =IF(ISERROR('Custos por Natureza'!K5),"",'Custos por Natureza'!K5) -> Custo das Mercadorias Vendidas e das Matérias-primas Consumidas | E68: =IF(ISERROR('Custos por Natureza'!L5),"",'Custos por Natureza'!L5) -> 1.7968478e+08 | F68: =IF(ISERROR('Custos por Natureza'!M5),"",'Custos por Natureza'!M5) | G68: =IF(ISERROR('Custos por Natureza'!J10),"",'Custos por Natureza'!J10) -> 4.6 | H68: =IF(ISERROR('Custos por Natureza'!K10),"",'Custos por Natureza'!K10) -> Custos e Perdas Financeiras para Filiais e Associadas | I68: =IF(ISERROR('Custos por Natureza'!L10),"",'Custos por Natureza'!L10) -> 0 | J68: =IF(ISERROR('Custos por Natureza'!M10),"",'Custos por Natureza'!M10)
C69: =IF(ISERROR('Custos por Natureza'!J6),"",'Custos por Natureza'!J6) -> 4.2 | D69: =IF(ISERROR('Custos por Natureza'!K6),"",'Custos por Natureza'!K6) -> Custos com o Pessoal | E69: =IF(ISERROR('Custos por Natureza'!L6),"",'Custos por Natureza'!L6) -> 3.3178513e+09 | F69: =IF(ISERROR('Custos por Natureza'!M6),"",'Custos por Natureza'!M6) | G69: =IF(ISERROR('Custos por Natureza'!J11),"",'Custos por Natureza'!J11) -> 4.7 | H69: =IF(ISERROR('Custos por Natureza'!K11),"",'Custos por Natureza'!K11) -> Outros Custos e Perdas não Operacionais | I69: =IF(ISERROR('Custos por Natureza'!L11),"",'Custos por Natureza'!L11) -> 1.0194258e+09 | J69: =IF(ISERROR('Custos por Natureza'!M11),"",'Custos por Natureza'!M11)
C70: =IF(ISERROR('Custos por Natureza'!J7),"",'Custos por Natureza'!J7) -> 4.3 | D70: =IF(ISERROR('Custos por Natureza'!K7),"",'Custos por Natureza'!K7) -> Amortizações do Exercício | E70: =IF(ISERROR('Custos por Natureza'!L7),"",'Custos por Natureza'!L7) -> 5.0839795e+08 | F70: =IF(ISERROR('Custos por Natureza'!M7),"",'Custos por Natureza'!M7) | G70: =IF(ISERROR('Custos por Natureza'!J12),"",'Custos por Natureza'!J12) -> 4.8 | H70: =IF(ISERROR('Custos por Natureza'!K12),"",'Custos por Natureza'!K12) -> Custos e Perdas Extraordinários | I70: =IF(ISERROR('Custos por Natureza'!L12),"",'Custos por Natureza'!L12) -> 0 | J70: =IF(ISERROR('Custos por Natureza'!M12),"",'Custos por Natureza'!M12)
C71: =IF(ISERROR('Custos por Natureza'!J8),"",'Custos por Natureza'!J8) -> 4.4 | D71: =IF(ISERROR('Custos por Natureza'!K8),"",'Custos por Natureza'!K8) -> Outros Custos e Perdas Operacionais | E71: =IF(ISERROR('Custos por Natureza'!L8),"",'Custos por Natureza'!L8) -> 1.5001827e+09 | F71: =IF(ISERROR('Custos por Natureza'!M8),"",'Custos por Natureza'!M8) | G71: =IF(ISERROR('Custos por Natureza'!J13),"",'Custos por Natureza'!J13) -> 0 | H71: =IF(ISERROR('Custos por Natureza'!K13),"",'Custos por Natureza'!K13) -> 0 | I71: =IF(ISERROR('Custos por Natureza'!L13),"",'Custos por Natureza'!L13) -> 0 | J71: =IF(ISERROR('Custos por Natureza'!M13),"",'Custos por Natureza'!M13)
C72: =IF(ISERROR('Custos por Natureza'!J9),"",'Custos por Natureza'!J9) -> 4.5 | D72: =IF(ISERROR('Custos por Natureza'!K9),"",'Custos por Natureza'!K9) -> Custos e Perdas Financeiras Gerais | E72: =IF(ISERROR('Custos por Natureza'!L9),"",'Custos por Natureza'!L9) -> 15878780 | F72: =IF(ISERROR('Custos por Natureza'!M9),"",'Custos por Natureza'!M9) | G72: =IF(ISERROR('Custos por Natureza'!J16),"",'Custos por Natureza'!J16) -> Total | I72: =IF(ISERROR('Custos por Natureza'!L16),"",'Custos por Natureza'!L16) -> 6.5414213e+09
C74: 6 - DEMONSTRAÇÃO DE RESULTADO DE EXERCÍCIO (DRE)
C75: Demonstração do Resultado do Exercício (DRE)
C76: Receitas | E76: =IF(ISERROR(DRE!E17),"",DRE!E17) -> 4.8672211e+09 | F76: =IF(ISERROR(DRE!F17),"",DRE!F17) -> 0.42662579
C77: Custos e Despesas | E77: =IF(ISERROR(DRE!E18),"",DRE!E18) -> 6.5414213e+09 | F77: =IF(ISERROR(DRE!F18),"",DRE!F18) -> 0.57337421
C78: Resultado do Exercício | E78: =IF(ISERROR(DRE!E19),"",DRE!E19) -> -1.6742002e+09
C80: 7 - GRÁFICOS
C81: Activos Correntes
C94: Activos não Correntes
C107: Passivo Corrente
C120: Passivo Não Corrente
C133: Balanço Patrimonial
C143: Balanço Patrimonial
C152: Proveitos
C165: Custos
C178: DRE
C187: DRE

Sheet 311231223
